Workbook

Sheet Léeme
A1: Catálogo de partidas Enzyme — Reforma de vivienda (España)
A2: Versión 1 · base de precios: presupuesto Ortega y Gasset 47 (P26018, REV 2) · precios en € sin IVA
A4: Cómo está organizado
A5: • Capítulos por gremio, cada uno referido a un capítulo del Generador de Precios de CYPE (Rehabilitación).
A6: • Un código = una partida con precio unitario. Los códigos no cambian de significado; una especificación nueva lleva código nuevo.
A7: • Todas las partidas son 'todo incluido' (suministro + colocación) en la calidad estándar Enzyme.
A8: • Fase de oferta: solo estándar, sin opciones ni peticiones del cliente. Las alternativas (tarima, PVC, gran altura…) son partidas del catálogo para después del contrato.
A10: Hojas
A11: • Capítulos: estructura y correspondencia con CYPE.
A12: • Partidas: catálogo con precio Enzyme y de dónde sale cada precio.
A13: • Plantillas: estancias tipo. Cantidad = factor × tamaño + fijo.
A14: • Calculadora: estancias y m² → presupuesto por capítulos. Ejemplo con superficies aproximadas; ajústelas.
... A31: • Electricidad por estancia: Las estancias pasan a la medición; las partidas son unitarias (ELE-020 a ELE-090).

Sheet Capítulos
A1: Código | B1: Capítulo | C1: Capítulo CYPE | D1: Orden | E1: Nº partidas
A3: PRE | B3: Actuaciones previas y medios auxiliares | C3: 0 | D3: 10 | E3: =COUNTIF(Partidas!$B:$B,A3) -> 4
A4: DEM | B4: Demoliciones y desmontajes | C4: D | D4: 20 | E4: =COUNTIF(Partidas!$B:$B,A4) -> 12
A5: TAB | B5: Tabiquería y trasdosados | C5: F | D5: 30 | E5: =COUNTIF(Partidas!$B:$B,A5) -> 3
A6: TEC | B6: Falsos techos y molduras | C6: R | D6: 40 | E6: =COUNTIF(Partidas!$B:$B,A6) -> 5
A7: IMP | B7: Aislamientos e impermeabilizaciones | C7: N | D7: 50 | E7: =COUNTIF(Partidas!$B:$B,A7) -> 3
A8: REV | B8: Revestimientos de paredes | C8: R | D8: 60 | E8: =COUNTIF(Partidas!$B:$B,A8) -> 5
A9: PAV | B9: Pavimentos y rodapiés | C9: R | D9: 70 | E9: =COUNTIF(Partidas!$B:$B,A9) -> 6
A10: CEX | B10: Carpintería exterior y protecciones solares | C10: L | D10: 80 | E10: =COUNTIF(Partidas!$B:$B,A10) -> 4
A11: CIN | B11: Carpintería interior y mobiliario a medida | C11: L | D11: 90 | E11: =COUNTIF(Partidas!$B:$B,A11) -> 6
A12: FON | B12: Fontanería y saneamiento | C12: I | D12: 100 | E12: =COUNTIF(Partidas!$B:$B,A12) -> 5
A13: SAN | B13: Sanitarios, grifería y equipamiento de baño | C13: I | D13: 110 | E13: =COUNTIF(Partidas!$B:$B,A13) -> 12
A14: COC | B14: Cocina | C14: S | D14: 120 | E14: =COUNTIF(Partidas!$B:$B,A14) -> 3
... A22: LIM | B22: Limpieza y entrega | C22: H | D22: 200 | E22: =COUNTIF(Partidas!$B:$B,A22) -> 1

Sheet Partidas
A1: Código | B1: Capítulo | C1: Ud | D1: Descripción | E1: Especificación estándar Enzyme | F1: Precio Enzyme (€/ud) | G1: Base del precio | H1: Ref. CYPE | I1: Estado
A3: PRE-010 | B3: PRE | C3: pa | D3: Protección de zonas comunes y elementos que se conservan | E3: Protección de portal, ascensor, rellanos, carpinterías y pavimentos que se conservan durante toda la obra, con retirada al final. | G3: OG47 LFO1 la incluye junto a la limpieza final (ver LIM-010) | I3: =IF(F3="","Sin precio","Con precio") -> Sin precio
A4: PRE-020 | B4: PRE | C4: pa | D4: Comunicación a la comunidad y gestión de ascensor/montacargas | E4: Aviso a la comunidad de propietarios, horarios de obra, reserva y protección de ascensor o montacargas para acopios. | I4: =IF(F4="","Sin precio","Con precio") -> Sin precio
A5: PRE-030 | B5: PRE | C5: pa | D5: Medios de elevación para carpintería exterior | E5: Plataforma elevadora, grúa o medio equivalente para subida de carpinterías y vidrios que no caben por escalera o ascensor, incluso permisos de vía pública. | I5: =IF(F5="","Sin precio","Con precio") -> Sin precio
A6: PRE-040 | B6: PRE | C6: pa | D6: Gestión de licencia o declaración responsable | E6: Tramitación ante el ayuntamiento de la licencia o declaración responsable que corresponda. Tasas e ICIO a cargo de la propiedad, fuera de esta partida. | I6: =IF(F6="","Sin precio","Con precio") -> Sin precio
A7: DEM-010 | B7: DEM | C7: pa | D7: Desmontaje de mobiliario existente | E7: Desmontaje de armarios, muebles de cocina y baño y estanterías, con carga y transporte a contenedor de lo no reutilizable. | F7: 500 | G7: OG47 DMC1 | I7: =IF(F7="","Sin precio","Con precio") -> Con precio
A8: DEM-020 | B8: DEM | C8: ud | D8: Desmontaje de carpintería exterior | E8: Desmontaje de hoja y marco de ventana o balconera existente, con retirada a contenedor y hueco preparado para la nueva carpintería. | F8: 32 | G8: OG47 DCE1 | I8: =IF(F8="","Sin precio","Con precio") -> Con precio
A9: DEM-030 | B9: DEM | C9: m2 | D9: Ajuste de hueco en fachada (ampliación o reducción) | E9: Demolición puntual de fábrica para modificar un hueco, repicado, corte de jambas, recibido y enfoscado de mochetas. Medición por m² de hueco intervenido. | F9: 24 | G9: OG47 DFHV | I9: =IF(F9="","Sin precio","Con precio") -> Con precio
A10: DEM-040 | B10: DEM | C10: m2 | D10: Demolición de tabique de placa de yeso laminado | E10: Demolición de tabique de PYL incluida perfilería y aislamiento, con carga a contenedor. | F10: 16 | G10: OG47 (sin código) | I10: =IF(F10="","Sin precio","Con precio") -> Con precio
A11: DEM-050 | B11: DEM | C11: m2 | D11: Demolición de tabique de ladrillo | E11: Demolición de tabique de ladrillo hueco con revestimientos, con carga a contenedor. | I11: =IF(F11="","Sin precio","Con precio") -> Sin precio
A12: DEM-060 | B12: DEM | C12: m2 | D12: Demolición de falso techo de PYL o escayola | E12: Demolición de falso techo incluida estructura de cuelgue, con carga a contenedor. | F12: 10 | G12: OG47 (sin código) | I12: =IF(F12="","Sin precio","Con precio") -> Con precio
A13: DEM-070 | B13: DEM | C13: ud | D13: Desmontaje de radiador | E13: Desmontaje de radiador, vaciado y purgado del circuito y taponado de tomas. | F13: 60 | G13: OG47 DRAD | I13: =IF(F13="","Sin precio","Con precio") -> Con precio
A14: DEM-080 | B14: DEM | C14: m2 | D14: Levantado de pavimento de madera, laminado o vinílico | E14: Levantado de tarima, parquet, laminado o vinílico con rastreles y adhesivos, con carga a contenedor. | F14: 18 | G14: OG47 LS | I14: =IF(F14="","Sin precio","Con precio") -> Con precio
A15: DEM-090 | B15: DEM | C15: m2 | D15: Picado de alicatado y solado cerámico | E15: Picado de revestimiento cerámico en paredes y suelos hasta soporte, con carga a contenedor. | F15: 28 | G15: OG47 LS (picado) | I15: =IF(F15="","Sin precio","Con precio") -> Con precio
A16: DEM-100 | B16: DEM | C16: ud | D16: Desmontaje de aparato sanitario o grifería | E16: Desmontaje de inodoro, lavabo, bañera, plato o grifería, con anulación de tomas y retirada. | I16: =IF(F16="","Sin precio","Con precio") -> Sin precio
A17: DEM-110 | B17: DEM | C17: ud | D17: Desmontaje de puerta interior | E17: Desmontaje de hoja, cerco y tapajuntas de puerta interior, con retirada. | I17: =IF(F17="","Sin precio","Con precio") -> Sin precio
A18: DEM-120 | B18: DEM | C18: pa | D18: Levantado de instalaciones existentes | E18: Levantado de instalación eléctrica, fontanería y calefacción que se sustituyen, con retirada. | I18: =IF(F18="","Sin precio","Con precio") -> Sin precio
A19: TAB-010 | B19: TAB | C19: m2 | D19: Tabique PYL 2 placas por cara con aislamiento | E19: Tabique de placa de yeso laminado sobre perfilería de 70 mm, 2 placas por cara (hidrófuga en zonas húmedas), lana mineral, juntas tratadas listo para pintar. | F19: 60 | G19: OG47 TP2PA | I19: =IF(F19="","Sin precio","Con precio") -> Con precio
A20: TAB-020 | B20: TAB | C20: m2 | D20: Trasdosado PYL 1 placa sobre perfilería con aislamiento | E20: Trasdosado de una placa sobre perfilería autoportante con lana mineral, juntas tratadas. | F20: 40 | G20: OG47 TA | I20: =IF(F20="","Sin precio","Con precio") -> Con precio
A21: TAB-030 | B21: TAB | C21: m2 | D21: Trasdosado PYL 1 placa directo | E21: Trasdosado directo de placa adherida al paramento con pasta de agarre, juntas tratadas. | F21: 30 | G21: OG47 TA (pegado) | I21: =IF(F21="","Sin precio","Con precio") -> Con precio
A22: TEC-010 | B22: TEC | C22: m2 | D22: Falso techo continuo PYL | E22: Falso techo continuo de placa de yeso laminado tipo N sobre estructura metálica, juntas tratadas listo para pintar. | F22: 30 | G22: OG47 FTYN | I22: =IF(F22="","Sin precio","Con precio") -> Con precio
A23: TEC-020 | B23: TEC | C23: m2 | D23: Falso techo continuo PYL hidrófugo | E23: Falso techo continuo de placa hidrófuga en baños, aseos, cocina y lavandería. | F23: 32 | G23: OG47 FTWA | I23: =IF(F23="","Sin precio","Con precio") -> Con precio
A24: TEC-030 | B24: TEC | C24: m | D24: Candileja o foseado perimetral para LED | E24: Cajeado perimetral en falso techo para tira LED (suministro en ILU), juntas tratadas. | F24: 40 | G24: OG47 CP1 | I24: =IF(F24="","Sin precio","Con precio") -> Con precio
A25: TEC-040 | B25: TEC | C25: m | D25: Moldura decorativa de escayola | E25: Suministro y colocación de moldura de escayola techo-pared, ingletes y juntas, lista para pintar. Modelo estándar. | F25: 20 | G25: OG47 ESC S 10 + ESC I 10 | I25: =IF(F25="","Sin precio","Con precio") -> Con precio
A26: TEC-050 | B26: TEC | C26: ud | D26: Registro en falso techo | E26: Trampilla de registro de PYL para acceso a instalaciones. | I26: =IF(F26="","Sin precio","Con precio") -> Sin precio
A27: IMP-010 | B27: IMP | C27: m2 | D27: Impermeabilización de suelo en zona húmeda | E27: Membrana impermeabilizante bajo solado en baños, aseos y lavandería, con banda perimetral y remate en encuentros. | I27: =IF(F27="","Sin precio","Con precio") -> Sin precio
A28: IMP-020 | B28: IMP | C28: ud | D28: Desagüe lineal y manta impermeable para ducha de obra | E28: Canaleta de desagüe lineal y manta impermeabilizante para ducha a nivel de suelo, suministro e instalación. | F28: 340 | G28: OG47 IDD 180 + IDD 160 | I28: =IF(F28="","Sin precio","Con precio") -> Con precio
A29: IMP-030 | B29: IMP | C29: m2 | D29: Lámina anti-impacto bajo pavimento | E29: Lámina acústica de polietileno reticulado bajo recrecido o pavimento flotante. | I29: =IF(F29="","Sin precio","Con precio") -> Sin precio
A30: REV-010 | B30: REV | C30: m2 | D30: Alicatado de gres porcelánico | E30: Suministro (gama estándar Enzyme) y colocación con adhesivo C2 y doble encolado, rejuntado, cortes e ingletes. Incluye 10 % de desperdicio. | F30: 90 | G30: OG47 PCA 40 + PS 45 × 43/38,9 m² = 89,7 | I30: =IF(F30="","Sin precio","Con precio") -> Con precio
A31: REV-020 | B31: REV | C31: m2 | D31: Enlucido o alisado de paredes | E31: Regularización de paramentos tras demoliciones con guarnecido y enlucido de yeso o alisado, listo para pintar. | I31: =IF(F31="","Sin precio","Con precio") -> Sin precio
A32: REV-030 | B32: REV | C32: m | D32: Moldura de pared tipo boiserie | E32: Suministro y colocación de moldura de PVC o HDPS sobre pared lisa formando paños, lista para pintar. | F32: 20 | G32: OG47 PM 10 + PM 10 | I32: =IF(F32="","Sin precio","Con precio") -> Con precio
A33: REV-040 | B33: REV | C33: m2 | D33: Espejo decorativo en pared | E33: Suministro y colocación de espejo con adhesivo específico y canteado de bordes. | F33: 80 | G33: OG47 OTRO5 (espejos salón) | I33: =IF(F33="","Sin precio","Con precio") -> Con precio
A34: REV-050 | B34: REV | C34: m | D34: Viga decorativa imitación madera | E34: Suministro y colocación de viga decorativa imitación madera con foseado y remates. | F34: 95 | G34: OG47 OTRO5 (vigas) | I34: =IF(F34="","Sin precio","Con precio") -> Con precio
A35: PAV-010 | B35: PAV | C35: m2 | D35: Recrecido de mortero autonivelante | E35: Recrecido con mortero autonivelante para regularizar el soporte, espesor según obra. | F35: 30 | G35: OG47 OTRO1 | I35: =IF(F35="","Sin precio","Con precio") -> Con precio
A36: PAV-020 | B36: PAV | C36: m2 | D36: Solado de gres porcelánico | E36: Suministro (gama estándar Enzyme) y colocación con adhesivo C2, rejuntado y cortes. Incluye 10 % de desperdicio. | F36: 86 | G36: OG47 PCS 35 + PS 45 × 12/10,5 m² = 86,4 | I36: =IF(F36="","Sin precio","Con precio") -> Con precio
A37: PAV-030 | B37: PAV | C37: m2 | D37: Suelo laminado flotante | E37: Suministro (gama estándar Enzyme, AC4) y colocación flotante sobre lámina, remates y juntas de dilatación. Incluye 10 % de desperdicio. | F37: 78 | G37: OG47 PS B 50 × 85/79 m² + PCS 24 = 77,8 (en espiga húngara) | I37: =IF(F37="","Sin precio","Con precio") -> Con precio
A38: PAV-040 | B38: PAV | C38: m2 | D38: Tarima de madera natural | E38: Suministro e instalación por instalador especializado de tarima de madera natural, acabado barnizado o aceitado. | F38: 120 | G38: OG47 PS A | I38: =IF(F38="","Sin precio","Con precio") -> Con precio
A39: PAV-050 | B39: PAV | C39: m2 | D39: Suelo vinílico SPC | E39: Suministro y colocación de suelo vinílico SPC con sistema click. | F39: 54 | G39: OG47 PS C 30 + PCS 24 | I39: =IF(F39="","Sin precio","Con precio") -> Con precio
A40: PAV-060 | B40: PAV | C40: m | D40: Rodapié lacado blanco 20 cm | E40: Suministro y colocación de rodapié blanco de 20 cm con adhesivo y/o clavado, juntas selladas. | F40: 18.75 | G40: OG47 PRE 10,75 + PCR 8 | I40: =IF(F40="","Sin precio","Con precio") -> Con precio
A41: CEX-010 | B41: CEX | C41: ud | D41: Ventana de aluminio con rotura de puente térmico | E41: Suministro y colocación de ventana de aluminio RPT, oscilobatiente, acabado blanco, doble acristalamiento bajo emisivo, herrajes, recibido y sellado. Tamaño medio de vivienda. | F41: 1052 | G41: OG47 OTRO2 A 9.470 € / 9 ventanas | I41: =IF(F41="","Sin precio","Con precio") -> Con precio
A42: CEX-020 | B42: CEX | C42: ud | D42: Ventana de PVC | E42: Suministro y colocación de ventana de PVC, oscilobatiente, blanco, doble acristalamiento bajo emisivo, herrajes, recibido y sellado. Tamaño medio de vivienda. | F42: 722 | G42: OG47 OTRO2 B 6.495 € / 9 ventanas | I42: =IF(F42="","Sin precio","Con precio") -> Con precio
A43: CEX-030 | B43: CEX | C43: ud | D43: Persiana enrollable motorizada con cajón | E43: Persiana de aluminio con cajón compacto o rehabilitación del existente, motor y mando. | I43: =IF(F43="","Sin precio","Con precio") -> Sin precio
A44: CEX-040 | B44: CEX | C44: ud | D44: Puerta de entrada blindada | E44: Suministro y colocación de puerta de entrada blindada con cerradura de seguridad, acabado interior a juego con carpintería. | I44: =IF(F44="","Sin precio","Con precio") -> Sin precio
A45: CIN-010 | B45: CIN | C45: ud | D45: Puerta de paso abatible, altura estándar | E45: Suministro y colocación de puerta lacada blanca de 203 cm con precerco, cerco, tapajuntas, herrajes y manilla estándar. | F45: 495 | G45: OG47 PIA1 A 295 + PCM1 50 + CPIA 150 | I45: =IF(F45="","Sin precio","Con precio") -> Con precio
A46: CIN-020 | B46: CIN | C46: ud | D46: Puerta de paso abatible, gran altura | E46: Como CIN-010 con hoja de 260 cm. | F46: 1160 | G46: OG47 PIA1 B 960 + PCM1 50 + CPIA 150 | I46: =IF(F46="","Sin precio","Con precio") -> Con precio
A47: CIN-030 | B47: CIN | C47: ud | D47: Puerta corredera con casoneto | E47: Suministro y montaje de puerta corredera con casoneto empotrado en tabique, guía, herrajes, tapajuntas y manivela embutida. | F47: 420 | G47: OG47 PCST1 | I47: =IF(F47="","Sin precio","Con precio") -> Con precio
A48: CIN-040 | B48: CIN | C48: m2 | D48: Armario empotrado de suelo a techo | E48: Suministro y montaje de armario con interior de barras y cajoneras, LED interior y puertas lacadas. Medición por m² de frente. | F48: 450 | G48: OG47 AE | I48: =IF(F48="","Sin precio","Con precio") -> Con precio
A49: CIN-050 | B49: CIN | C49: m2 | D49: Estantería o librería a medida | E49: Suministro y montaje de estantería a medida con iluminación LED. Medición por m² de frente. | F49: 450 | G49: OG47 AE (estantería) | I49: =IF(F49="","Sin precio","Con precio") -> Con precio
A50: CIN-060 | B50: CIN | C50: m2 | D50: Mueble de lavandería | E50: Suministro y montaje de mueble torre para lavadora y secadora con accesorios. Medición por m² de frente. | F50: 320 | G50: OG47 MA (lavandería) | I50: =IF(F50="","Sin precio","Con precio") -> Con precio
A51: FON-010 | B51: FON | C51: ud | D51: Punto de agua fría y caliente | E51: Red de fontanería en multicapa hasta punto de consumo, con rozas. El inodoro cuenta como medio punto. | F51: 120 | G51: OG47 FIF1 | I51: =IF(F51="","Sin precio","Con precio") -> Con precio
A52: FON-020 | B52: FON | C52: ud | D52: Punto de desagüe | E52: Red de saneamiento en PVC serie B desde aparato hasta bajante, con rozas y pendientes según CTE DB-HS5. | F52: 60 | G52: OG47 FRS | I52: =IF(F52="","Sin precio","Con precio") -> Con precio
A53: FON-030 | B53: FON | C53: ud | D53: Bote sifónico | E53: Bote sifónico registrable empotrado, conexiones y tapa. | F53: 75 | G53: OG47 FBS | I53: =IF(F53="","Sin precio","Con precio") -> Con precio
A54: FON-040 | B54: FON | C54: ud | D54: Llave de corte por estancia húmeda | E54: Llaves de corte de agua fría y caliente en cada baño, aseo y cocina. | I54: =IF(F54="","Sin precio","Con precio") -> Sin precio
A55: FON-050 | B55: FON | C55: pa | D55: Pruebas de presión y estanqueidad | E55: Pruebas de la red de fontanería y saneamiento con acta. | I55: =IF(F55="","Sin precio","Con precio") -> Sin precio
A56: SAN-010 | B56: SAN | C56: ud | D56: Plato de ducha | E56: Suministro (resina o porcelánico, gama estándar Enzyme) e instalación nivelada con conexión a desagüe. | F56: 640 | G56: OG47 PD 550 + IPD 90 (plato 80×200) | I56: =IF(F56="","Sin precio","Con precio") -> Con precio
A57: SAN-020 | B57: SAN | C57: ud | D57: Bañera | E57: Suministro (acrílica 160×70, gama estándar Enzyme) e instalación nivelada con conexiones. | F57: 850 | G57: OG47 FB 700 + FIB 150 | I57: =IF(F57="","Sin precio","Con precio") -> Con precio
A58: SAN-030 | B58: SAN | C58: ud | D58: Inodoro suspendido con bastidor | E58: Suministro de inodoro suspendido (tipo Roca Meridian o similar) y bastidor con cisterna empotrada, montaje y pulsador. | F58: 850 | G58: OG47 FIS 650 + IIS 200 | I58: =IF(F58="","Sin precio","Con precio") -> Con precio
A59: SAN-040 | B59: SAN | C59: ud | D59: Mueble de baño con lavabo | E59: Suministro de mueble de 60–80 cm con lavabo integrado (gama estándar Enzyme) y montaje. | F59: 420 | G59: OG47 MA 300 + IMB 120 | I59: =IF(F59="","Sin precio","Con precio") -> Con precio
A60: SAN-050 | B60: SAN | C60: ud | D60: Grifería de lavabo | E60: Suministro de grifo monomando (gama estándar Enzyme) e instalación. | F60: 255 | G60: OG47 GB 200 + IGL 55 | I60: =IF(F60="","Sin precio","Con precio") -> Con precio
A61: SAN-060 | B61: SAN | C61: ud | D61: Grifería termostática de ducha o bañera | E61: Suministro de conjunto termostático con rociador (gama estándar Enzyme) e instalación. | F61: 255 | G61: OG47 GB 200 + IGD 55 | I61: =IF(F61="","Sin precio","Con precio") -> Con precio
A62: SAN-070 | B62: SAN | C62: ud | D62: Mampara fija de ducha | E62: Suministro de panel fijo de vidrio templado de 120–130 cm e instalación con perfilería y sellado. | F62: 420 | G62: OG47 FM 300 + IM 120 | I62: =IF(F62="","Sin precio","Con precio") -> Con precio
A63: SAN-080 | B63: SAN | C63: ud | D63: Mampara de bañera | E63: Suministro de mampara lateral de vidrio templado para bañera e instalación. | F63: 320 | G63: OG47 FM 200 + IM 120 | I63: =IF(F63="","Sin precio","Con precio") -> Con precio
A64: SAN-090 | B64: SAN | C64: m2 | D64: Espejo de baño a medida | E64: Suministro y colocación de espejo con canteado y fijación oculta. | F64: 70 | G64: OG47 FE | I64: =IF(F64="","Sin precio","Con precio") -> Con precio
A65: SAN-100 | B65: SAN | C65: ud | D65: Toallero eléctrico | E65: Suministro de toallero eléctrico (gama estándar Enzyme) y conexión. | F65: 250 | G65: OG47 ITE BS 200 + ITE 50 | I65: =IF(F65="","Sin precio","Con precio") -> Con precio
A66: SAN-110 | B66: SAN | C66: ud | D66: Toallero-radiador de agua | E66: Suministro de toallero-radiador y conexión a la calefacción (2 puntos), purgado. | G66: OG47 IRA: solo instalación 180 € | I66: =IF(F66="","Sin precio","Con precio") -> Sin precio
A67: SAN-120 | B67: SAN | C67: ud | D67: Juego de accesorios de baño | E67: Portarrollos, toallero de lavabo y percha (gama estándar Enzyme), suministro y colocación. | I67: =IF(F67="","Sin precio","Con precio") -> Sin precio
A68: COC-010 | B68: COC | C68: m | D68: Mobiliario de cocina con encimera | E68: Suministro y montaje de muebles bajos y altos (gama estándar Enzyme) con encimera de porcelánico o compacto. Medición por metro lineal de frente. | G68: OG47: lo compró la propiedad | I68: =IF(F68="","Sin precio","Con precio") -> Sin precio
A69: COC-020 | B69: COC | C69: pa | D69: Montaje de cocina suministrada por la propiedad | E69: Montaje de muebles, encimera y fregadero suministrados por la propiedad. | I69: =IF(F69="","Sin precio","Con precio") -> Sin precio
A70: COC-030 | B70: COC | C70: pa | D70: Conexión de electrodomésticos y fregadero | E70: Conexión de fregadero, lavavajillas, placa, horno, campana y frigorífico a sus instalaciones. | I70: =IF(F70="","Sin precio","Con precio") -> Sin precio
A71: ELE-010 | B71: ELE | C71: pa | D71: Instalación eléctrica: cuadro, circuitos y boletín | E71: Adecuación a REBT: cuadro nuevo con protecciones, circuitos independientes por usos, cableado y tubos, cajas, certificado de instalación (CIE). | F71: 2850 | G71: OG47 E-AIE | I71: =IF(F71="","Sin precio","Con precio") -> Con precio
A72: ELE-020 | B72: ELE | C72: ud | D72: Punto de luz sencillo | E72: Un interruptor y un punto de luz, cableado y mecanismo de gama estándar. | F72: 50 | G72: OG47 regla 35 €/mecanismo + 15 € primer punto | I72: =IF(F72="","Sin precio","Con precio") -> Con precio
A73: ELE-030 | B73: ELE | C73: ud | D73: Punto de luz adicional en el mismo circuito | E73: Punto de luz adicional gobernado por un mecanismo ya contado. | F73: 10 | G73: OG47 regla 10 €/punto adicional | I73: =IF(F73="","Sin precio","Con precio") -> Con precio
A74: ELE-040 | B74: ELE | C74: ud | D74: Punto de luz conmutado | E74: Dos conmutadores y un punto de luz. | F74: 85 | G74: OG47 regla 35 + 35 + 15 | I74: =IF(F74="","Sin precio","Con precio") -> Con precio
A75: ELE-050 | B75: ELE | C75: ud | D75: Punto de luz de cruce | E75: Dos conmutadores, un cruzamiento y un punto de luz. | F75: 120 | G75: OG47 regla 35 + 35 + 35 + 15 | I75: =IF(F75="","Sin precio","Con precio") -> Con precio
A76: ELE-060 | B76: ELE | C76: ud | D76: Toma de corriente | E76: Base de enchufe 16 A con cableado y mecanismo de gama estándar. | F76: 45 | G76: OG47 E-TC | I76: =IF(F76="","Sin precio","Con precio") -> Con precio
A77: ELE-070 | B77: ELE | C77: ud | D77: Toma de corriente con cargador USB-C | E77: Base de enchufe con cargador USB-C integrado. | F77: 90 | G77: OG47 E-TC (USB-C) | I77: =IF(F77="","Sin precio","Con precio") -> Con precio
A78: ELE-080 | B78: ELE | C78: ud | D78: Toma de TV o datos | E78: Toma de TV o RJ45 con canalización desde registro. | F78: 45 | G78: OG47 E-TC (TV/datos) | I78: =IF(F78="","Sin precio","Con precio") -> Con precio
A79: ELE-090 | B79: ELE | C79: ud | D79: Toma para electrodoméstico | E79: Toma en circuito específico para horno, placa, lavadora, lavavajillas o secadora. | F79: 45 | G79: OG47 E-TC (electrodomésticos) | I79: =IF(F79="","Sin precio","Con precio") -> Con precio
A80: ELE-100 | B80: ELE | C80: ud | D80: Mecanismo de persiana motorizada | E80: Interruptor de subida y bajada para motor de persiana, con cableado. | F80: 45 | G80: OG47 E-IP | I80: =IF(F80="","Sin precio","Con precio") -> Con precio
A81: ELE-110 | B81: ELE | C81: ud | D81: Timbre | E81: Pulsador y zumbador con cableado. | F81: 65 | G81: OG47 E-ZT | I81: =IF(F81="","Sin precio","Con precio") -> Con precio
A82: ELE-120 | B82: ELE | C82: ud | D82: Videoportero, terminal interior | E82: Sustitución o reubicación del terminal interior compatible con la instalación del edificio. | I82: =IF(F82="","Sin precio","Con precio") -> Sin precio
A83: ELE-130 | B83: ELE | C83: ud | D83: Detector de humo autónomo | E83: Detector óptico autónomo con batería, colocado en techo. | I83: =IF(F83="","Sin precio","Con precio") -> Sin precio
A84: ILU-010 | B84: ILU | C84: ud | D84: Aplique de pared | E84: Suministro de aplique (gama estándar Enzyme) e instalación. | G84: OG47 I-IAP: solo instalación 35 € | I84: =IF(F84="","Sin precio","Con precio") -> Sin precio
A85: ILU-020 | B85: ILU | C85: ud | D85: Downlight LED empotrado | E85: Suministro de downlight LED orientable GU10 e instalación con apertura de hueco en falso techo. | F85: 42 | G85: OG47 L-FLO 22 + I-FL 20 | I85: =IF(F85="","Sin precio","Con precio") -> Con precio
A86: ILU-030 | B86: ILU | C86: m | D86: Tira LED con perfil | E86: Suministro de tira LED con perfil de aluminio, difusor y driver, e instalación. | F86: 35 | G86: OG47 L-L 20 + I-TL 15 | I86: =IF(F86="","Sin precio","Con precio") -> Con precio
A87: ILU-040 | B87: ILU | C87: ud | D87: Baliza empotrada de pared | E87: Suministro de baliza tipo ojo de buey e instalación. | F87: 50 | G87: OG47 L-AP 15 + I-IAP 35 | I87: =IF(F87="","Sin precio","Con precio") -> Con precio
A88: CLI-010 | B88: CLI | C88: pa | D88: Adaptación de calefacción por radiadores | E88: Adaptación del circuito a la nueva distribución, radiadores, purgado, prueba y puesta en marcha. Referencia 30 € por elemento de radiador. | F88: 4200 | G88: OG47 calefacción (91 m²) | I88: =IF(F88="","Sin precio","Con precio") -> Con precio
A89: CLI-020 | B89: CLI | C89: ud | D89: Aire acondicionado multisplit 3×1 | E89: Unidad exterior y tres splits, líneas frigoríficas, condensados, conexión y puesta en marcha. | F89: 3400 | G89: OG47 aire acondicionado | I89: =IF(F89="","Sin precio","Con precio") -> Con precio
A90: CLI-030 | B90: CLI | C90: ud | D90: Extractor con conducto | E90: Extractor en baño, aseo, lavandería o cocina conectado a conducto, con temporizador. | F90: 115 | G90: OG47 IEB | I90: =IF(F90="","Sin precio","Con precio") -> Con precio
A91: CLI-040 | B91: CLI | C91: ud | D91: Conducto de campana extractora | E91: Conducto de evacuación de campana hasta shunt o fachada, con rejilla y antirretorno. | I91: =IF(F91="","Sin precio","Con precio") -> Sin precio
A92: PIN-010 | B92: PIN | C92: m2 | D92: Pintura plástica lisa en paredes | E92: Lijado, plastecido y 2–3 manos de pintura plástica lisa mate (blanco o color estándar). | F92: 9 | G92: OG47 P-PVI | I92: =IF(F92="","Sin precio","Con precio") -> Con precio
A93: PIN-020 | B93: PIN | C93: m2 | D93: Pintura plástica lisa en techos | E93: Lijado, plastecido y 2–3 manos de pintura plástica lisa mate blanca, sin marcas de juntas. | F93: 9 | G93: OG47 P-PHI | I93: =IF(F93="","Sin precio","Con precio") -> Con precio
A94: PIN-030 | B94: PIN | C94: ud | D94: Lacado de puerta o radiador existente | E94: Lijado, imprimación y lacado de elemento existente que se conserva. | I94: =IF(F94="","Sin precio","Con precio") -> Sin precio
A95: AYU-010 | B95: AYU | C95: pa | D95: Ayudas de albañilería a instalaciones | E95: Rozas, pasos, recibido de cajas y cercos, remates y acarreo a contenedor durante toda la obra. | F95: 2000 | G95: OG47 AT1 (91 m²) | I95: =IF(F95="","Sin precio","Con precio") -> Con precio
A96: RES-010 | B96: RES | C96: ud | D96: Contenedor de escombros | E96: Suministro, cambio y retirada de contenedor de RCD a gestor autorizado. | F96: 254 | G96: OG47 TP-CON | I96: =IF(F96="","Sin precio","Con precio") -> Con precio
A97: RES-020 | B97: RES | C97: pa | D97: Gestión documental de residuos | E97: Estudio de gestión de residuos y certificados del gestor, según exija la licencia. | I97: =IF(F97="","Sin precio","Con precio") -> Sin precio
A98: SYS-010 | B98: SYS | C98: pa | D98: Seguridad y salud | E98: Protecciones colectivas, EPIs, señalización y botiquín durante la obra. | I98: =IF(F98="","Sin precio","Con precio") -> Sin precio
A99: LIM-010 | B99: LIM | C99: pa | D99: Limpieza de fin de obra | E99: Limpieza general de todas las estancias y retirada de protecciones. | F99: 650 | G99: OG47 LFO1 (incluía también las protecciones de PRE-010) | I99: =IF(F99="","Sin precio","Con precio") -> Con precio

Sheet Plantillas
A1: Plantilla | B1: Estancia | C1: Tamaño en | D1: Partida | E1: Descripción | F1: Ud | G1: Factor | H1: Fijo | I1: Nota
A3: GEN | B3: Partidas generales de la vivienda | C3: m² útiles de vivienda | D3: PRE-010 | E3: =INDEX(Partidas!$D$2:$D$99,MATCH(D3,Partidas!$A$2:$A$99,0)) -> Protección de zonas comunes y elementos que se conservan | F3: =INDEX(Partidas!$C$2:$C$99,MATCH(D3,Partidas!$A$2:$A$99,0)) -> pa | G3: 0 | H3: 1
A4: GEN | B4: Partidas generales de la vivienda | C4: m² útiles de vivienda | D4: PRE-020 | E4: =INDEX(Partidas!$D$2:$D$99,MATCH(D4,Partidas!$A$2:$A$99,0)) -> Comunicación a la comunidad y gestión de ascensor/montacargas | F4: =INDEX(Partidas!$C$2:$C$99,MATCH(D4,Partidas!$A$2:$A$99,0)) -> pa | G4: 0 | H4: 1
A5: GEN | B5: Partidas generales de la vivienda | C5: m² útiles de vivienda | D5: PRE-040 | E5: =INDEX(Partidas!$D$2:$D$99,MATCH(D5,Partidas!$A$2:$A$99,0)) -> Gestión de licencia o declaración responsable | F5: =INDEX(Partidas!$C$2:$C$99,MATCH(D5,Partidas!$A$2:$A$99,0)) -> pa | G5: 0 | H5: 1
A6: GEN | B6: Partidas generales de la vivienda | C6: m² útiles de vivienda | D6: DEM-010 | E6: =INDEX(Partidas!$D$2:$D$99,MATCH(D6,Partidas!$A$2:$A$99,0)) -> Desmontaje de mobiliario existente | F6: =INDEX(Partidas!$C$2:$C$99,MATCH(D6,Partidas!$A$2:$A$99,0)) -> pa | G6: 0 | H6: 1
A7: GEN | B7: Partidas generales de la vivienda | C7: m² útiles de vivienda | D7: DEM-120 | E7: =INDEX(Partidas!$D$2:$D$99,MATCH(D7,Partidas!$A$2:$A$99,0)) -> Levantado de instalaciones existentes | F7: =INDEX(Partidas!$C$2:$C$99,MATCH(D7,Partidas!$A$2:$A$99,0)) -> pa | G7: 0 | H7: 1
A8: GEN | B8: Partidas generales de la vivienda | C8: m² útiles de vivienda | D8: ELE-010 | E8: =INDEX(Partidas!$D$2:$D$99,MATCH(D8,Partidas!$A$2:$A$99,0)) -> Instalación eléctrica: cuadro, circuitos y boletín | F8: =INDEX(Partidas!$C$2:$C$99,MATCH(D8,Partidas!$A$2:$A$99,0)) -> pa | G8: 0 | H8: 1
A9: GEN | B9: Partidas generales de la vivienda | C9: m² útiles de vivienda | D9: ELE-110 | E9: =INDEX(Partidas!$D$2:$D$99,MATCH(D9,Partidas!$A$2:$A$99,0)) -> Timbre | F9: =INDEX(Partidas!$C$2:$C$99,MATCH(D9,Partidas!$A$2:$A$99,0)) -> ud | G9: 0 | H9: 1
A10: GEN | B10: Partidas generales de la vivienda | C10: m² útiles de vivienda | D10: ELE-130 | E10: =INDEX(Partidas!$D$2:$D$99,MATCH(D10,Partidas!$A$2:$A$99,0)) -> Detector de humo autónomo | F10: =INDEX(Partidas!$C$2:$C$99,MATCH(D10,Partidas!$A$2:$A$99,0)) -> ud | G10: 0 | H10: 2
A11: GEN | B11: Partidas generales de la vivienda | C11: m² útiles de vivienda | D11: AYU-010 | E11: =INDEX(Partidas!$D$2:$D$99,MATCH(D11,Partidas!$A$2:$A$99,0)) -> Ayudas de albañilería a instalaciones | F11: =INDEX(Partidas!$C$2:$C$99,MATCH(D11,Partidas!$A$2:$A$99,0)) -> pa | G11: 0 | H11: 1
A12: GEN | B12: Partidas generales de la vivienda | C12: m² útiles de vivienda | D12: RES-010 | E12: =INDEX(Partidas!$D$2:$D$99,MATCH(D12,Partidas!$A$2:$A$99,0)) -> Contenedor de escombros | F12: =INDEX(Partidas!$C$2:$C$99,MATCH(D12,Partidas!$A$2:$A$99,0)) -> ud | G12: 0.044 | H12: 0 | I12: OG47: 4 contenedores / 91 m²
A13: GEN | B13: Partidas generales de la vivienda | C13: m² útiles de vivienda | D13: RES-020 | E13: =INDEX(Partidas!$D$2:$D$99,MATCH(D13,Partidas!$A$2:$A$99,0)) -> Gestión documental de residuos | F13: =INDEX(Partidas!$C$2:$C$99,MATCH(D13,Partidas!$A$2:$A$99,0)) -> pa | G13: 0 | H13: 1
A14: GEN | B14: Partidas generales de la vivienda | C14: m² útiles de vivienda | D14: SYS-010 | E14: =INDEX(Partidas!$D$2:$D$99,MATCH(D14,Partidas!$A$2:$A$99,0)) -> Seguridad y salud | F14: =INDEX(Partidas!$C$2:$C$99,MATCH(D14,Partidas!$A$2:$A$99,0)) -> pa | G14: 0 | H14: 1
A15: GEN | B15: Partidas generales de la vivienda | C15: m² útiles de vivienda | D15: LIM-010 | E15: =INDEX(Partidas!$D$2:$D$99,MATCH(D15,Partidas!$A$2:$A$99,0)) -> Limpieza de fin de obra | F15: =INDEX(Partidas!$C$2:$C$99,MATCH(D15,Partidas!$A$2:$A$99,0)) -> pa | G15: 0 | H15: 1
A16: DOR | B16: Dormitorio | C16: m² de suelo | D16: PAV-030 | E16: =INDEX(Partidas!$D$2:$D$99,MATCH(D16,Partidas!$A$2:$A$99,0)) -> Suelo laminado flotante | F16: =INDEX(Partidas!$C$2:$C$99,MATCH(D16,Partidas!$A$2:$A$99,0)) -> m2 | G16: 1 | H16: 0
A17: DOR | B17: Dormitorio | C17: m² de suelo | D17: PAV-060 | E17: =INDEX(Partidas!$D$2:$D$99,MATCH(D17,Partidas!$A$2:$A$99,0)) -> Rodapié lacado blanco 20 cm | F17: =INDEX(Partidas!$C$2:$C$99,MATCH(D17,Partidas!$A$2:$A$99,0)) -> m | G17: 0.9 | H17: 0 | I17: OG47: 80 m / 91 m²
A18: DOR | B18: Dormitorio | C18: m² de suelo | D18: TEC-010 | E18: =INDEX(Partidas!$D$2:$D$99,MATCH(D18,Partidas!$A$2:$A$99,0)) -> Falso techo continuo PYL | F18: =INDEX(Partidas!$C$2:$C$99,MATCH(D18,Partidas!$A$2:$A$99,0)) -> m2 | G18: 1 | H18: 0
A19: DOR | B19: Dormitorio | C19: m² de suelo | D19: PIN-010 | E19: =INDEX(Partidas!$D$2:$D$99,MATCH(D19,Partidas!$A$2:$A$99,0)) -> Pintura plástica lisa en paredes | F19: =INDEX(Partidas!$C$2:$C$99,MATCH(D19,Partidas!$A$2:$A$99,0)) -> m2 | G19: 2.4 | H19: 0 | I19: OG47: 220 m² / 91 m²
A20: DOR | B20: Dormitorio | C20: m² de suelo | D20: PIN-020 | E20: =INDEX(Partidas!$D$2:$D$99,MATCH(D20,Partidas!$A$2:$A$99,0)) -> Pintura plástica lisa en techos | F20: =INDEX(Partidas!$C$2:$C$99,MATCH(D20,Partidas!$A$2:$A$99,0)) -> m2 | G20: 1 | H20: 0
A21: DOR | B21: Dormitorio | C21: m² de suelo | D21: ELE-040 | E21: =INDEX(Partidas!$D$2:$D$99,MATCH(D21,Partidas!$A$2:$A$99,0)) -> Punto de luz conmutado | F21: =INDEX(Partidas!$C$2:$C$99,MATCH(D21,Partidas!$A$2:$A$99,0)) -> ud | G21: 0 | H21: 1
A22: DOR | B22: Dormitorio | C22: m² de suelo | D22: ELE-030 | E22: =INDEX(Partidas!$D$2:$D$99,MATCH(D22,Partidas!$A$2:$A$99,0)) -> Punto de luz adicional en el mismo circuito | F22: =INDEX(Partidas!$C$2:$C$99,MATCH(D22,Partidas!$A$2:$A$99,0)) -> ud | G22: 0 | H22: 1
A23: DOR | B23: Dormitorio | C23: m² de suelo | D23: ELE-020 | E23: =INDEX(Partidas!$D$2:$D$99,MATCH(D23,Partidas!$A$2:$A$99,0)) -> Punto de luz sencillo | F23: =INDEX(Partidas!$C$2:$C$99,MATCH(D23,Partidas!$A$2:$A$99,0)) -> ud | G23: 0 | H23: 1
A24: DOR | B24: Dormitorio | C24: m² de suelo | D24: ELE-060 | E24: =INDEX(Partidas!$D$2:$D$99,MATCH(D24,Partidas!$A$2:$A$99,0)) -> Toma de corriente | F24: =INDEX(Partidas!$C$2:$C$99,MATCH(D24,Partidas!$A$2:$A$99,0)) -> ud | G24: 0 | H24: 4
A25: DOR | B25: Dormitorio | C25: m² de suelo | D25: CIN-010 | E25: =INDEX(Partidas!$D$2:$D$99,MATCH(D25,Partidas!$A$2:$A$99,0)) -> Puerta de paso abatible, altura estándar | F25: =INDEX(Partidas!$C$2:$C$99,MATCH(D25,Partidas!$A$2:$A$99,0)) -> ud | G25: 0 | H25: 1
A26: SAL | B26: Salón-comedor | C26: m² de suelo | D26: PAV-030 | E26: =INDEX(Partidas!$D$2:$D$99,MATCH(D26,Partidas!$A$2:$A$99,0)) -> Suelo laminado flotante | F26: =INDEX(Partidas!$C$2:$C$99,MATCH(D26,Partidas!$A$2:$A$99,0)) -> m2 | G26: 1 | H26: 0
A27: SAL | B27: Salón-comedor | C27: m² de suelo | D27: PAV-060 | E27: =INDEX(Partidas!$D$2:$D$99,MATCH(D27,Partidas!$A$2:$A$99,0)) -> Rodapié lacado blanco 20 cm | F27: =INDEX(Partidas!$C$2:$C$99,MATCH(D27,Partidas!$A$2:$A$99,0)) -> m | G27: 0.9 | H27: 0
A28: SAL | B28: Salón-comedor | C28: m² de suelo | D28: TEC-010 | E28: =INDEX(Partidas!$D$2:$D$99,MATCH(D28,Partidas!$A$2:$A$99,0)) -> Falso techo continuo PYL | F28: =INDEX(Partidas!$C$2:$C$99,MATCH(D28,Partidas!$A$2:$A$99,0)) -> m2 | G28: 1 | H28: 0
A29: SAL | B29: Salón-comedor | C29: m² de suelo | D29: PIN-010 | E29: =INDEX(Partidas!$D$2:$D$99,MATCH(D29,Partidas!$A$2:$A$99,0)) -> Pintura plástica lisa en paredes | F29: =INDEX(Partidas!$C$2:$C$99,MATCH(D29,Partidas!$A$2:$A$99,0)) -> m2 | G29: 2.4 | H29: 0
A30: SAL | B30: Salón-comedor | C30: m² de suelo | D30: PIN-020 | E30: =INDEX(Partidas!$D$2:$D$99,MATCH(D30,Partidas!$A$2:$A$99,0)) -> Pintura plástica lisa en techos | F30: =INDEX(Partidas!$C$2:$C$99,MATCH(D30,Partidas!$A$2:$A$99,0)) -> m2 | G30: 1 | H30: 0
A31: SAL | B31: Salón-comedor | C31: m² de suelo | D31: ELE-050 | E31: =INDEX(Partidas!$D$2:$D$99,MATCH(D31,Partidas!$A$2:$A$99,0)) -> Punto de luz de cruce | F31: =INDEX(Partidas!$C$2:$C$99,MATCH(D31,Partidas!$A$2:$A$99,0)) -> ud | G31: 0 | H31: 1
... A45: BAN | B45: Baño completo con ducha | C45: m² de suelo | D45: PAV-020 | E45: =INDEX(Partidas!$D$2:$D$99,MATCH(D45,Partidas!$A$2:$A$99,0)) -> Solado de gres porcelánico | F45: =INDEX(Partidas!$C$2:$C$99,MATCH(D45,Partidas!$A$2:$A$99,0)) -> m2 | G45: 1 | H45: 0
A46: BAN | B46: Baño completo con ducha | C46: m² de suelo | D46: REV-010 | E46: =INDEX(Partidas!$D$2:$D$99,MATCH(D46,Partidas!$A$2:$A$99,0)) -> Alicatado de gres porcelánico | F46: =INDEX(Partidas!$C$2:$C$99,MATCH(D46,Partidas!$A$2:$A$99,0)) -> m2 | G46: 3.7 | H46: 0 | I46: OG47: 38,9 m² alicatado / 10,5 m² suelo húmedo
A47: BAN | B47: Baño completo con ducha | C47: m² de suelo | D47: TEC-020 | E47: =INDEX(Partidas!$D$2:$D$99,MATCH(D47,Partidas!$A$2:$A$99,0)) -> Falso techo continuo PYL hidrófugo | F47: =INDEX(Partidas!$C$2:$C$99,MATCH(D47,Partidas!$A$2:$A$99,0)) -> m2 | G47: 1 | H47: 0
A48: BAN | B48: Baño completo con ducha | C48: m² de suelo | D48: PIN-020 | E48: =INDEX(Partidas!$D$2:$D$99,MATCH(D48,Partidas!$A$2:$A$99,0)) -> Pintura plástica lisa en techos | F48: =INDEX(Partidas!$C$2:$C$99,MATCH(D48,Partidas!$A$2:$A$99,0)) -> m2 | G48: 1 | H48: 0
A49: BAN | B49: Baño completo con ducha | C49: m² de suelo | D49: FON-010 | E49: =INDEX(Partidas!$D$2:$D$99,MATCH(D49,Partidas!$A$2:$A$99,0)) -> Punto de agua fría y caliente | F49: =INDEX(Partidas!$C$2:$C$99,MATCH(D49,Partidas!$A$2:$A$99,0)) -> ud | G49: 0 | H49: 4.5 | I49: lavabo 2 + ducha 2 + inodoro 0,5
A50: BAN | B50: Baño completo con ducha | C50: m² de suelo | D50: FON-020 | E50: =INDEX(Partidas!$D$2:$D$99,MATCH(D50,Partidas!$A$2:$A$99,0)) -> Punto de desagüe | F50: =INDEX(Partidas!$C$2:$C$99,MATCH(D50,Partidas!$A$2:$A$99,0)) -> ud | G50: 0 | H50: 3
A51: BAN | B51: Baño completo con ducha | C51: m² de suelo | D51: FON-030 | E51: =INDEX(Partidas!$D$2:$D$99,MATCH(D51,Partidas!$A$2:$A$99,0)) -> Bote sifónico | F51: =INDEX(Partidas!$C$2:$C$99,MATCH(D51,Partidas!$A$2:$A$99,0)) -> ud | G51: 0 | H51: 1
A52: BAN | B52: Baño completo con ducha | C52: m² de suelo | D52: FON-040 | E52: =INDEX(Partidas!$D$2:$D$99,MATCH(D52,Partidas!$A$2:$A$99,0)) -> Llave de corte por estancia húmeda | F52: =INDEX(Partidas!$C$2:$C$99,MATCH(D52,Partidas!$A$2:$A$99,0)) -> ud | G52: 0 | H52: 1
A53: BAN | B53: Baño completo con ducha | C53: m² de suelo | D53: SAN-010 | E53: =INDEX(Partidas!$D$2:$D$99,MATCH(D53,Partidas!$A$2:$A$99,0)) -> Plato de ducha | F53: =INDEX(Partidas!$C$2:$C$99,MATCH(D53,Partidas!$A$2:$A$99,0)) -> ud | G53: 0 | H53: 1
A54: BAN | B54: Baño completo con ducha | C54: m² de suelo | D54: SAN-030 | E54: =INDEX(Partidas!$D$2:$D$99,MATCH(D54,Partidas!$A$2:$A$99,0)) -> Inodoro suspendido con bastidor | F54: =INDEX(Partidas!$C$2:$C$99,MATCH(D54,Partidas!$A$2:$A$99,0)) -> ud | G54: 0 | H54: 1
A55: BAN | B55: Baño completo con ducha | C55: m² de suelo | D55: SAN-040 | E55: =INDEX(Partidas!$D$2:$D$99,MATCH(D55,Partidas!$A$2:$A$99,0)) -> Mueble de baño con lavabo | F55: =INDEX(Partidas!$C$2:$C$99,MATCH(D55,Partidas!$A$2:$A$99,0)) -> ud | G55: 0 | H55: 1
A56: BAN | B56: Baño completo con ducha | C56: m² de suelo | D56: SAN-050 | E56: =INDEX(Partidas!$D$2:$D$99,MATCH(D56,Partidas!$A$2:$A$99,0)) -> Grifería de lavabo | F56: =INDEX(Partidas!$C$2:$C$99,MATCH(D56,Partidas!$A$2:$A$99,0)) -> ud | G56: 0 | H56: 1
A57: BAN | B57: Baño completo con ducha | C57: m² de suelo | D57: SAN-060 | E57: =INDEX(Partidas!$D$2:$D$99,MATCH(D57,Partidas!$A$2:$A$99,0)) -> Grifería termostática de ducha o bañera | F57: =INDEX(Partidas!$C$2:$C$99,MATCH(D57,Partidas!$A$2:$A$99,0)) -> ud | G57: 0 | H57: 1
A58: BAN | B58: Baño completo con ducha | C58: m² de suelo | D58: SAN-070 | E58: =INDEX(Partidas!$D$2:$D$99,MATCH(D58,Partidas!$A$2:$A$99,0)) -> Mampara fija de ducha | F58: =INDEX(Partidas!$C$2:$C$99,MATCH(D58,Partidas!$A$2:$A$99,0)) -> ud | G58: 0 | H58: 1
A59: BAN | B59: Baño completo con ducha | C59: m² de suelo | D59: SAN-090 | E59: =INDEX(Partidas!$D$2:$D$99,MATCH(D59,Partidas!$A$2:$A$99,0)) -> Espejo de baño a medida | F59: =INDEX(Partidas!$C$2:$C$99,MATCH(D59,Partidas!$A$2:$A$99,0)) -> m2 | G59: 0 | H59: 0.8
A60: BAN | B60: Baño completo con ducha | C60: m² de suelo | D60: SAN-100 | E60: =INDEX(Partidas!$D$2:$D$99,MATCH(D60,Partidas!$A$2:$A$99,0)) -> Toallero eléctrico | F60: =INDEX(Partidas!$C$2:$C$99,MATCH(D60,Partidas!$A$2:$A$99,0)) -> ud | G60: 0 | H60: 1
A61: BAN | B61: Baño completo con ducha | C61: m² de suelo | D61: SAN-120 | E61: =INDEX(Partidas!$D$2:$D$99,MATCH(D61,Partidas!$A$2:$A$99,0)) -> Juego de accesorios de baño | F61: =INDEX(Partidas!$C$2:$C$99,MATCH(D61,Partidas!$A$2:$A$99,0)) -> ud | G61: 0 | H61: 1
... A112: VEN | B112: Sustitución de ventanas | C112: número de ventanas | D112: PRE-030 | E112: =INDEX(Partidas!$D$2:$D$99,MATCH(D112,Partidas!$A$2:$A$99,0)) -> Medios de elevación para carpintería exterior | F112: =INDEX(Partidas!$C$2:$C$99,MATCH(D112,Partidas!$A$2:$A$99,0)) -> pa | G112: 0 | H112: 1
A113: DBA | B113: Demolición de baño o cocina existente | C113: m² de suelo | D113: DEM-090 | E113: =INDEX(Partidas!$D$2:$D$99,MATCH(D113,Partidas!$A$2:$A$99,0)) -> Picado de alicatado y solado cerámico | F113: =INDEX(Partidas!$C$2:$C$99,MATCH(D113,Partidas!$A$2:$A$99,0)) -> m2 | G113: 4.7 | H113: 0 | I113: paredes (≈3,7×) + suelo (1×)
A114: DBA | B114: Demolición de baño o cocina existente | C114: m² de suelo | D114: DEM-100 | E114: =INDEX(Partidas!$D$2:$D$99,MATCH(D114,Partidas!$A$2:$A$99,0)) -> Desmontaje de aparato sanitario o grifería | F114: =INDEX(Partidas!$C$2:$C$99,MATCH(D114,Partidas!$A$2:$A$99,0)) -> ud | G114: 0 | H114: 3

Sheet Calculadora
A1: Calculadora de oferta — calidad estándar Enzyme
A2: Rellene en azul: nombre de estancia, plantilla y tamaño (m², o nº de ventanas para VEN). Ejemplo con superficies aproximadas de Ortega y Gasset 47; ajústelas.
A4: Estancia | E4: Vivienda | F4: Salón-comedor | G4: Dormitorio principal | H4: Dormitorio 2 | I4: Dormitorio 3 | J4: Pasillo | K4: Hall | L4: Cocina | M4: Lavandería | N4: Baño principal | O4: Baño 2 | P4: Ventanas
A5: Plantilla | E5: GEN | F5: SAL | G5: DOR | H5: DOR | I5: DOR | J5: PAS | K5: PAS | L5: COC | M5: LAV | N5: BAN | O5: BAN | P5: VEN
A6: Tamaño | E6: 91 | F6: 24 | G6: 15 | H6: 10 | I6: 10 | J6: 7 | K6: 4 | L6: 9 | M6: 3 | N6: 5 | O6: 4 | P6: 9
A8: Código | B8: Cap. | C8: Descripción | D8: Ud | E8: =E4&"" -> Vivienda | F8: =F4&"" -> Salón-comedor | G8: =G4&"" -> Dormitorio principal | H8: =H4&"" -> Dormitorio 2 | I8: =I4&"" -> Dormitorio 3 | J8: =J4&"" -> Pasillo | K8: =K4&"" -> Hall | L8: =L4&"" -> Cocina | ... R8: =R4&"" | S8: Cantidad | T8: Precio (€/ud) | U8: Importe (€)
A9: PRE | C9: Actuaciones previas y medios auxiliares | U9: =SUM(U10:U13) -> 0
A10: PRE-010 | B10: PRE | C10: =INDEX(Partidas!$D$2:$D$99,MATCH(A10,Partidas!$A$2:$A$99,0)) -> Protección de zonas comunes y elementos que se conservan | D10: =INDEX(Partidas!$C$2:$C$99,MATCH(A10,Partidas!$A$2:$A$99,0)) -> pa | E10: =IF(E$5="",0,SUMPRODUCT((Plantillas!$A$2:$A$114=E$5)*(Plantillas!$D$2:$D$114=$A10)*(Plantillas!$G$2:$G$114*N(E$6)+Plantillas!$H$2:$H$114))) -> 1 | F10: =IF(F$5="",0,SUMPRODUCT((Plantillas!$A$2:$A$114=F$5)*(Plantillas!$D$2:$D$114=$A10)*(Plantillas!$G$2:$G$114*N(F$6)+Plantillas!$H$2:$H$114))) -> 0 | G10: =IF(G$5="",0,SUMPRODUCT((Plantillas!$A$2:$A$114=G$5)*(Plantillas!$D$2:$D$114=$A10)*(Plantillas!$G$2:$G$114*N(G$6)+Plantillas!$H$2:$H$114))) -> 0 | H10: =IF(H$5="",0,SUMPRODUCT((Plantillas!$A$2:$A$114=H$5)*(Plantillas!$D$2:$D$114=$A10)*(Plantillas!$G$2:$G$114*N(H$6)+Plantillas!$H$2:$H$114))) -> 0 | I10: =IF(I$5="",0,SUMPRODUCT((Plantillas!$A$2:$A$114=I$5)*(Plantillas!$D$2:$D$114=$A10)*(Plantillas!$G$2:$G$114*N(I$6)+Plantillas!$H$2:$H$114))) -> 0 | J10: =IF(J$5="",0,SUMPRODUCT((Plantillas!$A$2:$A$114=J$5)*(Plantillas!$D$2:$D$114=$A10)*(Plantillas!$G$2:$G$114*N(J$6)+Plantillas!$H$2:$H$114))) -> 0 | K10: =IF(K$5="",0,SUMPRODUCT((Plantillas!$A$2:$A$114=K$5)*(Plantillas!$D$2:$D$114=$A10)*(Plantillas!$G$2:$G$114*N(K$6)+Plantillas!$H$2:$H$114))) -> 0 | L10: =IF(L$5="",0,SUMPRODUCT((Plantillas!$A$2:$A$114=L$5)*(Plantillas!$D$2:$D$114=$A10)*(Plantillas!$G$2:$G$114*N(L$6)+Plantillas!$H$2:$H$114))) -> 0 | ... R10: =IF(R$5="",0,SUMPRODUCT((Plantillas!$A$2:$A$114=R$5)*(Plantillas!$D$2:$D$114=$A10)*(Plantillas!$G$2:$G$114*N(R$6)+Plantillas!$H$2:$H$114))) -> 0 | S10: =SUM(E10:R10) -> 1 | T10: =IF(INDEX(Partidas!$F$2:$F$99,MATCH(A10,Partidas!$A$2:$A$99,0))="","",INDEX(Partidas!$F$2:$F$99,MATCH(A10,Partidas!$A$2:$A$99,0))) | U10: =IF(T10="",0,S10*T10) -> 0
A11: PRE-020 | B11: PRE | C11: =INDEX(Partidas!$D$2:$D$99,MATCH(A11,Partidas!$A$2:$A$99,0)) -> Comunicación a la comunidad y gestión de ascensor/montacargas | D11: =INDEX(Partidas!$C$2:$C$99,MATCH(A11,Partidas!$A$2:$A$99,0)) -> pa | E11: =IF(E$5="",0,SUMPRODUCT((Plantillas!$A$2:$A$114=E$5)*(Plantillas!$D$2:$D$114=$A11)*(Plantillas!$G$2:$G$114*N(E$6)+Plantillas!$H$2:$H$114))) -> 1 | F11: =IF(F$5="",0,SUMPRODUCT((Plantillas!$A$2:$A$114=F$5)*(Plantillas!$D$2:$D$114=$A11)*(Plantillas!$G$2:$G$114*N(F$6)+Plantillas!$H$2:$H$114))) -> 0 | G11: =IF(G$5="",0,SUMPRODUCT((Plantillas!$A$2:$A$114=G$5)*(Plantillas!$D$2:$D$114=$A11)*(Plantillas!$G$2:$G$114*N(G$6)+Plantillas!$H$2:$H$114))) -> 0 | H11: =IF(H$5="",0,SUMPRODUCT((Plantillas!$A$2:$A$114=H$5)*(Plantillas!$D$2:$D$114=$A11)*(Plantillas!$G$2:$G$114*N(H$6)+Plantillas!$H$2:$H$114))) -> 0 | I11: =IF(I$5="",0,SUMPRODUCT((Plantillas!$A$2:$A$114=I$5)*(Plantillas!$D$2:$D$114=$A11)*(Plantillas!$G$2:$G$114*N(I$6)+Plantillas!$H$2:$H$114))) -> 0 | J11: =IF(J$5="",0,SUMPRODUCT((Plantillas!$A$2:$A$114=J$5)*(Plantillas!$D$2:$D$114=$A11)*(Plantillas!$G$2:$G$114*N(J$6)+Plantillas!$H$2:$H$114))) -> 0 | K11: =IF(K$5="",0,SUMPRODUCT((Plantillas!$A$2:$A$114=K$5)*(Plantillas!$D$2:$D$114=$A11)*(Plantillas!$G$2:$G$114*N(K$6)+Plantillas!$H$2:$H$114))) -> 0 | L11: =IF(L$5="",0,SUMPRODUCT((Plantillas!$A$2:$A$114=L$5)*(Plantillas!$D$2:$D$114=$A11)*(Plantillas!$G$2:$G$114*N(L$6)+Plantillas!$H$2:$H$114))) -> 0 | ... R11: =IF(R$5="",0,SUMPRODUCT((Plantillas!$A$2:$A$114=R$5)*(Plantillas!$D$2:$D$114=$A11)*(Plantillas!$G$2:$G$114*N(R$6)+Plantillas!$H$2:$H$114))) -> 0 | S11: =SUM(E11:R11) -> 1 | T11: =IF(INDEX(Partidas!$F$2:$F$99,MATCH(A11,Partidas!$A$2:$A$99,0))="","",INDEX(Partidas!$F$2:$F$99,MATCH(A11,Partidas!$A$2:$A$99,0))) | U11: =IF(T11="",0,S11*T11) -> 0
A12: PRE-030 | B12: PRE | C12: =INDEX(Partidas!$D$2:$D$99,MATCH(A12,Partidas!$A$2:$A$99,0)) -> Medios de elevación para carpintería exterior | D12: =INDEX(Partidas!$C$2:$C$99,MATCH(A12,Partidas!$A$2:$A$99,0)) -> pa | E12: =IF(E$5="",0,SUMPRODUCT((Plantillas!$A$2:$A$114=E$5)*(Plantillas!$D$2:$D$114=$A12)*(Plantillas!$G$2:$G$114*N(E$6)+Plantillas!$H$2:$H$114))) -> 0 | F12: =IF(F$5="",0,SUMPRODUCT((Plantillas!$A$2:$A$114=F$5)*(Plantillas!$D$2:$D$114=$A12)*(Plantillas!$G$2:$G$114*N(F$6)+Plantillas!$H$2:$H$114))) -> 0 | G12: =IF(G$5="",0,SUMPRODUCT((Plantillas!$A$2:$A$114=G$5)*(Plantillas!$D$2:$D$114=$A12)*(Plantillas!$G$2:$G$114*N(G$6)+Plantillas!$H$2:$H$114))) -> 0 | H12: =IF(H$5="",0,SUMPRODUCT((Plantillas!$A$2:$A$114=H$5)*(Plantillas!$D$2:$D$114=$A12)*(Plantillas!$G$2:$G$114*N(H$6)+Plantillas!$H$2:$H$114))) -> 0 | I12: =IF(I$5="",0,SUMPRODUCT((Plantillas!$A$2:$A$114=I$5)*(Plantillas!$D$2:$D$114=$A12)*(Plantillas!$G$2:$G$114*N(I$6)+Plantillas!$H$2:$H$114))) -> 0 | J12: =IF(J$5="",0,SUMPRODUCT((Plantillas!$A$2:$A$114=J$5)*(Plantillas!$D$2:$D$114=$A12)*(Plantillas!$G$2:$G$114*N(J$6)+Plantillas!$H$2:$H$114))) -> 0 | K12: =IF(K$5="",0,SUMPRODUCT((Plantillas!$A$2:$A$114=K$5)*(Plantillas!$D$2:$D$114=$A12)*(Plantillas!$G$2:$G$114*N(K$6)+Plantillas!$H$2:$H$114))) -> 0 | L12: =IF(L$5="",0,SUMPRODUCT((Plantillas!$A$2:$A$114=L$5)*(Plantillas!$D$2:$D$114=$A12)*(Plantillas!$G$2:$G$114*N(L$6)+Plantillas!$H$2:$H$114))) -> 0 | ... R12: =IF(R$5="",0,SUMPRODUCT((Plantillas!$A$2:$A$114=R$5)*(Plantillas!$D$2:$D$114=$A12)*(Plantillas!$G$2:$G$114*N(R$6)+Plantillas!$H$2:$H$114))) -> 0 | S12: =SUM(E12:R12) -> 1 | T12: =IF(INDEX(Partidas!$F$2:$F$99,MATCH(A12,Partidas!$A$2:$A$99,0))="","",INDEX(Partidas!$F$2:$F$99,MATCH(A12,Partidas!$A$2:$A$99,0))) | U12: =IF(T12="",0,S12*T12) -> 0
A13: PRE-040 | B13: PRE | C13: =INDEX(Partidas!$D$2:$D$99,MATCH(A13,Partidas!$A$2:$A$99,0)) -> Gestión de licencia o declaración responsable | D13: =INDEX(Partidas!$C$2:$C$99,MATCH(A13,Partidas!$A$2:$A$99,0)) -> pa | E13: =IF(E$5="",0,SUMPRODUCT((Plantillas!$A$2:$A$114=E$5)*(Plantillas!$D$2:$D$114=$A13)*(Plantillas!$G$2:$G$114*N(E$6)+Plantillas!$H$2:$H$114))) -> 1 | F13: =IF(F$5="",0,SUMPRODUCT((Plantillas!$A$2:$A$114=F$5)*(Plantillas!$D$2:$D$114=$A13)*(Plantillas!$G$2:$G$114*N(F$6)+Plantillas!$H$2:$H$114))) -> 0 | G13: =IF(G$5="",0,SUMPRODUCT((Plantillas!$A$2:$A$114=G$5)*(Plantillas!$D$2:$D$114=$A13)*(Plantillas!$G$2:$G$114*N(G$6)+Plantillas!$H$2:$H$114))) -> 0 | H13: =IF(H$5="",0,SUMPRODUCT((Plantillas!$A$2:$A$114=H$5)*(Plantillas!$D$2:$D$114=$A13)*(Plantillas!$G$2:$G$114*N(H$6)+Plantillas!$H$2:$H$114))) -> 0 | I13: =IF(I$5="",0,SUMPRODUCT((Plantillas!$A$2:$A$114=I$5)*(Plantillas!$D$2:$D$114=$A13)*(Plantillas!$G$2:$G$114*N(I$6)+Plantillas!$H$2:$H$114))) -> 0 | J13: =IF(J$5="",0,SUMPRODUCT((Plantillas!$A$2:$A$114=J$5)*(Plantillas!$D$2:$D$114=$A13)*(Plantillas!$G$2:$G$114*N(J$6)+Plantillas!$H$2:$H$114))) -> 0 | K13: =IF(K$5="",0,SUMPRODUCT((Plantillas!$A$2:$A$114=K$5)*(Plantillas!$D$2:$D$114=$A13)*(Plantillas!$G$2:$G$114*N(K$6)+Plantillas!$H$2:$H$114))) -> 0 | L13: =IF(L$5="",0,SUMPRODUCT((Plantillas!$A$2:$A$114=L$5)*(Plantillas!$D$2:$D$114=$A13)*(Plantillas!$G$2:$G$114*N(L$6)+Plantillas!$H$2:$H$114))) -> 0 | ... R13: =IF(R$5="",0,SUMPRODUCT((Plantillas!$A$2:$A$114=R$5)*(Plantillas!$D$2:$D$114=$A13)*(Plantillas!$G$2:$G$114*N(R$6)+Plantillas!$H$2:$H$114))) -> 0 | S13: =SUM(E13:R13) -> 1 | T13: =IF(INDEX(Partidas!$F$2:$F$99,MATCH(A13,Partidas!$A$2:$A$99,0))="","",INDEX(Partidas!$F$2:$F$99,MATCH(A13,Partidas!$A$2:$A$99,0))) | U13: =IF(T13="",0,S13*T13) -> 0
A14: DEM | C14: Demoliciones y desmontajes | U14: =SUM(U15:U26) -> 788
A15: DEM-010 | B15: DEM | C15: =INDEX(Partidas!$D$2:$D$99,MATCH(A15,Partidas!$A$2:$A$99,0)) -> Desmontaje de mobiliario existente | D15: =INDEX(Partidas!$C$2:$C$99,MATCH(A15,Partidas!$A$2:$A$99,0)) -> pa | E15: =IF(E$5="",0,SUMPRODUCT((Plantillas!$A$2:$A$114=E$5)*(Plantillas!$D$2:$D$114=$A15)*(Plantillas!$G$2:$G$114*N(E$6)+Plantillas!$H$2:$H$114))) -> 1 | F15: =IF(F$5="",0,SUMPRODUCT((Plantillas!$A$2:$A$114=F$5)*(Plantillas!$D$2:$D$114=$A15)*(Plantillas!$G$2:$G$114*N(F$6)+Plantillas!$H$2:$H$114))) -> 0 | G15: =IF(G$5="",0,SUMPRODUCT((Plantillas!$A$2:$A$114=G$5)*(Plantillas!$D$2:$D$114=$A15)*(Plantillas!$G$2:$G$114*N(G$6)+Plantillas!$H$2:$H$114))) -> 0 | H15: =IF(H$5="",0,SUMPRODUCT((Plantillas!$A$2:$A$114=H$5)*(Plantillas!$D$2:$D$114=$A15)*(Plantillas!$G$2:$G$114*N(H$6)+Plantillas!$H$2:$H$114))) -> 0 | I15: =IF(I$5="",0,SUMPRODUCT((Plantillas!$A$2:$A$114=I$5)*(Plantillas!$D$2:$D$114=$A15)*(Plantillas!$G$2:$G$114*N(I$6)+Plantillas!$H$2:$H$114))) -> 0 | J15: =IF(J$5="",0,SUMPRODUCT((Plantillas!$A$2:$A$114=J$5)*(Plantillas!$D$2:$D$114=$A15)*(Plantillas!$G$2:$G$114*N(J$6)+Plantillas!$H$2:$H$114))) -> 0 | K15: =IF(K$5="",0,SUMPRODUCT((Plantillas!$A$2:$A$114=K$5)*(Plantillas!$D$2:$D$114=$A15)*(Plantillas!$G$2:$G$114*N(K$6)+Plantillas!$H$2:$H$114))) -> 0 | L15: =IF(L$5="",0,SUMPRODUCT((Plantillas!$A$2:$A$114=L$5)*(Plantillas!$D$2:$D$114=$A15)*(Plantillas!$G$2:$G$114*N(L$6)+Plantillas!$H$2:$H$114))) -> 0 | ... R15: =IF(R$5="",0,SUMPRODUCT((Plantillas!$A$2:$A$114=R$5)*(Plantillas!$D$2:$D$114=$A15)*(Plantillas!$G$2:$G$114*N(R$6)+Plantillas!$H$2:$H$114))) -> 0 | S15: =SUM(E15:R15) -> 1 | T15: =IF(INDEX(Partidas!$F$2:$F$99,MATCH(A15,Partidas!$A$2:$A$99,0))="","",INDEX(Partidas!$F$2:$F$99,MATCH(A15,Partidas!$A$2:$A$99,0))) -> 500 | U15: =IF(T15="",0,S15*T15) -> 500
A16: DEM-020 | B16: DEM | C16: =INDEX(Partidas!$D$2:$D$99,MATCH(A16,Partidas!$A$2:$A$99,0)) -> Desmontaje de carpintería exterior | D16: =INDEX(Partidas!$C$2:$C$99,MATCH(A16,Partidas!$A$2:$A$99,0)) -> ud | E16: =IF(E$5="",0,SUMPRODUCT((Plantillas!$A$2:$A$114=E$5)*(Plantillas!$D$2:$D$114=$A16)*(Plantillas!$G$2:$G$114*N(E$6)+Plantillas!$H$2:$H$114))) -> 0 | F16: =IF(F$5="",0,SUMPRODUCT((Plantillas!$A$2:$A$114=F$5)*(Plantillas!$D$2:$D$114=$A16)*(Plantillas!$G$2:$G$114*N(F$6)+Plantillas!$H$2:$H$114))) -> 0 | G16: =IF(G$5="",0,SUMPRODUCT((Plantillas!$A$2:$A$114=G$5)*(Plantillas!$D$2:$D$114=$A16)*(Plantillas!$G$2:$G$114*N(G$6)+Plantillas!$H$2:$H$114))) -> 0 | H16: =IF(H$5="",0,SUMPRODUCT((Plantillas!$A$2:$A$114=H$5)*(Plantillas!$D$2:$D$114=$A16)*(Plantillas!$G$2:$G$114*N(H$6)+Plantillas!$H$2:$H$114))) -> 0 | I16: =IF(I$5="",0,SUMPRODUCT((Plantillas!$A$2:$A$114=I$5)*(Plantillas!$D$2:$D$114=$A16)*(Plantillas!$G$2:$G$114*N(I$6)+Plantillas!$H$2:$H$114))) -> 0 | J16: =IF(J$5="",0,SUMPRODUCT((Plantillas!$A$2:$A$114=J$5)*(Plantillas!$D$2:$D$114=$A16)*(Plantillas!$G$2:$G$114*N(J$6)+Plantillas!$H$2:$H$114))) -> 0 | K16: =IF(K$5="",0,SUMPRODUCT((Plantillas!$A$2:$A$114=K$5)*(Plantillas!$D$2:$D$114=$A16)*(Plantillas!$G$2:$G$114*N(K$6)+Plantillas!$H$2:$H$114))) -> 0 | L16: =IF(L$5="",0,SUMPRODUCT((Plantillas!$A$2:$A$114=L$5)*(Plantillas!$D$2:$D$114=$A16)*(Plantillas!$G$2:$G$114*N(L$6)+Plantillas!$H$2:$H$114))) -> 0 | ... R16: =IF(R$5="",0,SUMPRODUCT((Plantillas!$A$2:$A$114=R$5)*(Plantillas!$D$2:$D$114=$A16)*(Plantillas!$G$2:$G$114*N(R$6)+Plantillas!$H$2:$H$114))) -> 0 | S16: =SUM(E16:R16) -> 9 | T16: =IF(INDEX(Partidas!$F$2:$F$99,MATCH(A16,Partidas!$A$2:$A$99,0))="","",INDEX(Partidas!$F$2:$F$99,MATCH(A16,Partidas!$A$2:$A$99,0))) -> 32 | U16: =IF(T16="",0,S16*T16) -> 288
A17: DEM-030 | B17: DEM | C17: =INDEX(Partidas!$D$2:$D$99,MATCH(A17,Partidas!$A$2:$A$99,0)) -> Ajuste de hueco en fachada (ampliación o reducción) | D17: =INDEX(Partidas!$C$2:$C$99,MATCH(A17,Partidas!$A$2:$A$99,0)) -> m2 | E17: =IF(E$5="",0,SUMPRODUCT((Plantillas!$A$2:$A$114=E$5)*(Plantillas!$D$2:$D$114=$A17)*(Plantillas!$G$2:$G$114*N(E$6)+Plantillas!$H$2:$H$114))) -> 0 | F17: =IF(F$5="",0,SUMPRODUCT((Plantillas!$A$2:$A$114=F$5)*(Plantillas!$D$2:$D$114=$A17)*(Plantillas!$G$2:$G$114*N(F$6)+Plantillas!$H$2:$H$114))) -> 0 | G17: =IF(G$5="",0,SUMPRODUCT((Plantillas!$A$2:$A$114=G$5)*(Plantillas!$D$2:$D$114=$A17)*(Plantillas!$G$2:$G$114*N(G$6)+Plantillas!$H$2:$H$114))) -> 0 | H17: =IF(H$5="",0,SUMPRODUCT((Plantillas!$A$2:$A$114=H$5)*(Plantillas!$D$2:$D$114=$A17)*(Plantillas!$G$2:$G$114*N(H$6)+Plantillas!$H$2:$H$114))) -> 0 | I17: =IF(I$5="",0,SUMPRODUCT((Plantillas!$A$2:$A$114=I$5)*(Plantillas!$D$2:$D$114=$A17)*(Plantillas!$G$2:$G$114*N(I$6)+Plantillas!$H$2:$H$114))) -> 0 | J17: =IF(J$5="",0,SUMPRODUCT((Plantillas!$A$2:$A$114=J$5)*(Plantillas!$D$2:$D$114=$A17)*(Plantillas!$G$2:$G$114*N(J$6)+Plantillas!$H$2:$H$114))) -> 0 | K17: =IF(K$5="",0,SUMPRODUCT((Plantillas!$A$2:$A$114=K$5)*(Plantillas!$D$2:$D$114=$A17)*(Plantillas!$G$2:$G$114*N(K$6)+Plantillas!$H$2:$H$114))) -> 0 | L17: =IF(L$5="",0,SUMPRODUCT((Plantillas!$A$2:$A$114=L$5)*(Plantillas!$D$2:$D$114=$A17)*(Plantillas!$G$2:$G$114*N(L$6)+Plantillas!$H$2:$H$114))) -> 0 | ... R17: =IF(R$5="",0,SUMPRODUCT((Plantillas!$A$2:$A$114=R$5)*(Plantillas!$D$2:$D$114=$A17)*(Plantillas!$G$2:$G$114*N(R$6)+Plantillas!$H$2:$H$114))) -> 0 | S17: =SUM(E17:R17) -> 0 | T17: =IF(INDEX(Partidas!$F$2:$F$99,MATCH(A17,Partidas!$A$2:$A$99,0))="","",INDEX(Partidas!$F$2:$F$99,MATCH(A17,Partidas!$A$2:$A$99,0))) -> 24 | U17: =IF(T17="",0,S17*T17) -> 0
A18: DEM-040 | B18: DEM | C18: =INDEX(Partidas!$D$2:$D$99,MATCH(A18,Partidas!$A$2:$A$99,0)) -> Demolición de tabique de placa de yeso laminado | D18: =INDEX(Partidas!$C$2:$C$99,MATCH(A18,Partidas!$A$2:$A$99,0)) -> m2 | E18: =IF(E$5="",0,SUMPRODUCT((Plantillas!$A$2:$A$114=E$5)*(Plantillas!$D$2:$D$114=$A18)*(Plantillas!$G$2:$G$114*N(E$6)+Plantillas!$H$2:$H$114))) -> 0 | F18: =IF(F$5="",0,SUMPRODUCT((Plantillas!$A$2:$A$114=F$5)*(Plantillas!$D$2:$D$114=$A18)*(Plantillas!$G$2:$G$114*N(F$6)+Plantillas!$H$2:$H$114))) -> 0 | G18: =IF(G$5="",0,SUMPRODUCT((Plantillas!$A$2:$A$114=G$5)*(Plantillas!$D$2:$D$114=$A18)*(Plantillas!$G$2:$G$114*N(G$6)+Plantillas!$H$2:$H$114))) -> 0 | H18: =IF(H$5="",0,SUMPRODUCT((Plantillas!$A$2:$A$114=H$5)*(Plantillas!$D$2:$D$114=$A18)*(Plantillas!$G$2:$G$114*N(H$6)+Plantillas!$H$2:$H$114))) -> 0 | I18: =IF(I$5="",0,SUMPRODUCT((Plantillas!$A$2:$A$114=I$5)*(Plantillas!$D$2:$D$114=$A18)*(Plantillas!$G$2:$G$114*N(I$6)+Plantillas!$H$2:$H$114))) -> 0 | J18: =IF(J$5="",0,SUMPRODUCT((Plantillas!$A$2:$A$114=J$5)*(Plantillas!$D$2:$D$114=$A18)*(Plantillas!$G$2:$G$114*N(J$6)+Plantillas!$H$2:$H$114))) -> 0 | K18: =IF(K$5="",0,SUMPRODUCT((Plantillas!$A$2:$A$114=K$5)*(Plantillas!$D$2:$D$114=$A18)*(Plantillas!$G$2:$G$114*N(K$6)+Plantillas!$H$2:$H$114))) -> 0 | L18: =IF(L$5="",0,SUMPRODUCT((Plantillas!$A$2:$A$114=L$5)*(Plantillas!$D$2:$D$114=$A18)*(Plantillas!$G$2:$G$114*N(L$6)+Plantillas!$H$2:$H$114))) -> 0 | ... R18: =IF(R$5="",0,SUMPRODUCT((Plantillas!$A$2:$A$114=R$5)*(Plantillas!$D$2:$D$114=$A18)*(Plantillas!$G$2:$G$114*N(R$6)+Plantillas!$H$2:$H$114))) -> 0 | S18: =SUM(E18:R18) -> 0 | T18: =IF(INDEX(Partidas!$F$2:$F$99,MATCH(A18,Partidas!$A$2:$A$99,0))="","",INDEX(Partidas!$F$2:$F$99,MATCH(A18,Partidas!$A$2:$A$99,0))) -> 16 | U18: =IF(T18="",0,S18*T18) -> 0
A19: DEM-050 | B19: DEM | C19: =INDEX(Partidas!$D$2:$D$99,MATCH(A19,Partidas!$A$2:$A$99,0)) -> Demolición de tabique de ladrillo | D19: =INDEX(Partidas!$C$2:$C$99,MATCH(A19,Partidas!$A$2:$A$99,0)) -> m2 | E19: =IF(E$5="",0,SUMPRODUCT((Plantillas!$A$2:$A$114=E$5)*(Plantillas!$D$2:$D$114=$A19)*(Plantillas!$G$2:$G$114*N(E$6)+Plantillas!$H$2:$H$114))) -> 0 | F19: =IF(F$5="",0,SUMPRODUCT((Plantillas!$A$2:$A$114=F$5)*(Plantillas!$D$2:$D$114=$A19)*(Plantillas!$G$2:$G$114*N(F$6)+Plantillas!$H$2:$H$114))) -> 0 | G19: =IF(G$5="",0,SUMPRODUCT((Plantillas!$A$2:$A$114=G$5)*(Plantillas!$D$2:$D$114=$A19)*(Plantillas!$G$2:$G$114*N(G$6)+Plantillas!$H$2:$H$114))) -> 0 | H19: =IF(H$5="",0,SUMPRODUCT((Plantillas!$A$2:$A$114=H$5)*(Plantillas!$D$2:$D$114=$A19)*(Plantillas!$G$2:$G$114*N(H$6)+Plantillas!$H$2:$H$114))) -> 0 | I19: =IF(I$5="",0,SUMPRODUCT((Plantillas!$A$2:$A$114=I$5)*(Plantillas!$D$2:$D$114=$A19)*(Plantillas!$G$2:$G$114*N(I$6)+Plantillas!$H$2:$H$114))) -> 0 | J19: =IF(J$5="",0,SUMPRODUCT((Plantillas!$A$2:$A$114=J$5)*(Plantillas!$D$2:$D$114=$A19)*(Plantillas!$G$2:$G$114*N(J$6)+Plantillas!$H$2:$H$114))) -> 0 | K19: =IF(K$5="",0,SUMPRODUCT((Plantillas!$A$2:$A$114=K$5)*(Plantillas!$D$2:$D$114=$A19)*(Plantillas!$G$2:$G$114*N(K$6)+Plantillas!$H$2:$H$114))) -> 0 | L19: =IF(L$5="",0,SUMPRODUCT((Plantillas!$A$2:$A$114=L$5)*(Plantillas!$D$2:$D$114=$A19)*(Plantillas!$G$2:$G$114*N(L$6)+Plantillas!$H$2:$H$114))) -> 0 | ... R19: =IF(R$5="",0,SUMPRODUCT((Plantillas!$A$2:$A$114=R$5)*(Plantillas!$D$2:$D$114=$A19)*(Plantillas!$G$2:$G$114*N(R$6)+Plantillas!$H$2:$H$114))) -> 0 | S19: =SUM(E19:R19) -> 0 | T19: =IF(INDEX(Partidas!$F$2:$F$99,MATCH(A19,Partidas!$A$2:$A$99,0))="","",INDEX(Partidas!$F$2:$F$99,MATCH(A19,Partidas!$A$2:$A$99,0))) | U19: =IF(T19="",0,S19*T19) -> 0
A20: DEM-060 | B20: DEM | C20: =INDEX(Partidas!$D$2:$D$99,MATCH(A20,Partidas!$A$2:$A$99,0)) -> Demolición de falso techo de PYL o escayola | D20: =INDEX(Partidas!$C$2:$C$99,MATCH(A20,Partidas!$A$2:$A$99,0)) -> m2 | E20: =IF(E$5="",0,SUMPRODUCT((Plantillas!$A$2:$A$114=E$5)*(Plantillas!$D$2:$D$114=$A20)*(Plantillas!$G$2:$G$114*N(E$6)+Plantillas!$H$2:$H$114))) -> 0 | F20: =IF(F$5="",0,SUMPRODUCT((Plantillas!$A$2:$A$114=F$5)*(Plantillas!$D$2:$D$114=$A20)*(Plantillas!$G$2:$G$114*N(F$6)+Plantillas!$H$2:$H$114))) -> 0 | G20: =IF(G$5="",0,SUMPRODUCT((Plantillas!$A$2:$A$114=G$5)*(Plantillas!$D$2:$D$114=$A20)*(Plantillas!$G$2:$G$114*N(G$6)+Plantillas!$H$2:$H$114))) -> 0 | H20: =IF(H$5="",0,SUMPRODUCT((Plantillas!$A$2:$A$114=H$5)*(Plantillas!$D$2:$D$114=$A20)*(Plantillas!$G$2:$G$114*N(H$6)+Plantillas!$H$2:$H$114))) -> 0 | I20: =IF(I$5="",0,SUMPRODUCT((Plantillas!$A$2:$A$114=I$5)*(Plantillas!$D$2:$D$114=$A20)*(Plantillas!$G$2:$G$114*N(I$6)+Plantillas!$H$2:$H$114))) -> 0 | J20: =IF(J$5="",0,SUMPRODUCT((Plantillas!$A$2:$A$114=J$5)*(Plantillas!$D$2:$D$114=$A20)*(Plantillas!$G$2:$G$114*N(J$6)+Plantillas!$H$2:$H$114))) -> 0 | K20: =IF(K$5="",0,SUMPRODUCT((Plantillas!$A$2:$A$114=K$5)*(Plantillas!$D$2:$D$114=$A20)*(Plantillas!$G$2:$G$114*N(K$6)+Plantillas!$H$2:$H$114))) -> 0 | L20: =IF(L$5="",0,SUMPRODUCT((Plantillas!$A$2:$A$114=L$5)*(Plantillas!$D$2:$D$114=$A20)*(Plantillas!$G$2:$G$114*N(L$6)+Plantillas!$H$2:$H$114))) -> 0 | ... R20: =IF(R$5="",0,SUMPRODUCT((Plantillas!$A$2:$A$114=R$5)*(Plantillas!$D$2:$D$114=$A20)*(Plantillas!$G$2:$G$114*N(R$6)+Plantillas!$H$2:$H$114))) -> 0 | S20: =SUM(E20:R20) -> 0 | T20: =IF(INDEX(Partidas!$F$2:$F$99,MATCH(A20,Partidas!$A$2:$A$99,0))="","",INDEX(Partidas!$F$2:$F$99,MATCH(A20,Partidas!$A$2:$A$99,0))) -> 10 | U20: =IF(T20="",0,S20*T20) -> 0
A21: DEM-070 | B21: DEM | C21: =INDEX(Partidas!$D$2:$D$99,MATCH(A21,Partidas!$A$2:$A$99,0)) -> Desmontaje de radiador | D21: =INDEX(Partidas!$C$2:$C$99,MATCH(A21,Partidas!$A$2:$A$99,0)) -> ud | E21: =IF(E$5="",0,SUMPRODUCT((Plantillas!$A$2:$A$114=E$5)*(Plantillas!$D$2:$D$114=$A21)*(Plantillas!$G$2:$G$114*N(E$6)+Plantillas!$H$2:$H$114))) -> 0 | F21: =IF(F$5="",0,SUMPRODUCT((Plantillas!$A$2:$A$114=F$5)*(Plantillas!$D$2:$D$114=$A21)*(Plantillas!$G$2:$G$114*N(F$6)+Plantillas!$H$2:$H$114))) -> 0 | G21: =IF(G$5="",0,SUMPRODUCT((Plantillas!$A$2:$A$114=G$5)*(Plantillas!$D$2:$D$114=$A21)*(Plantillas!$G$2:$G$114*N(G$6)+Plantillas!$H$2:$H$114))) -> 0 | H21: =IF(H$5="",0,SUMPRODUCT((Plantillas!$A$2:$A$114=H$5)*(Plantillas!$D$2:$D$114=$A21)*(Plantillas!$G$2:$G$114*N(H$6)+Plantillas!$H$2:$H$114))) -> 0 | I21: =IF(I$5="",0,SUMPRODUCT((Plantillas!$A$2:$A$114=I$5)*(Plantillas!$D$2:$D$114=$A21)*(Plantillas!$G$2:$G$114*N(I$6)+Plantillas!$H$2:$H$114))) -> 0 | J21: =IF(J$5="",0,SUMPRODUCT((Plantillas!$A$2:$A$114=J$5)*(Plantillas!$D$2:$D$114=$A21)*(Plantillas!$G$2:$G$114*N(J$6)+Plantillas!$H$2:$H$114))) -> 0 | K21: =IF(K$5="",0,SUMPRODUCT((Plantillas!$A$2:$A$114=K$5)*(Plantillas!$D$2:$D$114=$A21)*(Plantillas!$G$2:$G$114*N(K$6)+Plantillas!$H$2:$H$114))) -> 0 | L21: =IF(L$5="",0,SUMPRODUCT((Plantillas!$A$2:$A$114=L$5)*(Plantillas!$D$2:$D$114=$A21)*(Plantillas!$G$2:$G$114*N(L$6)+Plantillas!$H$2:$H$114))) -> 0 | ... R21: =IF(R$5="",0,SUMPRODUCT((Plantillas!$A$2:$A$114=R$5)*(Plantillas!$D$2:$D$114=$A21)*(Plantillas!$G$2:$G$114*N(R$6)+Plantillas!$H$2:$H$114))) -> 0 | S21: =SUM(E21:R21) -> 0 | T21: =IF(INDEX(Partidas!$F$2:$F$99,MATCH(A21,Partidas!$A$2:$A$99,0))="","",INDEX(Partidas!$F$2:$F$99,MATCH(A21,Partidas!$A$2:$A$99,0))) -> 60 | U21: =IF(T21="",0,S21*T21) -> 0
A22: DEM-080 | B22: DEM | C22: =INDEX(Partidas!$D$2:$D$99,MATCH(A22,Partidas!$A$2:$A$99,0)) -> Levantado de pavimento de madera, laminado o vinílico | D22: =INDEX(Partidas!$C$2:$C$99,MATCH(A22,Partidas!$A$2:$A$99,0)) -> m2 | E22: =IF(E$5="",0,SUMPRODUCT((Plantillas!$A$2:$A$114=E$5)*(Plantillas!$D$2:$D$114=$A22)*(Plantillas!$G$2:$G$114*N(E$6)+Plantillas!$H$2:$H$114))) -> 0 | F22: =IF(F$5="",0,SUMPRODUCT((Plantillas!$A$2:$A$114=F$5)*(Plantillas!$D$2:$D$114=$A22)*(Plantillas!$G$2:$G$114*N(F$6)+Plantillas!$H$2:$H$114))) -> 0 | G22: =IF(G$5="",0,SUMPRODUCT((Plantillas!$A$2:$A$114=G$5)*(Plantillas!$D$2:$D$114=$A22)*(Plantillas!$G$2:$G$114*N(G$6)+Plantillas!$H$2:$H$114))) -> 0 | H22: =IF(H$5="",0,SUMPRODUCT((Plantillas!$A$2:$A$114=H$5)*(Plantillas!$D$2:$D$114=$A22)*(Plantillas!$G$2:$G$114*N(H$6)+Plantillas!$H$2:$H$114))) -> 0 | I22: =IF(I$5="",0,SUMPRODUCT((Plantillas!$A$2:$A$114=I$5)*(Plantillas!$D$2:$D$114=$A22)*(Plantillas!$G$2:$G$114*N(I$6)+Plantillas!$H$2:$H$114))) -> 0 | J22: =IF(J$5="",0,SUMPRODUCT((Plantillas!$A$2:$A$114=J$5)*(Plantillas!$D$2:$D$114=$A22)*(Plantillas!$G$2:$G$114*N(J$6)+Plantillas!$H$2:$H$114))) -> 0 | K22: =IF(K$5="",0,SUMPRODUCT((Plantillas!$A$2:$A$114=K$5)*(Plantillas!$D$2:$D$114=$A22)*(Plantillas!$G$2:$G$114*N(K$6)+Plantillas!$H$2:$H$114))) -> 0 | L22: =IF(L$5="",0,SUMPRODUCT((Plantillas!$A$2:$A$114=L$5)*(Plantillas!$D$2:$D$114=$A22)*(Plantillas!$G$2:$G$114*N(L$6)+Plantillas!$H$2:$H$114))) -> 0 | ... R22: =IF(R$5="",0,SUMPRODUCT((Plantillas!$A$2:$A$114=R$5)*(Plantillas!$D$2:$D$114=$A22)*(Plantillas!$G$2:$G$114*N(R$6)+Plantillas!$H$2:$H$114))) -> 0 | S22: =SUM(E22:R22) -> 0 | T22: =IF(INDEX(Partidas!$F$2:$F$99,MATCH(A22,Partidas!$A$2:$A$99,0))="","",INDEX(Partidas!$F$2:$F$99,MATCH(A22,Partidas!$A$2:$A$99,0))) -> 18 | U22: =IF(T22="",0,S22*T22) -> 0
A23: DEM-090 | B23: DEM | C23: =INDEX(Partidas!$D$2:$D$99,MATCH(A23,Partidas!$A$2:$A$99,0)) -> Picado de alicatado y solado cerámico | D23: =INDEX(Partidas!$C$2:$C$99,MATCH(A23,Partidas!$A$2:$A$99,0)) -> m2 | E23: =IF(E$5="",0,SUMPRODUCT((Plantillas!$A$2:$A$114=E$5)*(Plantillas!$D$2:$D$114=$A23)*(Plantillas!$G$2:$G$114*N(E$6)+Plantillas!$H$2:$H$114))) -> 0 | F23: =IF(F$5="",0,SUMPRODUCT((Plantillas!$A$2:$A$114=F$5)*(Plantillas!$D$2:$D$114=$A23)*(Plantillas!$G$2:$G$114*N(F$6)+Plantillas!$H$2:$H$114))) -> 0 | G23: =IF(G$5="",0,SUMPRODUCT((Plantillas!$A$2:$A$114=G$5)*(Plantillas!$D$2:$D$114=$A23)*(Plantillas!$G$2:$G$114*N(G$6)+Plantillas!$H$2:$H$114))) -> 0 | H23: =IF(H$5="",0,SUMPRODUCT((Plantillas!$A$2:$A$114=H$5)*(Plantillas!$D$2:$D$114=$A23)*(Plantillas!$G$2:$G$114*N(H$6)+Plantillas!$H$2:$H$114))) -> 0 | I23: =IF(I$5="",0,SUMPRODUCT((Plantillas!$A$2:$A$114=I$5)*(Plantillas!$D$2:$D$114=$A23)*(Plantillas!$G$2:$G$114*N(I$6)+Plantillas!$H$2:$H$114))) -> 0 | J23: =IF(J$5="",0,SUMPRODUCT((Plantillas!$A$2:$A$114=J$5)*(Plantillas!$D$2:$D$114=$A23)*(Plantillas!$G$2:$G$114*N(J$6)+Plantillas!$H$2:$H$114))) -> 0 | K23: =IF(K$5="",0,SUMPRODUCT((Plantillas!$A$2:$A$114=K$5)*(Plantillas!$D$2:$D$114=$A23)*(Plantillas!$G$2:$G$114*N(K$6)+Plantillas!$H$2:$H$114))) -> 0 | L23: =IF(L$5="",0,SUMPRODUCT((Plantillas!$A$2:$A$114=L$5)*(Plantillas!$D$2:$D$114=$A23)*(Plantillas!$G$2:$G$114*N(L$6)+Plantillas!$H$2:$H$114))) -> 0 | ... R23: =IF(R$5="",0,SUMPRODUCT((Plantillas!$A$2:$A$114=R$5)*(Plantillas!$D$2:$D$114=$A23)*(Plantillas!$G$2:$G$114*N(R$6)+Plantillas!$H$2:$H$114))) -> 0 | S23: =SUM(E23:R23) -> 0 | T23: =IF(INDEX(Partidas!$F$2:$F$99,MATCH(A23,Partidas!$A$2:$A$99,0))="","",INDEX(Partidas!$F$2:$F$99,MATCH(A23,Partidas!$A$2:$A$99,0))) -> 28 | U23: =IF(T23="",0,S23*T23) -> 0
A24: DEM-100 | B24: DEM | C24: =INDEX(Partidas!$D$2:$D$99,MATCH(A24,Partidas!$A$2:$A$99,0)) -> Desmontaje de aparato sanitario o grifería | D24: =INDEX(Partidas!$C$2:$C$99,MATCH(A24,Partidas!$A$2:$A$99,0)) -> ud | E24: =IF(E$5="",0,SUMPRODUCT((Plantillas!$A$2:$A$114=E$5)*(Plantillas!$D$2:$D$114=$A24)*(Plantillas!$G$2:$G$114*N(E$6)+Plantillas!$H$2:$H$114))) -> 0 | F24: =IF(F$5="",0,SUMPRODUCT((Plantillas!$A$2:$A$114=F$5)*(Plantillas!$D$2:$D$114=$A24)*(Plantillas!$G$2:$G$114*N(F$6)+Plantillas!$H$2:$H$114))) -> 0 | G24: =IF(G$5="",0,SUMPRODUCT((Plantillas!$A$2:$A$114=G$5)*(Plantillas!$D$2:$D$114=$A24)*(Plantillas!$G$2:$G$114*N(G$6)+Plantillas!$H$2:$H$114))) -> 0 | H24: =IF(H$5="",0,SUMPRODUCT((Plantillas!$A$2:$A$114=H$5)*(Plantillas!$D$2:$D$114=$A24)*(Plantillas!$G$2:$G$114*N(H$6)+Plantillas!$H$2:$H$114))) -> 0 | I24: =IF(I$5="",0,SUMPRODUCT((Plantillas!$A$2:$A$114=I$5)*(Plantillas!$D$2:$D$114=$A24)*(Plantillas!$G$2:$G$114*N(I$6)+Plantillas!$H$2:$H$114))) -> 0 | J24: =IF(J$5="",0,SUMPRODUCT((Plantillas!$A$2:$A$114=J$5)*(Plantillas!$D$2:$D$114=$A24)*(Plantillas!$G$2:$G$114*N(J$6)+Plantillas!$H$2:$H$114))) -> 0 | K24: =IF(K$5="",0,SUMPRODUCT((Plantillas!$A$2:$A$114=K$5)*(Plantillas!$D$2:$D$114=$A24)*(Plantillas!$G$2:$G$114*N(K$6)+Plantillas!$H$2:$H$114))) -> 0 | L24: =IF(L$5="",0,SUMPRODUCT((Plantillas!$A$2:$A$114=L$5)*(Plantillas!$D$2:$D$114=$A24)*(Plantillas!$G$2:$G$114*N(L$6)+Plantillas!$H$2:$H$114))) -> 0 | ... R24: =IF(R$5="",0,SUMPRODUCT((Plantillas!$A$2:$A$114=R$5)*(Plantillas!$D$2:$D$114=$A24)*(Plantillas!$G$2:$G$114*N(R$6)+Plantillas!$H$2:$H$114))) -> 0 | S24: =SUM(E24:R24) -> 0 | T24: =IF(INDEX(Partidas!$F$2:$F$99,MATCH(A24,Partidas!$A$2:$A$99,0))="","",INDEX(Partidas!$F$2:$F$99,MATCH(A24,Partidas!$A$2:$A$99,0))) | U24: =IF(T24="",0,S24*T24) -> 0
A25: DEM-110 | B25: DEM | C25: =INDEX(Partidas!$D$2:$D$99,MATCH(A25,Partidas!$A$2:$A$99,0)) -> Desmontaje de puerta interior | D25: =INDEX(Partidas!$C$2:$C$99,MATCH(A25,Partidas!$A$2:$A$99,0)) -> ud | E25: =IF(E$5="",0,SUMPRODUCT((Plantillas!$A$2:$A$114=E$5)*(Plantillas!$D$2:$D$114=$A25)*(Plantillas!$G$2:$G$114*N(E$6)+Plantillas!$H$2:$H$114))) -> 0 | F25: =IF(F$5="",0,SUMPRODUCT((Plantillas!$A$2:$A$114=F$5)*(Plantillas!$D$2:$D$114=$A25)*(Plantillas!$G$2:$G$114*N(F$6)+Plantillas!$H$2:$H$114))) -> 0 | G25: =IF(G$5="",0,SUMPRODUCT((Plantillas!$A$2:$A$114=G$5)*(Plantillas!$D$2:$D$114=$A25)*(Plantillas!$G$2:$G$114*N(G$6)+Plantillas!$H$2:$H$114))) -> 0 | H25: =IF(H$5="",0,SUMPRODUCT((Plantillas!$A$2:$A$114=H$5)*(Plantillas!$D$2:$D$114=$A25)*(Plantillas!$G$2:$G$114*N(H$6)+Plantillas!$H$2:$H$114))) -> 0 | I25: =IF(I$5="",0,SUMPRODUCT((Plantillas!$A$2:$A$114=I$5)*(Plantillas!$D$2:$D$114=$A25)*(Plantillas!$G$2:$G$114*N(I$6)+Plantillas!$H$2:$H$114))) -> 0 | J25: =IF(J$5="",0,SUMPRODUCT((Plantillas!$A$2:$A$114=J$5)*(Plantillas!$D$2:$D$114=$A25)*(Plantillas!$G$2:$G$114*N(J$6)+Plantillas!$H$2:$H$114))) -> 0 | K25: =IF(K$5="",0,SUMPRODUCT((Plantillas!$A$2:$A$114=K$5)*(Plantillas!$D$2:$D$114=$A25)*(Plantillas!$G$2:$G$114*N(K$6)+Plantillas!$H$2:$H$114))) -> 0 | L25: =IF(L$5="",0,SUMPRODUCT((Plantillas!$A$2:$A$114=L$5)*(Plantillas!$D$2:$D$114=$A25)*(Plantillas!$G$2:$G$114*N(L$6)+Plantillas!$H$2:$H$114))) -> 0 | ... R25: =IF(R$5="",0,SUMPRODUCT((Plantillas!$A$2:$A$114=R$5)*(Plantillas!$D$2:$D$114=$A25)*(Plantillas!$G$2:$G$114*N(R$6)+Plantillas!$H$2:$H$114))) -> 0 | S25: =SUM(E25:R25) -> 0 | T25: =IF(INDEX(Partidas!$F$2:$F$99,MATCH(A25,Partidas!$A$2:$A$99,0))="","",INDEX(Partidas!$F$2:$F$99,MATCH(A25,Partidas!$A$2:$A$99,0))) | U25: =IF(T25="",0,S25*T25) -> 0
A26: DEM-120 | B26: DEM | C26: =INDEX(Partidas!$D$2:$D$99,MATCH(A26,Partidas!$A$2:$A$99,0)) -> Levantado de instalaciones existentes | D26: =INDEX(Partidas!$C$2:$C$99,MATCH(A26,Partidas!$A$2:$A$99,0)) -> pa | E26: =IF(E$5="",0,SUMPRODUCT((Plantillas!$A$2:$A$114=E$5)*(Plantillas!$D$2:$D$114=$A26)*(Plantillas!$G$2:$G$114*N(E$6)+Plantillas!$H$2:$H$114))) -> 1 | F26: =IF(F$5="",0,SUMPRODUCT((Plantillas!$A$2:$A$114=F$5)*(Plantillas!$D$2:$D$114=$A26)*(Plantillas!$G$2:$G$114*N(F$6)+Plantillas!$H$2:$H$114))) -> 0 | G26: =IF(G$5="",0,SUMPRODUCT((Plantillas!$A$2:$A$114=G$5)*(Plantillas!$D$2:$D$114=$A26)*(Plantillas!$G$2:$G$114*N(G$6)+Plantillas!$H$2:$H$114))) -> 0 | H26: =IF(H$5="",0,SUMPRODUCT((Plantillas!$A$2:$A$114=H$5)*(Plantillas!$D$2:$D$114=$A26)*(Plantillas!$G$2:$G$114*N(H$6)+Plantillas!$H$2:$H$114))) -> 0 | I26: =IF(I$5="",0,SUMPRODUCT((Plantillas!$A$2:$A$114=I$5)*(Plantillas!$D$2:$D$114=$A26)*(Plantillas!$G$2:$G$114*N(I$6)+Plantillas!$H$2:$H$114))) -> 0 | J26: =IF(J$5="",0,SUMPRODUCT((Plantillas!$A$2:$A$114=J$5)*(Plantillas!$D$2:$D$114=$A26)*(Plantillas!$G$2:$G$114*N(J$6)+Plantillas!$H$2:$H$114))) -> 0 | K26: =IF(K$5="",0,SUMPRODUCT((Plantillas!$A$2:$A$114=K$5)*(Plantillas!$D$2:$D$114=$A26)*(Plantillas!$G$2:$G$114*N(K$6)+Plantillas!$H$2:$H$114))) -> 0 | L26: =IF(L$5="",0,SUMPRODUCT((Plantillas!$A$2:$A$114=L$5)*(Plantillas!$D$2:$D$114=$A26)*(Plantillas!$G$2:$G$114*N(L$6)+Plantillas!$H$2:$H$114))) -> 0 | ... R26: =IF(R$5="",0,SUMPRODUCT((Plantillas!$A$2:$A$114=R$5)*(Plantillas!$D$2:$D$114=$A26)*(Plantillas!$G$2:$G$114*N(R$6)+Plantillas!$H$2:$H$114))) -> 0 | S26: =SUM(E26:R26) -> 1 | T26: =IF(INDEX(Partidas!$F$2:$F$99,MATCH(A26,Partidas!$A$2:$A$99,0))="","",INDEX(Partidas!$F$2:$F$99,MATCH(A26,Partidas!$A$2:$A$99,0))) | U26: =IF(T26="",0,S26*T26) -> 0
A27: TAB | C27: Tabiquería y trasdosados | U27: =SUM(U28:U30) -> 0
A28: TAB-010 | B28: TAB | C28: =INDEX(Partidas!$D$2:$D$99,MATCH(A28,Partidas!$A$2:$A$99,0)) -> Tabique PYL 2 placas por cara con aislamiento | D28: =INDEX(Partidas!$C$2:$C$99,MATCH(A28,Partidas!$A$2:$A$99,0)) -> m2 | E28: =IF(E$5="",0,SUMPRODUCT((Plantillas!$A$2:$A$114=E$5)*(Plantillas!$D$2:$D$114=$A28)*(Plantillas!$G$2:$G$114*N(E$6)+Plantillas!$H$2:$H$114))) -> 0 | F28: =IF(F$5="",0,SUMPRODUCT((Plantillas!$A$2:$A$114=F$5)*(Plantillas!$D$2:$D$114=$A28)*(Plantillas!$G$2:$G$114*N(F$6)+Plantillas!$H$2:$H$114))) -> 0 | G28: =IF(G$5="",0,SUMPRODUCT((Plantillas!$A$2:$A$114=G$5)*(Plantillas!$D$2:$D$114=$A28)*(Plantillas!$G$2:$G$114*N(G$6)+Plantillas!$H$2:$H$114))) -> 0 | H28: =IF(H$5="",0,SUMPRODUCT((Plantillas!$A$2:$A$114=H$5)*(Plantillas!$D$2:$D$114=$A28)*(Plantillas!$G$2:$G$114*N(H$6)+Plantillas!$H$2:$H$114))) -> 0 | I28: =IF(I$5="",0,SUMPRODUCT((Plantillas!$A$2:$A$114=I$5)*(Plantillas!$D$2:$D$114=$A28)*(Plantillas!$G$2:$G$114*N(I$6)+Plantillas!$H$2:$H$114))) -> 0 | J28: =IF(J$5="",0,SUMPRODUCT((Plantillas!$A$2:$A$114=J$5)*(Plantillas!$D$2:$D$114=$A28)*(Plantillas!$G$2:$G$114*N(J$6)+Plantillas!$H$2:$H$114))) -> 0 | K28: =IF(K$5="",0,SUMPRODUCT((Plantillas!$A$2:$A$114=K$5)*(Plantillas!$D$2:$D$114=$A28)*(Plantillas!$G$2:$G$114*N(K$6)+Plantillas!$H$2:$H$114))) -> 0 | L28: =IF(L$5="",0,SUMPRODUCT((Plantillas!$A$2:$A$114=L$5)*(Plantillas!$D$2:$D$114=$A28)*(Plantillas!$G$2:$G$114*N(L$6)+Plantillas!$H$2:$H$114))) -> 0 | ... R28: =IF(R$5="",0,SUMPRODUCT((Plantillas!$A$2:$A$114=R$5)*(Plantillas!$D$2:$D$114=$A28)*(Plantillas!$G$2:$G$114*N(R$6)+Plantillas!$H$2:$H$114))) -> 0 | S28: =SUM(E28:R28) -> 0 | T28: =IF(INDEX(Partidas!$F$2:$F$99,MATCH(A28,Partidas!$A$2:$A$99,0))="","",INDEX(Partidas!$F$2:$F$99,MATCH(A28,Partidas!$A$2:$A$99,0))) -> 60 | U28: =IF(T28="",0,S28*T28) -> 0
A29: TAB-020 | B29: TAB | C29: =INDEX(Partidas!$D$2:$D$99,MATCH(A29,Partidas!$A$2:$A$99,0)) -> Trasdosado PYL 1 placa sobre perfilería con aislamiento | D29: =INDEX(Partidas!$C$2:$C$99,MATCH(A29,Partidas!$A$2:$A$99,0)) -> m2 | E29: =IF(E$5="",0,SUMPRODUCT((Plantillas!$A$2:$A$114=E$5)*(Plantillas!$D$2:$D$114=$A29)*(Plantillas!$G$2:$G$114*N(E$6)+Plantillas!$H$2:$H$114))) -> 0 | F29: =IF(F$5="",0,SUMPRODUCT((Plantillas!$A$2:$A$114=F$5)*(Plantillas!$D$2:$D$114=$A29)*(Plantillas!$G$2:$G$114*N(F$6)+Plantillas!$H$2:$H$114))) -> 0 | G29: =IF(G$5="",0,SUMPRODUCT((Plantillas!$A$2:$A$114=G$5)*(Plantillas!$D$2:$D$114=$A29)*(Plantillas!$G$2:$G$114*N(G$6)+Plantillas!$H$2:$H$114))) -> 0 | H29: =IF(H$5="",0,SUMPRODUCT((Plantillas!$A$2:$A$114=H$5)*(Plantillas!$D$2:$D$114=$A29)*(Plantillas!$G$2:$G$114*N(H$6)+Plantillas!$H$2:$H$114))) -> 0 | I29: =IF(I$5="",0,SUMPRODUCT((Plantillas!$A$2:$A$114=I$5)*(Plantillas!$D$2:$D$114=$A29)*(Plantillas!$G$2:$G$114*N(I$6)+Plantillas!$H$2:$H$114))) -> 0 | J29: =IF(J$5="",0,SUMPRODUCT((Plantillas!$A$2:$A$114=J$5)*(Plantillas!$D$2:$D$114=$A29)*(Plantillas!$G$2:$G$114*N(J$6)+Plantillas!$H$2:$H$114))) -> 0 | K29: =IF(K$5="",0,SUMPRODUCT((Plantillas!$A$2:$A$114=K$5)*(Plantillas!$D$2:$D$114=$A29)*(Plantillas!$G$2:$G$114*N(K$6)+Plantillas!$H$2:$H$114))) -> 0 | L29: =IF(L$5="",0,SUMPRODUCT((Plantillas!$A$2:$A$114=L$5)*(Plantillas!$D$2:$D$114=$A29)*(Plantillas!$G$2:$G$114*N(L$6)+Plantillas!$H$2:$H$114))) -> 0 | ... R29: =IF(R$5="",0,SUMPRODUCT((Plantillas!$A$2:$A$114=R$5)*(Plantillas!$D$2:$D$114=$A29)*(Plantillas!$G$2:$G$114*N(R$6)+Plantillas!$H$2:$H$114))) -> 0 | S29: =SUM(E29:R29) -> 0 | T29: =IF(INDEX(Partidas!$F$2:$F$99,MATCH(A29,Partidas!$A$2:$A$99,0))="","",INDEX(Partidas!$F$2:$F$99,MATCH(A29,Partidas!$A$2:$A$99,0))) -> 40 | U29: =IF(T29="",0,S29*T29) -> 0
A30: TAB-030 | B30: TAB | C30: =INDEX(Partidas!$D$2:$D$99,MATCH(A30,Partidas!$A$2:$A$99,0)) -> Trasdosado PYL 1 placa directo | D30: =INDEX(Partidas!$C$2:$C$99,MATCH(A30,Partidas!$A$2:$A$99,0)) -> m2 | E30: =IF(E$5="",0,SUMPRODUCT((Plantillas!$A$2:$A$114=E$5)*(Plantillas!$D$2:$D$114=$A30)*(Plantillas!$G$2:$G$114*N(E$6)+Plantillas!$H$2:$H$114))) -> 0 | F30: =IF(F$5="",0,SUMPRODUCT((Plantillas!$A$2:$A$114=F$5)*(Plantillas!$D$2:$D$114=$A30)*(Plantillas!$G$2:$G$114*N(F$6)+Plantillas!$H$2:$H$114))) -> 0 | G30: =IF(G$5="",0,SUMPRODUCT((Plantillas!$A$2:$A$114=G$5)*(Plantillas!$D$2:$D$114=$A30)*(Plantillas!$G$2:$G$114*N(G$6)+Plantillas!$H$2:$H$114))) -> 0 | H30: =IF(H$5="",0,SUMPRODUCT((Plantillas!$A$2:$A$114=H$5)*(Plantillas!$D$2:$D$114=$A30)*(Plantillas!$G$2:$G$114*N(H$6)+Plantillas!$H$2:$H$114))) -> 0 | I30: =IF(I$5="",0,SUMPRODUCT((Plantillas!$A$2:$A$114=I$5)*(Plantillas!$D$2:$D$114=$A30)*(Plantillas!$G$2:$G$114*N(I$6)+Plantillas!$H$2:$H$114))) -> 0 | J30: =IF(J$5="",0,SUMPRODUCT((Plantillas!$A$2:$A$114=J$5)*(Plantillas!$D$2:$D$114=$A30)*(Plantillas!$G$2:$G$114*N(J$6)+Plantillas!$H$2:$H$114))) -> 0 | K30: =IF(K$5="",0,SUMPRODUCT((Plantillas!$A$2:$A$114=K$5)*(Plantillas!$D$2:$D$114=$A30)*(Plantillas!$G$2:$G$114*N(K$6)+Plantillas!$H$2:$H$114))) -> 0 | L30: =IF(L$5="",0,SUMPRODUCT((Plantillas!$A$2:$A$114=L$5)*(Plantillas!$D$2:$D$114=$A30)*(Plantillas!$G$2:$G$114*N(L$6)+Plantillas!$H$2:$H$114))) -> 0 | ... R30: =IF(R$5="",0,SUMPRODUCT((Plantillas!$A$2:$A$114=R$5)*(Plantillas!$D$2:$D$114=$A30)*(Plantillas!$G$2:$G$114*N(R$6)+Plantillas!$H$2:$H$114))) -> 0 | S30: =SUM(E30:R30) -> 0 | T30: =IF(INDEX(Partidas!$F$2:$F$99,MATCH(A30,Partidas!$A$2:$A$99,0))="","",INDEX(Partidas!$F$2:$F$99,MATCH(A30,Partidas!$A$2:$A$99,0))) -> 30 | U30: =IF(T30="",0,S30*T30) -> 0
A31: TEC | C31: Falsos techos y molduras | U31: =SUM(U32:U36) -> 2772
A32: TEC-010 | B32: TEC | C32: =INDEX(Partidas!$D$2:$D$99,MATCH(A32,Partidas!$A$2:$A$99,0)) -> Falso techo continuo PYL | D32: =INDEX(Partidas!$C$2:$C$99,MATCH(A32,Partidas!$A$2:$A$99,0)) -> m2 | E32: =IF(E$5="",0,SUMPRODUCT((Plantillas!$A$2:$A$114=E$5)*(Plantillas!$D$2:$D$114=$A32)*(Plantillas!$G$2:$G$114*N(E$6)+Plantillas!$H$2:$H$114))) -> 0 | F32: =IF(F$5="",0,SUMPRODUCT((Plantillas!$A$2:$A$114=F$5)*(Plantillas!$D$2:$D$114=$A32)*(Plantillas!$G$2:$G$114*N(F$6)+Plantillas!$H$2:$H$114))) -> 24 | G32: =IF(G$5="",0,SUMPRODUCT((Plantillas!$A$2:$A$114=G$5)*(Plantillas!$D$2:$D$114=$A32)*(Plantillas!$G$2:$G$114*N(G$6)+Plantillas!$H$2:$H$114))) -> 15 | H32: =IF(H$5="",0,SUMPRODUCT((Plantillas!$A$2:$A$114=H$5)*(Plantillas!$D$2:$D$114=$A32)*(Plantillas!$G$2:$G$114*N(H$6)+Plantillas!$H$2:$H$114))) -> 10 | I32: =IF(I$5="",0,SUMPRODUCT((Plantillas!$A$2:$A$114=I$5)*(Plantillas!$D$2:$D$114=$A32)*(Plantillas!$G$2:$G$114*N(I$6)+Plantillas!$H$2:$H$114))) -> 10 | J32: =IF(J$5="",0,SUMPRODUCT((Plantillas!$A$2:$A$114=J$5)*(Plantillas!$D$2:$D$114=$A32)*(Plantillas!$G$2:$G$114*N(J$6)+Plantillas!$H$2:$H$114))) -> 7 | K32: =IF(K$5="",0,SUMPRODUCT((Plantillas!$A$2:$A$114=K$5)*(Plantillas!$D$2:$D$114=$A32)*(Plantillas!$G$2:$G$114*N(K$6)+Plantillas!$H$2:$H$114))) -> 4 | L32: =IF(L$5="",0,SUMPRODUCT((Plantillas!$A$2:$A$114=L$5)*(Plantillas!$D$2:$D$114=$A32)*(Plantillas!$G$2:$G$114*N(L$6)+Plantillas!$H$2:$H$114))) -> 0 | ... R32: =IF(R$5="",0,SUMPRODUCT((Plantillas!$A$2:$A$114=R$5)*(Plantillas!$D$2:$D$114=$A32)*(Plantillas!$G$2:$G$114*N(R$6)+Plantillas!$H$2:$H$114))) -> 0 | S32: =SUM(E32:R32) -> 70 | T32: =IF(INDEX(Partidas!$F$2:$F$99,MATCH(A32,Partidas!$A$2:$A$99,0))="","",INDEX(Partidas!$F$2:$F$99,MATCH(A32,Partidas!$A$2:$A$99,0))) -> 30 | U32: =IF(T32="",0,S32*T32) -> 2100
A33: TEC-020 | B33: TEC | C33: =INDEX(Partidas!$D$2:$D$99,MATCH(A33,Partidas!$A$2:$A$99,0)) -> Falso techo continuo PYL hidrófugo | D33: =INDEX(Partidas!$C$2:$C$99,MATCH(A33,Partidas!$A$2:$A$99,0)) -> m2 | E33: =IF(E$5="",0,SUMPRODUCT((Plantillas!$A$2:$A$114=E$5)*(Plantillas!$D$2:$D$114=$A33)*(Plantillas!$G$2:$G$114*N(E$6)+Plantillas!$H$2:$H$114))) -> 0 | F33: =IF(F$5="",0,SUMPRODUCT((Plantillas!$A$2:$A$114=F$5)*(Plantillas!$D$2:$D$114=$A33)*(Plantillas!$G$2:$G$114*N(F$6)+Plantillas!$H$2:$H$114))) -> 0 | G33: =IF(G$5="",0,SUMPRODUCT((Plantillas!$A$2:$A$114=G$5)*(Plantillas!$D$2:$D$114=$A33)*(Plantillas!$G$2:$G$114*N(G$6)+Plantillas!$H$2:$H$114))) -> 0 | H33: =IF(H$5="",0,SUMPRODUCT((Plantillas!$A$2:$A$114=H$5)*(Plantillas!$D$2:$D$114=$A33)*(Plantillas!$G$2:$G$114*N(H$6)+Plantillas!$H$2:$H$114))) -> 0 | I33: =IF(I$5="",0,SUMPRODUCT((Plantillas!$A$2:$A$114=I$5)*(Plantillas!$D$2:$D$114=$A33)*(Plantillas!$G$2:$G$114*N(I$6)+Plantillas!$H$2:$H$114))) -> 0 | J33: =IF(J$5="",0,SUMPRODUCT((Plantillas!$A$2:$A$114=J$5)*(Plantillas!$D$2:$D$114=$A33)*(Plantillas!$G$2:$G$114*N(J$6)+Plantillas!$H$2:$H$114))) -> 0 | K33: =IF(K$5="",0,SUMPRODUCT((Plantillas!$A$2:$A$114=K$5)*(Plantillas!$D$2:$D$114=$A33)*(Plantillas!$G$2:$G$114*N(K$6)+Plantillas!$H$2:$H$114))) -> 0 | L33: =IF(L$5="",0,SUMPRODUCT((Plantillas!$A$2:$A$114=L$5)*(Plantillas!$D$2:$D$114=$A33)*(Plantillas!$G$2:$G$114*N(L$6)+Plantillas!$H$2:$H$114))) -> 9 | ... R33: =IF(R$5="",0,SUMPRODUCT((Plantillas!$A$2:$A$114=R$5)*(Plantillas!$D$2:$D$114=$A33)*(Plantillas!$G$2:$G$114*N(R$6)+Plantillas!$H$2:$H$114))) -> 0 | S33: =SUM(E33:R33) -> 21 | T33: =IF(INDEX(Partidas!$F$2:$F$99,MATCH(A33,Partidas!$A$2:$A$99,0))="","",INDEX(Partidas!$F$2:$F$99,MATCH(A33,Partidas!$A$2:$A$99,0))) -> 32 | U33: =IF(T33="",0,S33*T33) -> 672
A34: TEC-030 | B34: TEC | C34: =INDEX(Partidas!$D$2:$D$99,MATCH(A34,Partidas!$A$2:$A$99,0)) -> Candileja o foseado perimetral para LED | D34: =INDEX(Partidas!$C$2:$C$99,MATCH(A34,Partidas!$A$2:$A$99,0)) -> m | E34: =IF(E$5="",0,SUMPRODUCT((Plantillas!$A$2:$A$114=E$5)*(Plantillas!$D$2:$D$114=$A34)*(Plantillas!$G$2:$G$114*N(E$6)+Plantillas!$H$2:$H$114))) -> 0 | F34: =IF(F$5="",0,SUMPRODUCT((Plantillas!$A$2:$A$114=F$5)*(Plantillas!$D$2:$D$114=$A34)*(Plantillas!$G$2:$G$114*N(F$6)+Plantillas!$H$2:$H$114))) -> 0 | G34: =IF(G$5="",0,SUMPRODUCT((Plantillas!$A$2:$A$114=G$5)*(Plantillas!$D$2:$D$114=$A34)*(Plantillas!$G$2:$G$114*N(G$6)+Plantillas!$H$2:$H$114))) -> 0 | H34: =IF(H$5="",0,SUMPRODUCT((Plantillas!$A$2:$A$114=H$5)*(Plantillas!$D$2:$D$114=$A34)*(Plantillas!$G$2:$G$114*N(H$6)+Plantillas!$H$2:$H$114))) -> 0 | I34: =IF(I$5="",0,SUMPRODUCT((Plantillas!$A$2:$A$114=I$5)*(Plantillas!$D$2:$D$114=$A34)*(Plantillas!$G$2:$G$114*N(I$6)+Plantillas!$H$2:$H$114))) -> 0 | J34: =IF(J$5="",0,SUMPRODUCT((Plantillas!$A$2:$A$114=J$5)*(Plantillas!$D$2:$D$114=$A34)*(Plantillas!$G$2:$G$114*N(J$6)+Plantillas!$H$2:$H$114))) -> 0 | K34: =IF(K$5="",0,SUMPRODUCT((Plantillas!$A$2:$A$114=K$5)*(Plantillas!$D$2:$D$114=$A34)*(Plantillas!$G$2:$G$114*N(K$6)+Plantillas!$H$2:$H$114))) -> 0 | L34: =IF(L$5="",0,SUMPRODUCT((Plantillas!$A$2:$A$114=L$5)*(Plantillas!$D$2:$D$114=$A34)*(Plantillas!$G$2:$G$114*N(L$6)+Plantillas!$H$2:$H$114))) -> 0 | ... R34: =IF(R$5="",0,SUMPRODUCT((Plantillas!$A$2:$A$114=R$5)*(Plantillas!$D$2:$D$114=$A34)*(Plantillas!$G$2:$G$114*N(R$6)+Plantillas!$H$2:$H$114))) -> 0 | S34: =SUM(E34:R34) -> 0 | T34: =IF(INDEX(Partidas!$F$2:$F$99,MATCH(A34,Partidas!$A$2:$A$99,0))="","",INDEX(Partidas!$F$2:$F$99,MATCH(A34,Partidas!$A$2:$A$99,0))) -> 40 | U34: =IF(T34="",0,S34*T34) -> 0
A35: TEC-040 | B35: TEC | C35: =INDEX(Partidas!$D$2:$D$99,MATCH(A35,Partidas!$A$2:$A$99,0)) -> Moldura decorativa de escayola | D35: =INDEX(Partidas!$C$2:$C$99,MATCH(A35,Partidas!$A$2:$A$99,0)) -> m | E35: =IF(E$5="",0,SUMPRODUCT((Plantillas!$A$2:$A$114=E$5)*(Plantillas!$D$2:$D$114=$A35)*(Plantillas!$G$2:$G$114*N(E$6)+Plantillas!$H$2:$H$114))) -> 0 | F35: =IF(F$5="",0,SUMPRODUCT((Plantillas!$A$2:$A$114=F$5)*(Plantillas!$D$2:$D$114=$A35)*(Plantillas!$G$2:$G$114*N(F$6)+Plantillas!$H$2:$H$114))) -> 0 | G35: =IF(G$5="",0,SUMPRODUCT((Plantillas!$A$2:$A$114=G$5)*(Plantillas!$D$2:$D$114=$A35)*(Plantillas!$G$2:$G$114*N(G$6)+Plantillas!$H$2:$H$114))) -> 0 | H35: =IF(H$5="",0,SUMPRODUCT((Plantillas!$A$2:$A$114=H$5)*(Plantillas!$D$2:$D$114=$A35)*(Plantillas!$G$2:$G$114*N(H$6)+Plantillas!$H$2:$H$114))) -> 0 | I35: =IF(I$5="",0,SUMPRODUCT((Plantillas!$A$2:$A$114=I$5)*(Plantillas!$D$2:$D$114=$A35)*(Plantillas!$G$2:$G$114*N(I$6)+Plantillas!$H$2:$H$114))) -> 0 | J35: =IF(J$5="",0,SUMPRODUCT((Plantillas!$A$2:$A$114=J$5)*(Plantillas!$D$2:$D$114=$A35)*(Plantillas!$G$2:$G$114*N(J$6)+Plantillas!$H$2:$H$114))) -> 0 | K35: =IF(K$5="",0,SUMPRODUCT((Plantillas!$A$2:$A$114=K$5)*(Plantillas!$D$2:$D$114=$A35)*(Plantillas!$G$2:$G$114*N(K$6)+Plantillas!$H$2:$H$114))) -> 0 | L35: =IF(L$5="",0,SUMPRODUCT((Plantillas!$A$2:$A$114=L$5)*(Plantillas!$D$2:$D$114=$A35)*(Plantillas!$G$2:$G$114*N(L$6)+Plantillas!$H$2:$H$114))) -> 0 | ... R35: =IF(R$5="",0,SUMPRODUCT((Plantillas!$A$2:$A$114=R$5)*(Plantillas!$D$2:$D$114=$A35)*(Plantillas!$G$2:$G$114*N(R$6)+Plantillas!$H$2:$H$114))) -> 0 | S35: =SUM(E35:R35) -> 0 | T35: =IF(INDEX(Partidas!$F$2:$F$99,MATCH(A35,Partidas!$A$2:$A$99,0))="","",INDEX(Partidas!$F$2:$F$99,MATCH(A35,Partidas!$A$2:$A$99,0))) -> 20 | U35: =IF(T35="",0,S35*T35) -> 0
A36: TEC-050 | B36: TEC | C36: =INDEX(Partidas!$D$2:$D$99,MATCH(A36,Partidas!$A$2:$A$99,0)) -> Registro en falso techo | D36: =INDEX(Partidas!$C$2:$C$99,MATCH(A36,Partidas!$A$2:$A$99,0)) -> ud | E36: =IF(E$5="",0,SUMPRODUCT((Plantillas!$A$2:$A$114=E$5)*(Plantillas!$D$2:$D$114=$A36)*(Plantillas!$G$2:$G$114*N(E$6)+Plantillas!$H$2:$H$114))) -> 0 | F36: =IF(F$5="",0,SUMPRODUCT((Plantillas!$A$2:$A$114=F$5)*(Plantillas!$D$2:$D$114=$A36)*(Plantillas!$G$2:$G$114*N(F$6)+Plantillas!$H$2:$H$114))) -> 0 | G36: =IF(G$5="",0,SUMPRODUCT((Plantillas!$A$2:$A$114=G$5)*(Plantillas!$D$2:$D$114=$A36)*(Plantillas!$G$2:$G$114*N(G$6)+Plantillas!$H$2:$H$114))) -> 0 | H36: =IF(H$5="",0,SUMPRODUCT((Plantillas!$A$2:$A$114=H$5)*(Plantillas!$D$2:$D$114=$A36)*(Plantillas!$G$2:$G$114*N(H$6)+Plantillas!$H$2:$H$114))) -> 0 | I36: =IF(I$5="",0,SUMPRODUCT((Plantillas!$A$2:$A$114=I$5)*(Plantillas!$D$2:$D$114=$A36)*(Plantillas!$G$2:$G$114*N(I$6)+Plantillas!$H$2:$H$114))) -> 0 | J36: =IF(J$5="",0,SUMPRODUCT((Plantillas!$A$2:$A$114=J$5)*(Plantillas!$D$2:$D$114=$A36)*(Plantillas!$G$2:$G$114*N(J$6)+Plantillas!$H$2:$H$114))) -> 0 | K36: =IF(K$5="",0,SUMPRODUCT((Plantillas!$A$2:$A$114=K$5)*(Plantillas!$D$2:$D$114=$A36)*(Plantillas!$G$2:$G$114*N(K$6)+Plantillas!$H$2:$H$114))) -> 0 | L36: =IF(L$5="",0,SUMPRODUCT((Plantillas!$A$2:$A$114=L$5)*(Plantillas!$D$2:$D$114=$A36)*(Plantillas!$G$2:$G$114*N(L$6)+Plantillas!$H$2:$H$114))) -> 0 | ... R36: =IF(R$5="",0,SUMPRODUCT((Plantillas!$A$2:$A$114=R$5)*(Plantillas!$D$2:$D$114=$A36)*(Plantillas!$G$2:$G$114*N(R$6)+Plantillas!$H$2:$H$114))) -> 0 | S36: =SUM(E36:R36) -> 0 | T36: =IF(INDEX(Partidas!$F$2:$F$99,MATCH(A36,Partidas!$A$2:$A$99,0))="","",INDEX(Partidas!$F$2:$F$99,MATCH(A36,Partidas!$A$2:$A$99,0))) | U36: =IF(T36="",0,S36*T36) -> 0
A37: IMP | C37: Aislamientos e impermeabilizaciones | U37: =SUM(U38:U40) -> 0
A38: IMP-010 | B38: IMP | C38: =INDEX(Partidas!$D$2:$D$99,MATCH(A38,Partidas!$A$2:$A$99,0)) -> Impermeabilización de suelo en zona húmeda | D38: =INDEX(Partidas!$C$2:$C$99,MATCH(A38,Partidas!$A$2:$A$99,0)) -> m2 | E38: =IF(E$5="",0,SUMPRODUCT((Plantillas!$A$2:$A$114=E$5)*(Plantillas!$D$2:$D$114=$A38)*(Plantillas!$G$2:$G$114*N(E$6)+Plantillas!$H$2:$H$114))) -> 0 | F38: =IF(F$5="",0,SUMPRODUCT((Plantillas!$A$2:$A$114=F$5)*(Plantillas!$D$2:$D$114=$A38)*(Plantillas!$G$2:$G$114*N(F$6)+Plantillas!$H$2:$H$114))) -> 0 | G38: =IF(G$5="",0,SUMPRODUCT((Plantillas!$A$2:$A$114=G$5)*(Plantillas!$D$2:$D$114=$A38)*(Plantillas!$G$2:$G$114*N(G$6)+Plantillas!$H$2:$H$114))) -> 0 | H38: =IF(H$5="",0,SUMPRODUCT((Plantillas!$A$2:$A$114=H$5)*(Plantillas!$D$2:$D$114=$A38)*(Plantillas!$G$2:$G$114*N(H$6)+Plantillas!$H$2:$H$114))) -> 0 | I38: =IF(I$5="",0,SUMPRODUCT((Plantillas!$A$2:$A$114=I$5)*(Plantillas!$D$2:$D$114=$A38)*(Plantillas!$G$2:$G$114*N(I$6)+Plantillas!$H$2:$H$114))) -> 0 | J38: =IF(J$5="",0,SUMPRODUCT((Plantillas!$A$2:$A$114=J$5)*(Plantillas!$D$2:$D$114=$A38)*(Plantillas!$G$2:$G$114*N(J$6)+Plantillas!$H$2:$H$114))) -> 0 | K38: =IF(K$5="",0,SUMPRODUCT((Plantillas!$A$2:$A$114=K$5)*(Plantillas!$D$2:$D$114=$A38)*(Plantillas!$G$2:$G$114*N(K$6)+Plantillas!$H$2:$H$114))) -> 0 | L38: =IF(L$5="",0,SUMPRODUCT((Plantillas!$A$2:$A$114=L$5)*(Plantillas!$D$2:$D$114=$A38)*(Plantillas!$G$2:$G$114*N(L$6)+Plantillas!$H$2:$H$114))) -> 0 | ... R38: =IF(R$5="",0,SUMPRODUCT((Plantillas!$A$2:$A$114=R$5)*(Plantillas!$D$2:$D$114=$A38)*(Plantillas!$G$2:$G$114*N(R$6)+Plantillas!$H$2:$H$114))) -> 0 | S38: =SUM(E38:R38) -> 12 | T38: =IF(INDEX(Partidas!$F$2:$F$99,MATCH(A38,Partidas!$A$2:$A$99,0))="","",INDEX(Partidas!$F$2:$F$99,MATCH(A38,Partidas!$A$2:$A$99,0))) | U38: =IF(T38="",0,S38*T38) -> 0
A39: IMP-020 | B39: IMP | C39: =INDEX(Partidas!$D$2:$D$99,MATCH(A39,Partidas!$A$2:$A$99,0)) -> Desagüe lineal y manta impermeable para ducha de obra | D39: =INDEX(Partidas!$C$2:$C$99,MATCH(A39,Partidas!$A$2:$A$99,0)) -> ud | E39: =IF(E$5="",0,SUMPRODUCT((Plantillas!$A$2:$A$114=E$5)*(Plantillas!$D$2:$D$114=$A39)*(Plantillas!$G$2:$G$114*N(E$6)+Plantillas!$H$2:$H$114))) -> 0 | F39: =IF(F$5="",0,SUMPRODUCT((Plantillas!$A$2:$A$114=F$5)*(Plantillas!$D$2:$D$114=$A39)*(Plantillas!$G$2:$G$114*N(F$6)+Plantillas!$H$2:$H$114))) -> 0 | G39: =IF(G$5="",0,SUMPRODUCT((Plantillas!$A$2:$A$114=G$5)*(Plantillas!$D$2:$D$114=$A39)*(Plantillas!$G$2:$G$114*N(G$6)+Plantillas!$H$2:$H$114))) -> 0 | H39: =IF(H$5="",0,SUMPRODUCT((Plantillas!$A$2:$A$114=H$5)*(Plantillas!$D$2:$D$114=$A39)*(Plantillas!$G$2:$G$114*N(H$6)+Plantillas!$H$2:$H$114))) -> 0 | I39: =IF(I$5="",0,SUMPRODUCT((Plantillas!$A$2:$A$114=I$5)*(Plantillas!$D$2:$D$114=$A39)*(Plantillas!$G$2:$G$114*N(I$6)+Plantillas!$H$2:$H$114))) -> 0 | J39: =IF(J$5="",0,SUMPRODUCT((Plantillas!$A$2:$A$114=J$5)*(Plantillas!$D$2:$D$114=$A39)*(Plantillas!$G$2:$G$114*N(J$6)+Plantillas!$H$2:$H$114))) -> 0 | K39: =IF(K$5="",0,SUMPRODUCT((Plantillas!$A$2:$A$114=K$5)*(Plantillas!$D$2:$D$114=$A39)*(Plantillas!$G$2:$G$114*N(K$6)+Plantillas!$H$2:$H$114))) -> 0 | L39: =IF(L$5="",0,SUMPRODUCT((Plantillas!$A$2:$A$114=L$5)*(Plantillas!$D$2:$D$114=$A39)*(Plantillas!$G$2:$G$114*N(L$6)+Plantillas!$H$2:$H$114))) -> 0 | ... R39: =IF(R$5="",0,SUMPRODUCT((Plantillas!$A$2:$A$114=R$5)*(Plantillas!$D$2:$D$114=$A39)*(Plantillas!$G$2:$G$114*N(R$6)+Plantillas!$H$2:$H$114))) -> 0 | S39: =SUM(E39:R39) -> 0 | T39: =IF(INDEX(Partidas!$F$2:$F$99,MATCH(A39,Partidas!$A$2:$A$99,0))="","",INDEX(Partidas!$F$2:$F$99,MATCH(A39,Partidas!$A$2:$A$99,0))) -> 340 | U39: =IF(T39="",0,S39*T39) -> 0
A40: IMP-030 | B40: IMP | C40: =INDEX(Partidas!$D$2:$D$99,MATCH(A40,Partidas!$A$2:$A$99,0)) -> Lámina anti-impacto bajo pavimento | D40: =INDEX(Partidas!$C$2:$C$99,MATCH(A40,Partidas!$A$2:$A$99,0)) -> m2 | E40: =IF(E$5="",0,SUMPRODUCT((Plantillas!$A$2:$A$114=E$5)*(Plantillas!$D$2:$D$114=$A40)*(Plantillas!$G$2:$G$114*N(E$6)+Plantillas!$H$2:$H$114))) -> 0 | F40: =IF(F$5="",0,SUMPRODUCT((Plantillas!$A$2:$A$114=F$5)*(Plantillas!$D$2:$D$114=$A40)*(Plantillas!$G$2:$G$114*N(F$6)+Plantillas!$H$2:$H$114))) -> 0 | G40: =IF(G$5="",0,SUMPRODUCT((Plantillas!$A$2:$A$114=G$5)*(Plantillas!$D$2:$D$114=$A40)*(Plantillas!$G$2:$G$114*N(G$6)+Plantillas!$H$2:$H$114))) -> 0 | H40: =IF(H$5="",0,SUMPRODUCT((Plantillas!$A$2:$A$114=H$5)*(Plantillas!$D$2:$D$114=$A40)*(Plantillas!$G$2:$G$114*N(H$6)+Plantillas!$H$2:$H$114))) -> 0 | I40: =IF(I$5="",0,SUMPRODUCT((Plantillas!$A$2:$A$114=I$5)*(Plantillas!$D$2:$D$114=$A40)*(Plantillas!$G$2:$G$114*N(I$6)+Plantillas!$H$2:$H$114))) -> 0 | J40: =IF(J$5="",0,SUMPRODUCT((Plantillas!$A$2:$A$114=J$5)*(Plantillas!$D$2:$D$114=$A40)*(Plantillas!$G$2:$G$114*N(J$6)+Plantillas!$H$2:$H$114))) -> 0 | K40: =IF(K$5="",0,SUMPRODUCT((Plantillas!$A$2:$A$114=K$5)*(Plantillas!$D$2:$D$114=$A40)*(Plantillas!$G$2:$G$114*N(K$6)+Plantillas!$H$2:$H$114))) -> 0 | L40: =IF(L$5="",0,SUMPRODUCT((Plantillas!$A$2:$A$114=L$5)*(Plantillas!$D$2:$D$114=$A40)*(Plantillas!$G$2:$G$114*N(L$6)+Plantillas!$H$2:$H$114))) -> 0 | ... R40: =IF(R$5="",0,SUMPRODUCT((Plantillas!$A$2:$A$114=R$5)*(Plantillas!$D$2:$D$114=$A40)*(Plantillas!$G$2:$G$114*N(R$6)+Plantillas!$H$2:$H$114))) -> 0 | S40: =SUM(E40:R40) -> 0 | T40: =IF(INDEX(Partidas!$F$2:$F$99,MATCH(A40,Partidas!$A$2:$A$99,0))="","",INDEX(Partidas!$F$2:$F$99,MATCH(A40,Partidas!$A$2:$A$99,0))) | U40: =IF(T40="",0,S40*T40) -> 0
A41: REV | C41: Revestimientos de paredes | U41: =SUM(U42:U46) -> 3483
A42: REV-010 | B42: REV | C42: =INDEX(Partidas!$D$2:$D$99,MATCH(A42,Partidas!$A$2:$A$99,0)) -> Alicatado de gres porcelánico | D42: =INDEX(Partidas!$C$2:$C$99,MATCH(A42,Partidas!$A$2:$A$99,0)) -> m2 | E42: =IF(E$5="",0,SUMPRODUCT((Plantillas!$A$2:$A$114=E$5)*(Plantillas!$D$2:$D$114=$A42)*(Plantillas!$G$2:$G$114*N(E$6)+Plantillas!$H$2:$H$114))) -> 0 | F42: =IF(F$5="",0,SUMPRODUCT((Plantillas!$A$2:$A$114=F$5)*(Plantillas!$D$2:$D$114=$A42)*(Plantillas!$G$2:$G$114*N(F$6)+Plantillas!$H$2:$H$114))) -> 0 | G42: =IF(G$5="",0,SUMPRODUCT((Plantillas!$A$2:$A$114=G$5)*(Plantillas!$D$2:$D$114=$A42)*(Plantillas!$G$2:$G$114*N(G$6)+Plantillas!$H$2:$H$114))) -> 0 | H42: =IF(H$5="",0,SUMPRODUCT((Plantillas!$A$2:$A$114=H$5)*(Plantillas!$D$2:$D$114=$A42)*(Plantillas!$G$2:$G$114*N(H$6)+Plantillas!$H$2:$H$114))) -> 0 | I42: =IF(I$5="",0,SUMPRODUCT((Plantillas!$A$2:$A$114=I$5)*(Plantillas!$D$2:$D$114=$A42)*(Plantillas!$G$2:$G$114*N(I$6)+Plantillas!$H$2:$H$114))) -> 0 | J42: =IF(J$5="",0,SUMPRODUCT((Plantillas!$A$2:$A$114=J$5)*(Plantillas!$D$2:$D$114=$A42)*(Plantillas!$G$2:$G$114*N(J$6)+Plantillas!$H$2:$H$114))) -> 0 | K42: =IF(K$5="",0,SUMPRODUCT((Plantillas!$A$2:$A$114=K$5)*(Plantillas!$D$2:$D$114=$A42)*(Plantillas!$G$2:$G$114*N(K$6)+Plantillas!$H$2:$H$114))) -> 0 | L42: =IF(L$5="",0,SUMPRODUCT((Plantillas!$A$2:$A$114=L$5)*(Plantillas!$D$2:$D$114=$A42)*(Plantillas!$G$2:$G$114*N(L$6)+Plantillas!$H$2:$H$114))) -> 5.4 | ... R42: =IF(R$5="",0,SUMPRODUCT((Plantillas!$A$2:$A$114=R$5)*(Plantillas!$D$2:$D$114=$A42)*(Plantillas!$G$2:$G$114*N(R$6)+Plantillas!$H$2:$H$114))) -> 0 | S42: =SUM(E42:R42) -> 38.7 | T42: =IF(INDEX(Partidas!$F$2:$F$99,MATCH(A42,Partidas!$A$2:$A$99,0))="","",INDEX(Partidas!$F$2:$F$99,MATCH(A42,Partidas!$A$2:$A$99,0))) -> 90 | U42: =IF(T42="",0,S42*T42) -> 3483
A43: REV-020 | B43: REV | C43: =INDEX(Partidas!$D$2:$D$99,MATCH(A43,Partidas!$A$2:$A$99,0)) -> Enlucido o alisado de paredes | D43: =INDEX(Partidas!$C$2:$C$99,MATCH(A43,Partidas!$A$2:$A$99,0)) -> m2 | E43: =IF(E$5="",0,SUMPRODUCT((Plantillas!$A$2:$A$114=E$5)*(Plantillas!$D$2:$D$114=$A43)*(Plantillas!$G$2:$G$114*N(E$6)+Plantillas!$H$2:$H$114))) -> 0 | F43: =IF(F$5="",0,SUMPRODUCT((Plantillas!$A$2:$A$114=F$5)*(Plantillas!$D$2:$D$114=$A43)*(Plantillas!$G$2:$G$114*N(F$6)+Plantillas!$H$2:$H$114))) -> 0 | G43: =IF(G$5="",0,SUMPRODUCT((Plantillas!$A$2:$A$114=G$5)*(Plantillas!$D$2:$D$114=$A43)*(Plantillas!$G$2:$G$114*N(G$6)+Plantillas!$H$2:$H$114))) -> 0 | H43: =IF(H$5="",0,SUMPRODUCT((Plantillas!$A$2:$A$114=H$5)*(Plantillas!$D$2:$D$114=$A43)*(Plantillas!$G$2:$G$114*N(H$6)+Plantillas!$H$2:$H$114))) -> 0 | I43: =IF(I$5="",0,SUMPRODUCT((Plantillas!$A$2:$A$114=I$5)*(Plantillas!$D$2:$D$114=$A43)*(Plantillas!$G$2:$G$114*N(I$6)+Plantillas!$H$2:$H$114))) -> 0 | J43: =IF(J$5="",0,SUMPRODUCT((Plantillas!$A$2:$A$114=J$5)*(Plantillas!$D$2:$D$114=$A43)*(Plantillas!$G$2:$G$114*N(J$6)+Plantillas!$H$2:$H$114))) -> 0 | K43: =IF(K$5="",0,SUMPRODUCT((Plantillas!$A$2:$A$114=K$5)*(Plantillas!$D$2:$D$114=$A43)*(Plantillas!$G$2:$G$114*N(K$6)+Plantillas!$H$2:$H$114))) -> 0 | L43: =IF(L$5="",0,SUMPRODUCT((Plantillas!$A$2:$A$114=L$5)*(Plantillas!$D$2:$D$114=$A43)*(Plantillas!$G$2:$G$114*N(L$6)+Plantillas!$H$2:$H$114))) -> 0 | ... R43: =IF(R$5="",0,SUMPRODUCT((Plantillas!$A$2:$A$114=R$5)*(Plantillas!$D$2:$D$114=$A43)*(Plantillas!$G$2:$G$114*N(R$6)+Plantillas!$H$2:$H$114))) -> 0 | S43: =SUM(E43:R43) -> 0 | T43: =IF(INDEX(Partidas!$F$2:$F$99,MATCH(A43,Partidas!$A$2:$A$99,0))="","",INDEX(Partidas!$F$2:$F$99,MATCH(A43,Partidas!$A$2:$A$99,0))) | U43: =IF(T43="",0,S43*T43) -> 0
A44: REV-030 | B44: REV | C44: =INDEX(Partidas!$D$2:$D$99,MATCH(A44,Partidas!$A$2:$A$99,0)) -> Moldura de pared tipo boiserie | D44: =INDEX(Partidas!$C$2:$C$99,MATCH(A44,Partidas!$A$2:$A$99,0)) -> m | E44: =IF(E$5="",0,SUMPRODUCT((Plantillas!$A$2:$A$114=E$5)*(Plantillas!$D$2:$D$114=$A44)*(Plantillas!$G$2:$G$114*N(E$6)+Plantillas!$H$2:$H$114))) -> 0 | F44: =IF(F$5="",0,SUMPRODUCT((Plantillas!$A$2:$A$114=F$5)*(Plantillas!$D$2:$D$114=$A44)*(Plantillas!$G$2:$G$114*N(F$6)+Plantillas!$H$2:$H$114))) -> 0 | G44: =IF(G$5="",0,SUMPRODUCT((Plantillas!$A$2:$A$114=G$5)*(Plantillas!$D$2:$D$114=$A44)*(Plantillas!$G$2:$G$114*N(G$6)+Plantillas!$H$2:$H$114))) -> 0 | H44: =IF(H$5="",0,SUMPRODUCT((Plantillas!$A$2:$A$114=H$5)*(Plantillas!$D$2:$D$114=$A44)*(Plantillas!$G$2:$G$114*N(H$6)+Plantillas!$H$2:$H$114))) -> 0 | I44: =IF(I$5="",0,SUMPRODUCT((Plantillas!$A$2:$A$114=I$5)*(Plantillas!$D$2:$D$114=$A44)*(Plantillas!$G$2:$G$114*N(I$6)+Plantillas!$H$2:$H$114))) -> 0 | J44: =IF(J$5="",0,SUMPRODUCT((Plantillas!$A$2:$A$114=J$5)*(Plantillas!$D$2:$D$114=$A44)*(Plantillas!$G$2:$G$114*N(J$6)+Plantillas!$H$2:$H$114))) -> 0 | K44: =IF(K$5="",0,SUMPRODUCT((Plantillas!$A$2:$A$114=K$5)*(Plantillas!$D$2:$D$114=$A44)*(Plantillas!$G$2:$G$114*N(K$6)+Plantillas!$H$2:$H$114))) -> 0 | L44: =IF(L$5="",0,SUMPRODUCT((Plantillas!$A$2:$A$114=L$5)*(Plantillas!$D$2:$D$114=$A44)*(Plantillas!$G$2:$G$114*N(L$6)+Plantillas!$H$2:$H$114))) -> 0 | ... R44: =IF(R$5="",0,SUMPRODUCT((Plantillas!$A$2:$A$114=R$5)*(Plantillas!$D$2:$D$114=$A44)*(Plantillas!$G$2:$G$114*N(R$6)+Plantillas!$H$2:$H$114))) -> 0 | S44: =SUM(E44:R44) -> 0 | T44: =IF(INDEX(Partidas!$F$2:$F$99,MATCH(A44,Partidas!$A$2:$A$99,0))="","",INDEX(Partidas!$F$2:$F$99,MATCH(A44,Partidas!$A$2:$A$99,0))) -> 20 | U44: =IF(T44="",0,S44*T44) -> 0
A45: REV-040 | B45: REV | C45: =INDEX(Partidas!$D$2:$D$99,MATCH(A45,Partidas!$A$2:$A$99,0)) -> Espejo decorativo en pared | D45: =INDEX(Partidas!$C$2:$C$99,MATCH(A45,Partidas!$A$2:$A$99,0)) -> m2 | E45: =IF(E$5="",0,SUMPRODUCT((Plantillas!$A$2:$A$114=E$5)*(Plantillas!$D$2:$D$114=$A45)*(Plantillas!$G$2:$G$114*N(E$6)+Plantillas!$H$2:$H$114))) -> 0 | F45: =IF(F$5="",0,SUMPRODUCT((Plantillas!$A$2:$A$114=F$5)*(Plantillas!$D$2:$D$114=$A45)*(Plantillas!$G$2:$G$114*N(F$6)+Plantillas!$H$2:$H$114))) -> 0 | G45: =IF(G$5="",0,SUMPRODUCT((Plantillas!$A$2:$A$114=G$5)*(Plantillas!$D$2:$D$114=$A45)*(Plantillas!$G$2:$G$114*N(G$6)+Plantillas!$H$2:$H$114))) -> 0 | H45: =IF(H$5="",0,SUMPRODUCT((Plantillas!$A$2:$A$114=H$5)*(Plantillas!$D$2:$D$114=$A45)*(Plantillas!$G$2:$G$114*N(H$6)+Plantillas!$H$2:$H$114))) -> 0 | I45: =IF(I$5="",0,SUMPRODUCT((Plantillas!$A$2:$A$114=I$5)*(Plantillas!$D$2:$D$114=$A45)*(Plantillas!$G$2:$G$114*N(I$6)+Plantillas!$H$2:$H$114))) -> 0 | J45: =IF(J$5="",0,SUMPRODUCT((Plantillas!$A$2:$A$114=J$5)*(Plantillas!$D$2:$D$114=$A45)*(Plantillas!$G$2:$G$114*N(J$6)+Plantillas!$H$2:$H$114))) -> 0 | K45: =IF(K$5="",0,SUMPRODUCT((Plantillas!$A$2:$A$114=K$5)*(Plantillas!$D$2:$D$114=$A45)*(Plantillas!$G$2:$G$114*N(K$6)+Plantillas!$H$2:$H$114))) -> 0 | L45: =IF(L$5="",0,SUMPRODUCT((Plantillas!$A$2:$A$114=L$5)*(Plantillas!$D$2:$D$114=$A45)*(Plantillas!$G$2:$G$114*N(L$6)+Plantillas!$H$2:$H$114))) -> 0 | ... R45: =IF(R$5="",0,SUMPRODUCT((Plantillas!$A$2:$A$114=R$5)*(Plantillas!$D$2:$D$114=$A45)*(Plantillas!$G$2:$G$114*N(R$6)+Plantillas!$H$2:$H$114))) -> 0 | S45: =SUM(E45:R45) -> 0 | T45: =IF(INDEX(Partidas!$F$2:$F$99,MATCH(A45,Partidas!$A$2:$A$99,0))="","",INDEX(Partidas!$F$2:$F$99,MATCH(A45,Partidas!$A$2:$A$99,0))) -> 80 | U45: =IF(T45="",0,S45*T45) -> 0
A46: REV-050 | B46: REV | C46: =INDEX(Partidas!$D$2:$D$99,MATCH(A46,Partidas!$A$2:$A$99,0)) -> Viga decorativa imitación madera | D46: =INDEX(Partidas!$C$2:$C$99,MATCH(A46,Partidas!$A$2:$A$99,0)) -> m | E46: =IF(E$5="",0,SUMPRODUCT((Plantillas!$A$2:$A$114=E$5)*(Plantillas!$D$2:$D$114=$A46)*(Plantillas!$G$2:$G$114*N(E$6)+Plantillas!$H$2:$H$114))) -> 0 | F46: =IF(F$5="",0,SUMPRODUCT((Plantillas!$A$2:$A$114=F$5)*(Plantillas!$D$2:$D$114=$A46)*(Plantillas!$G$2:$G$114*N(F$6)+Plantillas!$H$2:$H$114))) -> 0 | G46: =IF(G$5="",0,SUMPRODUCT((Plantillas!$A$2:$A$114=G$5)*(Plantillas!$D$2:$D$114=$A46)*(Plantillas!$G$2:$G$114*N(G$6)+Plantillas!$H$2:$H$114))) -> 0 | H46: =IF(H$5="",0,SUMPRODUCT((Plantillas!$A$2:$A$114=H$5)*(Plantillas!$D$2:$D$114=$A46)*(Plantillas!$G$2:$G$114*N(H$6)+Plantillas!$H$2:$H$114))) -> 0 | I46: =IF(I$5="",0,SUMPRODUCT((Plantillas!$A$2:$A$114=I$5)*(Plantillas!$D$2:$D$114=$A46)*(Plantillas!$G$2:$G$114*N(I$6)+Plantillas!$H$2:$H$114))) -> 0 | J46: =IF(J$5="",0,SUMPRODUCT((Plantillas!$A$2:$A$114=J$5)*(Plantillas!$D$2:$D$114=$A46)*(Plantillas!$G$2:$G$114*N(J$6)+Plantillas!$H$2:$H$114))) -> 0 | K46: =IF(K$5="",0,SUMPRODUCT((Plantillas!$A$2:$A$114=K$5)*(Plantillas!$D$2:$D$114=$A46)*(Plantillas!$G$2:$G$114*N(K$6)+Plantillas!$H$2:$H$114))) -> 0 | L46: =IF(L$5="",0,SUMPRODUCT((Plantillas!$A$2:$A$114=L$5)*(Plantillas!$D$2:$D$114=$A46)*(Plantillas!$G$2:$G$114*N(L$6)+Plantillas!$H$2:$H$114))) -> 0 | ... R46: =IF(R$5="",0,SUMPRODUCT((Plantillas!$A$2:$A$114=R$5)*(Plantillas!$D$2:$D$114=$A46)*(Plantillas!$G$2:$G$114*N(R$6)+Plantillas!$H$2:$H$114))) -> 0 | S46: =SUM(E46:R46) -> 0 | T46: =IF(INDEX(Partidas!$F$2:$F$99,MATCH(A46,Partidas!$A$2:$A$99,0))="","",INDEX(Partidas!$F$2:$F$99,MATCH(A46,Partidas!$A$2:$A$99,0))) -> 95 | U46: =IF(T46="",0,S46*T46) -> 0
A47: PAV | C47: Pavimentos y rodapiés | U47: =SUM(U48:U53) -> 8591.625
A48: PAV-010 | B48: PAV | C48: =INDEX(Partidas!$D$2:$D$99,MATCH(A48,Partidas!$A$2:$A$99,0)) -> Recrecido de mortero autonivelante | D48: =INDEX(Partidas!$C$2:$C$99,MATCH(A48,Partidas!$A$2:$A$99,0)) -> m2 | E48: =IF(E$5="",0,SUMPRODUCT((Plantillas!$A$2:$A$114=E$5)*(Plantillas!$D$2:$D$114=$A48)*(Plantillas!$G$2:$G$114*N(E$6)+Plantillas!$H$2:$H$114))) -> 0 | F48: =IF(F$5="",0,SUMPRODUCT((Plantillas!$A$2:$A$114=F$5)*(Plantillas!$D$2:$D$114=$A48)*(Plantillas!$G$2:$G$114*N(F$6)+Plantillas!$H$2:$H$114))) -> 0 | G48: =IF(G$5="",0,SUMPRODUCT((Plantillas!$A$2:$A$114=G$5)*(Plantillas!$D$2:$D$114=$A48)*(Plantillas!$G$2:$G$114*N(G$6)+Plantillas!$H$2:$H$114))) -> 0 | H48: =IF(H$5="",0,SUMPRODUCT((Plantillas!$A$2:$A$114=H$5)*(Plantillas!$D$2:$D$114=$A48)*(Plantillas!$G$2:$G$114*N(H$6)+Plantillas!$H$2:$H$114))) -> 0 | I48: =IF(I$5="",0,SUMPRODUCT((Plantillas!$A$2:$A$114=I$5)*(Plantillas!$D$2:$D$114=$A48)*(Plantillas!$G$2:$G$114*N(I$6)+Plantillas!$H$2:$H$114))) -> 0 | J48: =IF(J$5="",0,SUMPRODUCT((Plantillas!$A$2:$A$114=J$5)*(Plantillas!$D$2:$D$114=$A48)*(Plantillas!$G$2:$G$114*N(J$6)+Plantillas!$H$2:$H$114))) -> 0 | K48: =IF(K$5="",0,SUMPRODUCT((Plantillas!$A$2:$A$114=K$5)*(Plantillas!$D$2:$D$114=$A48)*(Plantillas!$G$2:$G$114*N(K$6)+Plantillas!$H$2:$H$114))) -> 0 | L48: =IF(L$5="",0,SUMPRODUCT((Plantillas!$A$2:$A$114=L$5)*(Plantillas!$D$2:$D$114=$A48)*(Plantillas!$G$2:$G$114*N(L$6)+Plantillas!$H$2:$H$114))) -> 0 | ... R48: =IF(R$5="",0,SUMPRODUCT((Plantillas!$A$2:$A$114=R$5)*(Plantillas!$D$2:$D$114=$A48)*(Plantillas!$G$2:$G$114*N(R$6)+Plantillas!$H$2:$H$114))) -> 0 | S48: =SUM(E48:R48) -> 0 | T48: =IF(INDEX(Partidas!$F$2:$F$99,MATCH(A48,Partidas!$A$2:$A$99,0))="","",INDEX(Partidas!$F$2:$F$99,MATCH(A48,Partidas!$A$2:$A$99,0))) -> 30 | U48: =IF(T48="",0,S48*T48) -> 0
A49: PAV-020 | B49: PAV | C49: =INDEX(Partidas!$D$2:$D$99,MATCH(A49,Partidas!$A$2:$A$99,0)) -> Solado de gres porcelánico | D49: =INDEX(Partidas!$C$2:$C$99,MATCH(A49,Partidas!$A$2:$A$99,0)) -> m2 | E49: =IF(E$5="",0,SUMPRODUCT((Plantillas!$A$2:$A$114=E$5)*(Plantillas!$D$2:$D$114=$A49)*(Plantillas!$G$2:$G$114*N(E$6)+Plantillas!$H$2:$H$114))) -> 0 | F49: =IF(F$5="",0,SUMPRODUCT((Plantillas!$A$2:$A$114=F$5)*(Plantillas!$D$2:$D$114=$A49)*(Plantillas!$G$2:$G$114*N(F$6)+Plantillas!$H$2:$H$114))) -> 0 | G49: =IF(G$5="",0,SUMPRODUCT((Plantillas!$A$2:$A$114=G$5)*(Plantillas!$D$2:$D$114=$A49)*(Plantillas!$G$2:$G$114*N(G$6)+Plantillas!$H$2:$H$114))) -> 0 | H49: =IF(H$5="",0,SUMPRODUCT((Plantillas!$A$2:$A$114=H$5)*(Plantillas!$D$2:$D$114=$A49)*(Plantillas!$G$2:$G$114*N(H$6)+Plantillas!$H$2:$H$114))) -> 0 | I49: =IF(I$5="",0,SUMPRODUCT((Plantillas!$A$2:$A$114=I$5)*(Plantillas!$D$2:$D$114=$A49)*(Plantillas!$G$2:$G$114*N(I$6)+Plantillas!$H$2:$H$114))) -> 0 | J49: =IF(J$5="",0,SUMPRODUCT((Plantillas!$A$2:$A$114=J$5)*(Plantillas!$D$2:$D$114=$A49)*(Plantillas!$G$2:$G$114*N(J$6)+Plantillas!$H$2:$H$114))) -> 0 | K49: =IF(K$5="",0,SUMPRODUCT((Plantillas!$A$2:$A$114=K$5)*(Plantillas!$D$2:$D$114=$A49)*(Plantillas!$G$2:$G$114*N(K$6)+Plantillas!$H$2:$H$114))) -> 0 | L49: =IF(L$5="",0,SUMPRODUCT((Plantillas!$A$2:$A$114=L$5)*(Plantillas!$D$2:$D$114=$A49)*(Plantillas!$G$2:$G$114*N(L$6)+Plantillas!$H$2:$H$114))) -> 9 | ... R49: =IF(R$5="",0,SUMPRODUCT((Plantillas!$A$2:$A$114=R$5)*(Plantillas!$D$2:$D$114=$A49)*(Plantillas!$G$2:$G$114*N(R$6)+Plantillas!$H$2:$H$114))) -> 0 | S49: =SUM(E49:R49) -> 21 | T49: =IF(INDEX(Partidas!$F$2:$F$99,MATCH(A49,Partidas!$A$2:$A$99,0))="","",INDEX(Partidas!$F$2:$F$99,MATCH(A49,Partidas!$A$2:$A$99,0))) -> 86 | U49: =IF(T49="",0,S49*T49) -> 1806
A50: PAV-030 | B50: PAV | C50: =INDEX(Partidas!$D$2:$D$99,MATCH(A50,Partidas!$A$2:$A$99,0)) -> Suelo laminado flotante | D50: =INDEX(Partidas!$C$2:$C$99,MATCH(A50,Partidas!$A$2:$A$99,0)) -> m2 | E50: =IF(E$5="",0,SUMPRODUCT((Plantillas!$A$2:$A$114=E$5)*(Plantillas!$D$2:$D$114=$A50)*(Plantillas!$G$2:$G$114*N(E$6)+Plantillas!$H$2:$H$114))) -> 0 | F50: =IF(F$5="",0,SUMPRODUCT((Plantillas!$A$2:$A$114=F$5)*(Plantillas!$D$2:$D$114=$A50)*(Plantillas!$G$2:$G$114*N(F$6)+Plantillas!$H$2:$H$114))) -> 24 | G50: =IF(G$5="",0,SUMPRODUCT((Plantillas!$A$2:$A$114=G$5)*(Plantillas!$D$2:$D$114=$A50)*(Plantillas!$G$2:$G$114*N(G$6)+Plantillas!$H$2:$H$114))) -> 15 | H50: =IF(H$5="",0,SUMPRODUCT((Plantillas!$A$2:$A$114=H$5)*(Plantillas!$D$2:$D$114=$A50)*(Plantillas!$G$2:$G$114*N(H$6)+Plantillas!$H$2:$H$114))) -> 10 | I50: =IF(I$5="",0,SUMPRODUCT((Plantillas!$A$2:$A$114=I$5)*(Plantillas!$D$2:$D$114=$A50)*(Plantillas!$G$2:$G$114*N(I$6)+Plantillas!$H$2:$H$114))) -> 10 | J50: =IF(J$5="",0,SUMPRODUCT((Plantillas!$A$2:$A$114=J$5)*(Plantillas!$D$2:$D$114=$A50)*(Plantillas!$G$2:$G$114*N(J$6)+Plantillas!$H$2:$H$114))) -> 7 | K50: =IF(K$5="",0,SUMPRODUCT((Plantillas!$A$2:$A$114=K$5)*(Plantillas!$D$2:$D$114=$A50)*(Plantillas!$G$2:$G$114*N(K$6)+Plantillas!$H$2:$H$114))) -> 4 | L50: =IF(L$5="",0,SUMPRODUCT((Plantillas!$A$2:$A$114=L$5)*(Plantillas!$D$2:$D$114=$A50)*(Plantillas!$G$2:$G$114*N(L$6)+Plantillas!$H$2:$H$114))) -> 0 | ... R50: =IF(R$5="",0,SUMPRODUCT((Plantillas!$A$2:$A$114=R$5)*(Plantillas!$D$2:$D$114=$A50)*(Plantillas!$G$2:$G$114*N(R$6)+Plantillas!$H$2:$H$114))) -> 0 | S50: =SUM(E50:R50) -> 70 | T50: =IF(INDEX(Partidas!$F$2:$F$99,MATCH(A50,Partidas!$A$2:$A$99,0))="","",INDEX(Partidas!$F$2:$F$99,MATCH(A50,Partidas!$A$2:$A$99,0))) -> 78 | U50: =IF(T50="",0,S50*T50) -> 5460
A51: PAV-040 | B51: PAV | C51: =INDEX(Partidas!$D$2:$D$99,MATCH(A51,Partidas!$A$2:$A$99,0)) -> Tarima de madera natural | D51: =INDEX(Partidas!$C$2:$C$99,MATCH(A51,Partidas!$A$2:$A$99,0)) -> m2 | E51: =IF(E$5="",0,SUMPRODUCT((Plantillas!$A$2:$A$114=E$5)*(Plantillas!$D$2:$D$114=$A51)*(Plantillas!$G$2:$G$114*N(E$6)+Plantillas!$H$2:$H$114))) -> 0 | F51: =IF(F$5="",0,SUMPRODUCT((Plantillas!$A$2:$A$114=F$5)*(Plantillas!$D$2:$D$114=$A51)*(Plantillas!$G$2:$G$114*N(F$6)+Plantillas!$H$2:$H$114))) -> 0 | G51: =IF(G$5="",0,SUMPRODUCT((Plantillas!$A$2:$A$114=G$5)*(Plantillas!$D$2:$D$114=$A51)*(Plantillas!$G$2:$G$114*N(G$6)+Plantillas!$H$2:$H$114))) -> 0 | H51: =IF(H$5="",0,SUMPRODUCT((Plantillas!$A$2:$A$114=H$5)*(Plantillas!$D$2:$D$114=$A51)*(Plantillas!$G$2:$G$114*N(H$6)+Plantillas!$H$2:$H$114))) -> 0 | I51: =IF(I$5="",0,SUMPRODUCT((Plantillas!$A$2:$A$114=I$5)*(Plantillas!$D$2:$D$114=$A51)*(Plantillas!$G$2:$G$114*N(I$6)+Plantillas!$H$2:$H$114))) -> 0 | J51: =IF(J$5="",0,SUMPRODUCT((Plantillas!$A$2:$A$114=J$5)*(Plantillas!$D$2:$D$114=$A51)*(Plantillas!$G$2:$G$114*N(J$6)+Plantillas!$H$2:$H$114))) -> 0 | K51: =IF(K$5="",0,SUMPRODUCT((Plantillas!$A$2:$A$114=K$5)*(Plantillas!$D$2:$D$114=$A51)*(Plantillas!$G$2:$G$114*N(K$6)+Plantillas!$H$2:$H$114))) -> 0 | L51: =IF(L$5="",0,SUMPRODUCT((Plantillas!$A$2:$A$114=L$5)*(Plantillas!$D$2:$D$114=$A51)*(Plantillas!$G$2:$G$114*N(L$6)+Plantillas!$H$2:$H$114))) -> 0 | ... R51: =IF(R$5="",0,SUMPRODUCT((Plantillas!$A$2:$A$114=R$5)*(Plantillas!$D$2:$D$114=$A51)*(Plantillas!$G$2:$G$114*N(R$6)+Plantillas!$H$2:$H$114))) -> 0 | S51: =SUM(E51:R51) -> 0 | T51: =IF(INDEX(Partidas!$F$2:$F$99,MATCH(A51,Partidas!$A$2:$A$99,0))="","",INDEX(Partidas!$F$2:$F$99,MATCH(A51,Partidas!$A$2:$A$99,0))) -> 120 | U51: =IF(T51="",0,S51*T51) -> 0
A52: PAV-050 | B52: PAV | C52: =INDEX(Partidas!$D$2:$D$99,MATCH(A52,Partidas!$A$2:$A$99,0)) -> Suelo vinílico SPC | D52: =INDEX(Partidas!$C$2:$C$99,MATCH(A52,Partidas!$A$2:$A$99,0)) -> m2 | E52: =IF(E$5="",0,SUMPRODUCT((Plantillas!$A$2:$A$114=E$5)*(Plantillas!$D$2:$D$114=$A52)*(Plantillas!$G$2:$G$114*N(E$6)+Plantillas!$H$2:$H$114))) -> 0 | F52: =IF(F$5="",0,SUMPRODUCT((Plantillas!$A$2:$A$114=F$5)*(Plantillas!$D$2:$D$114=$A52)*(Plantillas!$G$2:$G$114*N(F$6)+Plantillas!$H$2:$H$114))) -> 0 | G52: =IF(G$5="",0,SUMPRODUCT((Plantillas!$A$2:$A$114=G$5)*(Plantillas!$D$2:$D$114=$A52)*(Plantillas!$G$2:$G$114*N(G$6)+Plantillas!$H$2:$H$114))) -> 0 | H52: =IF(H$5="",0,SUMPRODUCT((Plantillas!$A$2:$A$114=H$5)*(Plantillas!$D$2:$D$114=$A52)*(Plantillas!$G$2:$G$114*N(H$6)+Plantillas!$H$2:$H$114))) -> 0 | I52: =IF(I$5="",0,SUMPRODUCT((Plantillas!$A$2:$A$114=I$5)*(Plantillas!$D$2:$D$114=$A52)*(Plantillas!$G$2:$G$114*N(I$6)+Plantillas!$H$2:$H$114))) -> 0 | J52: =IF(J$5="",0,SUMPRODUCT((Plantillas!$A$2:$A$114=J$5)*(Plantillas!$D$2:$D$114=$A52)*(Plantillas!$G$2:$G$114*N(J$6)+Plantillas!$H$2:$H$114))) -> 0 | K52: =IF(K$5="",0,SUMPRODUCT((Plantillas!$A$2:$A$114=K$5)*(Plantillas!$D$2:$D$114=$A52)*(Plantillas!$G$2:$G$114*N(K$6)+Plantillas!$H$2:$H$114))) -> 0 | L52: =IF(L$5="",0,SUMPRODUCT((Plantillas!$A$2:$A$114=L$5)*(Plantillas!$D$2:$D$114=$A52)*(Plantillas!$G$2:$G$114*N(L$6)+Plantillas!$H$2:$H$114))) -> 0 | ... R52: =IF(R$5="",0,SUMPRODUCT((Plantillas!$A$2:$A$114=R$5)*(Plantillas!$D$2:$D$114=$A52)*(Plantillas!$G$2:$G$114*N(R$6)+Plantillas!$H$2:$H$114))) -> 0 | S52: =SUM(E52:R52) -> 0 | T52: =IF(INDEX(Partidas!$F$2:$F$99,MATCH(A52,Partidas!$A$2:$A$99,0))="","",INDEX(Partidas!$F$2:$F$99,MATCH(A52,Partidas!$A$2:$A$99,0))) -> 54 | U52: =IF(T52="",0,S52*T52) -> 0
A53: PAV-060 | B53: PAV | C53: =INDEX(Partidas!$D$2:$D$99,MATCH(A53,Partidas!$A$2:$A$99,0)) -> Rodapié lacado blanco 20 cm | D53: =INDEX(Partidas!$C$2:$C$99,MATCH(A53,Partidas!$A$2:$A$99,0)) -> m | E53: =IF(E$5="",0,SUMPRODUCT((Plantillas!$A$2:$A$114=E$5)*(Plantillas!$D$2:$D$114=$A53)*(Plantillas!$G$2:$G$114*N(E$6)+Plantillas!$H$2:$H$114))) -> 0 | F53: =IF(F$5="",0,SUMPRODUCT((Plantillas!$A$2:$A$114=F$5)*(Plantillas!$D$2:$D$114=$A53)*(Plantillas!$G$2:$G$114*N(F$6)+Plantillas!$H$2:$H$114))) -> 21.6 | G53: =IF(G$5="",0,SUMPRODUCT((Plantillas!$A$2:$A$114=G$5)*(Plantillas!$D$2:$D$114=$A53)*(Plantillas!$G$2:$G$114*N(G$6)+Plantillas!$H$2:$H$114))) -> 13.5 | H53: =IF(H$5="",0,SUMPRODUCT((Plantillas!$A$2:$A$114=H$5)*(Plantillas!$D$2:$D$114=$A53)*(Plantillas!$G$2:$G$114*N(H$6)+Plantillas!$H$2:$H$114))) -> 9 | I53: =IF(I$5="",0,SUMPRODUCT((Plantillas!$A$2:$A$114=I$5)*(Plantillas!$D$2:$D$114=$A53)*(Plantillas!$G$2:$G$114*N(I$6)+Plantillas!$H$2:$H$114))) -> 9 | J53: =IF(J$5="",0,SUMPRODUCT((Plantillas!$A$2:$A$114=J$5)*(Plantillas!$D$2:$D$114=$A53)*(Plantillas!$G$2:$G$114*N(J$6)+Plantillas!$H$2:$H$114))) -> 11.2 | K53: =IF(K$5="",0,SUMPRODUCT((Plantillas!$A$2:$A$114=K$5)*(Plantillas!$D$2:$D$114=$A53)*(Plantillas!$G$2:$G$114*N(K$6)+Plantillas!$H$2:$H$114))) -> 6.4 | L53: =IF(L$5="",0,SUMPRODUCT((Plantillas!$A$2:$A$114=L$5)*(Plantillas!$D$2:$D$114=$A53)*(Plantillas!$G$2:$G$114*N(L$6)+Plantillas!$H$2:$H$114))) -> 0 | ... R53: =IF(R$5="",0,SUMPRODUCT((Plantillas!$A$2:$A$114=R$5)*(Plantillas!$D$2:$D$114=$A53)*(Plantillas!$G$2:$G$114*N(R$6)+Plantillas!$H$2:$H$114))) -> 0 | S53: =SUM(E53:R53) -> 70.7 | T53: =IF(INDEX(Partidas!$F$2:$F$99,MATCH(A53,Partidas!$A$2:$A$99,0))="","",INDEX(Partidas!$F$2:$F$99,MATCH(A53,Partidas!$A$2:$A$99,0))) -> 18.75 | U53: =IF(T53="",0,S53*T53) -> 1325.625
A54: CEX | C54: Carpintería exterior y protecciones solares | U54: =SUM(U55:U58) -> 9468
A55: CEX-010 | B55: CEX | C55: =INDEX(Partidas!$D$2:$D$99,MATCH(A55,Partidas!$A$2:$A$99,0)) -> Ventana de aluminio con rotura de puente térmico | D55: =INDEX(Partidas!$C$2:$C$99,MATCH(A55,Partidas!$A$2:$A$99,0)) -> ud | E55: =IF(E$5="",0,SUMPRODUCT((Plantillas!$A$2:$A$114=E$5)*(Plantillas!$D$2:$D$114=$A55)*(Plantillas!$G$2:$G$114*N(E$6)+Plantillas!$H$2:$H$114))) -> 0 | F55: =IF(F$5="",0,SUMPRODUCT((Plantillas!$A$2:$A$114=F$5)*(Plantillas!$D$2:$D$114=$A55)*(Plantillas!$G$2:$G$114*N(F$6)+Plantillas!$H$2:$H$114))) -> 0 | G55: =IF(G$5="",0,SUMPRODUCT((Plantillas!$A$2:$A$114=G$5)*(Plantillas!$D$2:$D$114=$A55)*(Plantillas!$G$2:$G$114*N(G$6)+Plantillas!$H$2:$H$114))) -> 0 | H55: =IF(H$5="",0,SUMPRODUCT((Plantillas!$A$2:$A$114=H$5)*(Plantillas!$D$2:$D$114=$A55)*(Plantillas!$G$2:$G$114*N(H$6)+Plantillas!$H$2:$H$114))) -> 0 | I55: =IF(I$5="",0,SUMPRODUCT((Plantillas!$A$2:$A$114=I$5)*(Plantillas!$D$2:$D$114=$A55)*(Plantillas!$G$2:$G$114*N(I$6)+Plantillas!$H$2:$H$114))) -> 0 | J55: =IF(J$5="",0,SUMPRODUCT((Plantillas!$A$2:$A$114=J$5)*(Plantillas!$D$2:$D$114=$A55)*(Plantillas!$G$2:$G$114*N(J$6)+Plantillas!$H$2:$H$114))) -> 0 | K55: =IF(K$5="",0,SUMPRODUCT((Plantillas!$A$2:$A$114=K$5)*(Plantillas!$D$2:$D$114=$A55)*(Plantillas!$G$2:$G$114*N(K$6)+Plantillas!$H$2:$H$114))) -> 0 | L55: =IF(L$5="",0,SUMPRODUCT((Plantillas!$A$2:$A$114=L$5)*(Plantillas!$D$2:$D$114=$A55)*(Plantillas!$G$2:$G$114*N(L$6)+Plantillas!$H$2:$H$114))) -> 0 | ... R55: =IF(R$5="",0,SUMPRODUCT((Plantillas!$A$2:$A$114=R$5)*(Plantillas!$D$2:$D$114=$A55)*(Plantillas!$G$2:$G$114*N(R$6)+Plantillas!$H$2:$H$114))) -> 0 | S55: =SUM(E55:R55) -> 9 | T55: =IF(INDEX(Partidas!$F$2:$F$99,MATCH(A55,Partidas!$A$2:$A$99,0))="","",INDEX(Partidas!$F$2:$F$99,MATCH(A55,Partidas!$A$2:$A$99,0))) -> 1052 | U55: =IF(T55="",0,S55*T55) -> 9468
A56: CEX-020 | B56: CEX | C56: =INDEX(Partidas!$D$2:$D$99,MATCH(A56,Partidas!$A$2:$A$99,0)) -> Ventana de PVC | D56: =INDEX(Partidas!$C$2:$C$99,MATCH(A56,Partidas!$A$2:$A$99,0)) -> ud | E56: =IF(E$5="",0,SUMPRODUCT((Plantillas!$A$2:$A$114=E$5)*(Plantillas!$D$2:$D$114=$A56)*(Plantillas!$G$2:$G$114*N(E$6)+Plantillas!$H$2:$H$114))) -> 0 | F56: =IF(F$5="",0,SUMPRODUCT((Plantillas!$A$2:$A$114=F$5)*(Plantillas!$D$2:$D$114=$A56)*(Plantillas!$G$2:$G$114*N(F$6)+Plantillas!$H$2:$H$114))) -> 0 | G56: =IF(G$5="",0,SUMPRODUCT((Plantillas!$A$2:$A$114=G$5)*(Plantillas!$D$2:$D$114=$A56)*(Plantillas!$G$2:$G$114*N(G$6)+Plantillas!$H$2:$H$114))) -> 0 | H56: =IF(H$5="",0,SUMPRODUCT((Plantillas!$A$2:$A$114=H$5)*(Plantillas!$D$2:$D$114=$A56)*(Plantillas!$G$2:$G$114*N(H$6)+Plantillas!$H$2:$H$114))) -> 0 | I56: =IF(I$5="",0,SUMPRODUCT((Plantillas!$A$2:$A$114=I$5)*(Plantillas!$D$2:$D$114=$A56)*(Plantillas!$G$2:$G$114*N(I$6)+Plantillas!$H$2:$H$114))) -> 0 | J56: =IF(J$5="",0,SUMPRODUCT((Plantillas!$A$2:$A$114=J$5)*(Plantillas!$D$2:$D$114=$A56)*(Plantillas!$G$2:$G$114*N(J$6)+Plantillas!$H$2:$H$114))) -> 0 | K56: =IF(K$5="",0,SUMPRODUCT((Plantillas!$A$2:$A$114=K$5)*(Plantillas!$D$2:$D$114=$A56)*(Plantillas!$G$2:$G$114*N(K$6)+Plantillas!$H$2:$H$114))) -> 0 | L56: =IF(L$5="",0,SUMPRODUCT((Plantillas!$A$2:$A$114=L$5)*(Plantillas!$D$2:$D$114=$A56)*(Plantillas!$G$2:$G$114*N(L$6)+Plantillas!$H$2:$H$114))) -> 0 | ... R56: =IF(R$5="",0,SUMPRODUCT((Plantillas!$A$2:$A$114=R$5)*(Plantillas!$D$2:$D$114=$A56)*(Plantillas!$G$2:$G$114*N(R$6)+Plantillas!$H$2:$H$114))) -> 0 | S56: =SUM(E56:R56) -> 0 | T56: =IF(INDEX(Partidas!$F$2:$F$99,MATCH(A56,Partidas!$A$2:$A$99,0))="","",INDEX(Partidas!$F$2:$F$99,MATCH(A56,Partidas!$A$2:$A$99,0))) -> 722 | U56: =IF(T56="",0,S56*T56) -> 0
A57: CEX-030 | B57: CEX | C57: =INDEX(Partidas!$D$2:$D$99,MATCH(A57,Partidas!$A$2:$A$99,0)) -> Persiana enrollable motorizada con cajón | D57: =INDEX(Partidas!$C$2:$C$99,MATCH(A57,Partidas!$A$2:$A$99,0)) -> ud | E57: =IF(E$5="",0,SUMPRODUCT((Plantillas!$A$2:$A$114=E$5)*(Plantillas!$D$2:$D$114=$A57)*(Plantillas!$G$2:$G$114*N(E$6)+Plantillas!$H$2:$H$114))) -> 0 | F57: =IF(F$5="",0,SUMPRODUCT((Plantillas!$A$2:$A$114=F$5)*(Plantillas!$D$2:$D$114=$A57)*(Plantillas!$G$2:$G$114*N(F$6)+Plantillas!$H$2:$H$114))) -> 0 | G57: =IF(G$5="",0,SUMPRODUCT((Plantillas!$A$2:$A$114=G$5)*(Plantillas!$D$2:$D$114=$A57)*(Plantillas!$G$2:$G$114*N(G$6)+Plantillas!$H$2:$H$114))) -> 0 | H57: =IF(H$5="",0,SUMPRODUCT((Plantillas!$A$2:$A$114=H$5)*(Plantillas!$D$2:$D$114=$A57)*(Plantillas!$G$2:$G$114*N(H$6)+Plantillas!$H$2:$H$114))) -> 0 | I57: =IF(I$5="",0,SUMPRODUCT((Plantillas!$A$2:$A$114=I$5)*(Plantillas!$D$2:$D$114=$A57)*(Plantillas!$G$2:$G$114*N(I$6)+Plantillas!$H$2:$H$114))) -> 0 | J57: =IF(J$5="",0,SUMPRODUCT((Plantillas!$A$2:$A$114=J$5)*(Plantillas!$D$2:$D$114=$A57)*(Plantillas!$G$2:$G$114*N(J$6)+Plantillas!$H$2:$H$114))) -> 0 | K57: =IF(K$5="",0,SUMPRODUCT((Plantillas!$A$2:$A$114=K$5)*(Plantillas!$D$2:$D$114=$A57)*(Plantillas!$G$2:$G$114*N(K$6)+Plantillas!$H$2:$H$114))) -> 0 | L57: =IF(L$5="",0,SUMPRODUCT((Plantillas!$A$2:$A$114=L$5)*(Plantillas!$D$2:$D$114=$A57)*(Plantillas!$G$2:$G$114*N(L$6)+Plantillas!$H$2:$H$114))) -> 0 | ... R57: =IF(R$5="",0,SUMPRODUCT((Plantillas!$A$2:$A$114=R$5)*(Plantillas!$D$2:$D$114=$A57)*(Plantillas!$G$2:$G$114*N(R$6)+Plantillas!$H$2:$H$114))) -> 0 | S57: =SUM(E57:R57) -> 0 | T57: =IF(INDEX(Partidas!$F$2:$F$99,MATCH(A57,Partidas!$A$2:$A$99,0))="","",INDEX(Partidas!$F$2:$F$99,MATCH(A57,Partidas!$A$2:$A$99,0))) | U57: =IF(T57="",0,S57*T57) -> 0
A58: CEX-040 | B58: CEX | C58: =INDEX(Partidas!$D$2:$D$99,MATCH(A58,Partidas!$A$2:$A$99,0)) -> Puerta de entrada blindada | D58: =INDEX(Partidas!$C$2:$C$99,MATCH(A58,Partidas!$A$2:$A$99,0)) -> ud | E58: =IF(E$5="",0,SUMPRODUCT((Plantillas!$A$2:$A$114=E$5)*(Plantillas!$D$2:$D$114=$A58)*(Plantillas!$G$2:$G$114*N(E$6)+Plantillas!$H$2:$H$114))) -> 0 | F58: =IF(F$5="",0,SUMPRODUCT((Plantillas!$A$2:$A$114=F$5)*(Plantillas!$D$2:$D$114=$A58)*(Plantillas!$G$2:$G$114*N(F$6)+Plantillas!$H$2:$H$114))) -> 0 | G58: =IF(G$5="",0,SUMPRODUCT((Plantillas!$A$2:$A$114=G$5)*(Plantillas!$D$2:$D$114=$A58)*(Plantillas!$G$2:$G$114*N(G$6)+Plantillas!$H$2:$H$114))) -> 0 | H58: =IF(H$5="",0,SUMPRODUCT((Plantillas!$A$2:$A$114=H$5)*(Plantillas!$D$2:$D$114=$A58)*(Plantillas!$G$2:$G$114*N(H$6)+Plantillas!$H$2:$H$114))) -> 0 | I58: =IF(I$5="",0,SUMPRODUCT((Plantillas!$A$2:$A$114=I$5)*(Plantillas!$D$2:$D$114=$A58)*(Plantillas!$G$2:$G$114*N(I$6)+Plantillas!$H$2:$H$114))) -> 0 | J58: =IF(J$5="",0,SUMPRODUCT((Plantillas!$A$2:$A$114=J$5)*(Plantillas!$D$2:$D$114=$A58)*(Plantillas!$G$2:$G$114*N(J$6)+Plantillas!$H$2:$H$114))) -> 0 | K58: =IF(K$5="",0,SUMPRODUCT((Plantillas!$A$2:$A$114=K$5)*(Plantillas!$D$2:$D$114=$A58)*(Plantillas!$G$2:$G$114*N(K$6)+Plantillas!$H$2:$H$114))) -> 0 | L58: =IF(L$5="",0,SUMPRODUCT((Plantillas!$A$2:$A$114=L$5)*(Plantillas!$D$2:$D$114=$A58)*(Plantillas!$G$2:$G$114*N(L$6)+Plantillas!$H$2:$H$114))) -> 0 | ... R58: =IF(R$5="",0,SUMPRODUCT((Plantillas!$A$2:$A$114=R$5)*(Plantillas!$D$2:$D$114=$A58)*(Plantillas!$G$2:$G$114*N(R$6)+Plantillas!$H$2:$H$114))) -> 0 | S58: =SUM(E58:R58) -> 0 | T58: =IF(INDEX(Partidas!$F$2:$F$99,MATCH(A58,Partidas!$A$2:$A$99,0))="","",INDEX(Partidas!$F$2:$F$99,MATCH(A58,Partidas!$A$2:$A$99,0))) | U58: =IF(T58="",0,S58*T58) -> 0
A59: CIN | C59: Carpintería interior y mobiliario a medida | U59: =SUM(U60:U65) -> 2895
A60: CIN-010 | B60: CIN | C60: =INDEX(Partidas!$D$2:$D$99,MATCH(A60,Partidas!$A$2:$A$99,0)) -> Puerta de paso abatible, altura estándar | D60: =INDEX(Partidas!$C$2:$C$99,MATCH(A60,Partidas!$A$2:$A$99,0)) -> ud | E60: =IF(E$5="",0,SUMPRODUCT((Plantillas!$A$2:$A$114=E$5)*(Plantillas!$D$2:$D$114=$A60)*(Plantillas!$G$2:$G$114*N(E$6)+Plantillas!$H$2:$H$114))) -> 0 | F60: =IF(F$5="",0,SUMPRODUCT((Plantillas!$A$2:$A$114=F$5)*(Plantillas!$D$2:$D$114=$A60)*(Plantillas!$G$2:$G$114*N(F$6)+Plantillas!$H$2:$H$114))) -> 0 | G60: =IF(G$5="",0,SUMPRODUCT((Plantillas!$A$2:$A$114=G$5)*(Plantillas!$D$2:$D$114=$A60)*(Plantillas!$G$2:$G$114*N(G$6)+Plantillas!$H$2:$H$114))) -> 1 | H60: =IF(H$5="",0,SUMPRODUCT((Plantillas!$A$2:$A$114=H$5)*(Plantillas!$D$2:$D$114=$A60)*(Plantillas!$G$2:$G$114*N(H$6)+Plantillas!$H$2:$H$114))) -> 1 | I60: =IF(I$5="",0,SUMPRODUCT((Plantillas!$A$2:$A$114=I$5)*(Plantillas!$D$2:$D$114=$A60)*(Plantillas!$G$2:$G$114*N(I$6)+Plantillas!$H$2:$H$114))) -> 1 | J60: =IF(J$5="",0,SUMPRODUCT((Plantillas!$A$2:$A$114=J$5)*(Plantillas!$D$2:$D$114=$A60)*(Plantillas!$G$2:$G$114*N(J$6)+Plantillas!$H$2:$H$114))) -> 0 | K60: =IF(K$5="",0,SUMPRODUCT((Plantillas!$A$2:$A$114=K$5)*(Plantillas!$D$2:$D$114=$A60)*(Plantillas!$G$2:$G$114*N(K$6)+Plantillas!$H$2:$H$114))) -> 0 | L60: =IF(L$5="",0,SUMPRODUCT((Plantillas!$A$2:$A$114=L$5)*(Plantillas!$D$2:$D$114=$A60)*(Plantillas!$G$2:$G$114*N(L$6)+Plantillas!$H$2:$H$114))) -> 0 | ... R60: =IF(R$5="",0,SUMPRODUCT((Plantillas!$A$2:$A$114=R$5)*(Plantillas!$D$2:$D$114=$A60)*(Plantillas!$G$2:$G$114*N(R$6)+Plantillas!$H$2:$H$114))) -> 0 | S60: =SUM(E60:R60) -> 5 | T60: =IF(INDEX(Partidas!$F$2:$F$99,MATCH(A60,Partidas!$A$2:$A$99,0))="","",INDEX(Partidas!$F$2:$F$99,MATCH(A60,Partidas!$A$2:$A$99,0))) -> 495 | U60: =IF(T60="",0,S60*T60) -> 2475
A61: CIN-020 | B61: CIN | C61: =INDEX(Partidas!$D$2:$D$99,MATCH(A61,Partidas!$A$2:$A$99,0)) -> Puerta de paso abatible, gran altura | D61: =INDEX(Partidas!$C$2:$C$99,MATCH(A61,Partidas!$A$2:$A$99,0)) -> ud | E61: =IF(E$5="",0,SUMPRODUCT((Plantillas!$A$2:$A$114=E$5)*(Plantillas!$D$2:$D$114=$A61)*(Plantillas!$G$2:$G$114*N(E$6)+Plantillas!$H$2:$H$114))) -> 0 | F61: =IF(F$5="",0,SUMPRODUCT((Plantillas!$A$2:$A$114=F$5)*(Plantillas!$D$2:$D$114=$A61)*(Plantillas!$G$2:$G$114*N(F$6)+Plantillas!$H$2:$H$114))) -> 0 | G61: =IF(G$5="",0,SUMPRODUCT((Plantillas!$A$2:$A$114=G$5)*(Plantillas!$D$2:$D$114=$A61)*(Plantillas!$G$2:$G$114*N(G$6)+Plantillas!$H$2:$H$114))) -> 0 | H61: =IF(H$5="",0,SUMPRODUCT((Plantillas!$A$2:$A$114=H$5)*(Plantillas!$D$2:$D$114=$A61)*(Plantillas!$G$2:$G$114*N(H$6)+Plantillas!$H$2:$H$114))) -> 0 | I61: =IF(I$5="",0,SUMPRODUCT((Plantillas!$A$2:$A$114=I$5)*(Plantillas!$D$2:$D$114=$A61)*(Plantillas!$G$2:$G$114*N(I$6)+Plantillas!$H$2:$H$114))) -> 0 | J61: =IF(J$5="",0,SUMPRODUCT((Plantillas!$A$2:$A$114=J$5)*(Plantillas!$D$2:$D$114=$A61)*(Plantillas!$G$2:$G$114*N(J$6)+Plantillas!$H$2:$H$114))) -> 0 | K61: =IF(K$5="",0,SUMPRODUCT((Plantillas!$A$2:$A$114=K$5)*(Plantillas!$D$2:$D$114=$A61)*(Plantillas!$G$2:$G$114*N(K$6)+Plantillas!$H$2:$H$114))) -> 0 | L61: =IF(L$5="",0,SUMPRODUCT((Plantillas!$A$2:$A$114=L$5)*(Plantillas!$D$2:$D$114=$A61)*(Plantillas!$G$2:$G$114*N(L$6)+Plantillas!$H$2:$H$114))) -> 0 | ... R61: =IF(R$5="",0,SUMPRODUCT((Plantillas!$A$2:$A$114=R$5)*(Plantillas!$D$2:$D$114=$A61)*(Plantillas!$G$2:$G$114*N(R$6)+Plantillas!$H$2:$H$114))) -> 0 | S61: =SUM(E61:R61) -> 0 | T61: =IF(INDEX(Partidas!$F$2:$F$99,MATCH(A61,Partidas!$A$2:$A$99,0))="","",INDEX(Partidas!$F$2:$F$99,MATCH(A61,Partidas!$A$2:$A$99,0))) -> 1160 | U61: =IF(T61="",0,S61*T61) -> 0
A62: CIN-030 | B62: CIN | C62: =INDEX(Partidas!$D$2:$D$99,MATCH(A62,Partidas!$A$2:$A$99,0)) -> Puerta corredera con casoneto | D62: =INDEX(Partidas!$C$2:$C$99,MATCH(A62,Partidas!$A$2:$A$99,0)) -> ud | E62: =IF(E$5="",0,SUMPRODUCT((Plantillas!$A$2:$A$114=E$5)*(Plantillas!$D$2:$D$114=$A62)*(Plantillas!$G$2:$G$114*N(E$6)+Plantillas!$H$2:$H$114))) -> 0 | F62: =IF(F$5="",0,SUMPRODUCT((Plantillas!$A$2:$A$114=F$5)*(Plantillas!$D$2:$D$114=$A62)*(Plantillas!$G$2:$G$114*N(F$6)+Plantillas!$H$2:$H$114))) -> 0 | G62: =IF(G$5="",0,SUMPRODUCT((Plantillas!$A$2:$A$114=G$5)*(Plantillas!$D$2:$D$114=$A62)*(Plantillas!$G$2:$G$114*N(G$6)+Plantillas!$H$2:$H$114))) -> 0 | H62: =IF(H$5="",0,SUMPRODUCT((Plantillas!$A$2:$A$114=H$5)*(Plantillas!$D$2:$D$114=$A62)*(Plantillas!$G$2:$G$114*N(H$6)+Plantillas!$H$2:$H$114))) -> 0 | I62: =IF(I$5="",0,SUMPRODUCT((Plantillas!$A$2:$A$114=I$5)*(Plantillas!$D$2:$D$114=$A62)*(Plantillas!$G$2:$G$114*N(I$6)+Plantillas!$H$2:$H$114))) -> 0 | J62: =IF(J$5="",0,SUMPRODUCT((Plantillas!$A$2:$A$114=J$5)*(Plantillas!$D$2:$D$114=$A62)*(Plantillas!$G$2:$G$114*N(J$6)+Plantillas!$H$2:$H$114))) -> 0 | K62: =IF(K$5="",0,SUMPRODUCT((Plantillas!$A$2:$A$114=K$5)*(Plantillas!$D$2:$D$114=$A62)*(Plantillas!$G$2:$G$114*N(K$6)+Plantillas!$H$2:$H$114))) -> 0 | L62: =IF(L$5="",0,SUMPRODUCT((Plantillas!$A$2:$A$114=L$5)*(Plantillas!$D$2:$D$114=$A62)*(Plantillas!$G$2:$G$114*N(L$6)+Plantillas!$H$2:$H$114))) -> 0 | ... R62: =IF(R$5="",0,SUMPRODUCT((Plantillas!$A$2:$A$114=R$5)*(Plantillas!$D$2:$D$114=$A62)*(Plantillas!$G$2:$G$114*N(R$6)+Plantillas!$H$2:$H$114))) -> 0 | S62: =SUM(E62:R62) -> 1 | T62: =IF(INDEX(Partidas!$F$2:$F$99,MATCH(A62,Partidas!$A$2:$A$99,0))="","",INDEX(Partidas!$F$2:$F$99,MATCH(A62,Partidas!$A$2:$A$99,0))) -> 420 | U62: =IF(T62="",0,S62*T62) -> 420
A63: CIN-040 | B63: CIN | C63: =INDEX(Partidas!$D$2:$D$99,MATCH(A63,Partidas!$A$2:$A$99,0)) -> Armario empotrado de suelo a techo | D63: =INDEX(Partidas!$C$2:$C$99,MATCH(A63,Partidas!$A$2:$A$99,0)) -> m2 | E63: =IF(E$5="",0,SUMPRODUCT((Plantillas!$A$2:$A$114=E$5)*(Plantillas!$D$2:$D$114=$A63)*(Plantillas!$G$2:$G$114*N(E$6)+Plantillas!$H$2:$H$114))) -> 0 | F63: =IF(F$5="",0,SUMPRODUCT((Plantillas!$A$2:$A$114=F$5)*(Plantillas!$D$2:$D$114=$A63)*(Plantillas!$G$2:$G$114*N(F$6)+Plantillas!$H$2:$H$114))) -> 0 | G63: =IF(G$5="",0,SUMPRODUCT((Plantillas!$A$2:$A$114=G$5)*(Plantillas!$D$2:$D$114=$A63)*(Plantillas!$G$2:$G$114*N(G$6)+Plantillas!$H$2:$H$114))) -> 0 | H63: =IF(H$5="",0,SUMPRODUCT((Plantillas!$A$2:$A$114=H$5)*(Plantillas!$D$2:$D$114=$A63)*(Plantillas!$G$2:$G$114*N(H$6)+Plantillas!$H$2:$H$114))) -> 0 | I63: =IF(I$5="",0,SUMPRODUCT((Plantillas!$A$2:$A$114=I$5)*(Plantillas!$D$2:$D$114=$A63)*(Plantillas!$G$2:$G$114*N(I$6)+Plantillas!$H$2:$H$114))) -> 0 | J63: =IF(J$5="",0,SUMPRODUCT((Plantillas!$A$2:$A$114=J$5)*(Plantillas!$D$2:$D$114=$A63)*(Plantillas!$G$2:$G$114*N(J$6)+Plantillas!$H$2:$H$114))) -> 0 | K63: =IF(K$5="",0,SUMPRODUCT((Plantillas!$A$2:$A$114=K$5)*(Plantillas!$D$2:$D$114=$A63)*(Plantillas!$G$2:$G$114*N(K$6)+Plantillas!$H$2:$H$114))) -> 0 | L63: =IF(L$5="",0,SUMPRODUCT((Plantillas!$A$2:$A$114=L$5)*(Plantillas!$D$2:$D$114=$A63)*(Plantillas!$G$2:$G$114*N(L$6)+Plantillas!$H$2:$H$114))) -> 0 | ... R63: =IF(R$5="",0,SUMPRODUCT((Plantillas!$A$2:$A$114=R$5)*(Plantillas!$D$2:$D$114=$A63)*(Plantillas!$G$2:$G$114*N(R$6)+Plantillas!$H$2:$H$114))) -> 0 | S63: =SUM(E63:R63) -> 0 | T63: =IF(INDEX(Partidas!$F$2:$F$99,MATCH(A63,Partidas!$A$2:$A$99,0))="","",INDEX(Partidas!$F$2:$F$99,MATCH(A63,Partidas!$A$2:$A$99,0))) -> 450 | U63: =IF(T63="",0,S63*T63) -> 0
A64: CIN-050 | B64: CIN | C64: =INDEX(Partidas!$D$2:$D$99,MATCH(A64,Partidas!$A$2:$A$99,0)) -> Estantería o librería a medida | D64: =INDEX(Partidas!$C$2:$C$99,MATCH(A64,Partidas!$A$2:$A$99,0)) -> m2 | E64: =IF(E$5="",0,SUMPRODUCT((Plantillas!$A$2:$A$114=E$5)*(Plantillas!$D$2:$D$114=$A64)*(Plantillas!$G$2:$G$114*N(E$6)+Plantillas!$H$2:$H$114))) -> 0 | F64: =IF(F$5="",0,SUMPRODUCT((Plantillas!$A$2:$A$114=F$5)*(Plantillas!$D$2:$D$114=$A64)*(Plantillas!$G$2:$G$114*N(F$6)+Plantillas!$H$2:$H$114))) -> 0 | G64: =IF(G$5="",0,SUMPRODUCT((Plantillas!$A$2:$A$114=G$5)*(Plantillas!$D$2:$D$114=$A64)*(Plantillas!$G$2:$G$114*N(G$6)+Plantillas!$H$2:$H$114))) -> 0 | H64: =IF(H$5="",0,SUMPRODUCT((Plantillas!$A$2:$A$114=H$5)*(Plantillas!$D$2:$D$114=$A64)*(Plantillas!$G$2:$G$114*N(H$6)+Plantillas!$H$2:$H$114))) -> 0 | I64: =IF(I$5="",0,SUMPRODUCT((Plantillas!$A$2:$A$114=I$5)*(Plantillas!$D$2:$D$114=$A64)*(Plantillas!$G$2:$G$114*N(I$6)+Plantillas!$H$2:$H$114))) -> 0 | J64: =IF(J$5="",0,SUMPRODUCT((Plantillas!$A$2:$A$114=J$5)*(Plantillas!$D$2:$D$114=$A64)*(Plantillas!$G$2:$G$114*N(J$6)+Plantillas!$H$2:$H$114))) -> 0 | K64: =IF(K$5="",0,SUMPRODUCT((Plantillas!$A$2:$A$114=K$5)*(Plantillas!$D$2:$D$114=$A64)*(Plantillas!$G$2:$G$114*N(K$6)+Plantillas!$H$2:$H$114))) -> 0 | L64: =IF(L$5="",0,SUMPRODUCT((Plantillas!$A$2:$A$114=L$5)*(Plantillas!$D$2:$D$114=$A64)*(Plantillas!$G$2:$G$114*N(L$6)+Plantillas!$H$2:$H$114))) -> 0 | ... R64: =IF(R$5="",0,SUMPRODUCT((Plantillas!$A$2:$A$114=R$5)*(Plantillas!$D$2:$D$114=$A64)*(Plantillas!$G$2:$G$114*N(R$6)+Plantillas!$H$2:$H$114))) -> 0 | S64: =SUM(E64:R64) -> 0 | T64: =IF(INDEX(Partidas!$F$2:$F$99,MATCH(A64,Partidas!$A$2:$A$99,0))="","",INDEX(Partidas!$F$2:$F$99,MATCH(A64,Partidas!$A$2:$A$99,0))) -> 450 | U64: =IF(T64="",0,S64*T64) -> 0
A65: CIN-060 | B65: CIN | C65: =INDEX(Partidas!$D$2:$D$99,MATCH(A65,Partidas!$A$2:$A$99,0)) -> Mueble de lavandería | D65: =INDEX(Partidas!$C$2:$C$99,MATCH(A65,Partidas!$A$2:$A$99,0)) -> m2 | E65: =IF(E$5="",0,SUMPRODUCT((Plantillas!$A$2:$A$114=E$5)*(Plantillas!$D$2:$D$114=$A65)*(Plantillas!$G$2:$G$114*N(E$6)+Plantillas!$H$2:$H$114))) -> 0 | F65: =IF(F$5="",0,SUMPRODUCT((Plantillas!$A$2:$A$114=F$5)*(Plantillas!$D$2:$D$114=$A65)*(Plantillas!$G$2:$G$114*N(F$6)+Plantillas!$H$2:$H$114))) -> 0 | G65: =IF(G$5="",0,SUMPRODUCT((Plantillas!$A$2:$A$114=G$5)*(Plantillas!$D$2:$D$114=$A65)*(Plantillas!$G$2:$G$114*N(G$6)+Plantillas!$H$2:$H$114))) -> 0 | H65: =IF(H$5="",0,SUMPRODUCT((Plantillas!$A$2:$A$114=H$5)*(Plantillas!$D$2:$D$114=$A65)*(Plantillas!$G$2:$G$114*N(H$6)+Plantillas!$H$2:$H$114))) -> 0 | I65: =IF(I$5="",0,SUMPRODUCT((Plantillas!$A$2:$A$114=I$5)*(Plantillas!$D$2:$D$114=$A65)*(Plantillas!$G$2:$G$114*N(I$6)+Plantillas!$H$2:$H$114))) -> 0 | J65: =IF(J$5="",0,SUMPRODUCT((Plantillas!$A$2:$A$114=J$5)*(Plantillas!$D$2:$D$114=$A65)*(Plantillas!$G$2:$G$114*N(J$6)+Plantillas!$H$2:$H$114))) -> 0 | K65: =IF(K$5="",0,SUMPRODUCT((Plantillas!$A$2:$A$114=K$5)*(Plantillas!$D$2:$D$114=$A65)*(Plantillas!$G$2:$G$114*N(K$6)+Plantillas!$H$2:$H$114))) -> 0 | L65: =IF(L$5="",0,SUMPRODUCT((Plantillas!$A$2:$A$114=L$5)*(Plantillas!$D$2:$D$114=$A65)*(Plantillas!$G$2:$G$114*N(L$6)+Plantillas!$H$2:$H$114))) -> 0 | ... R65: =IF(R$5="",0,SUMPRODUCT((Plantillas!$A$2:$A$114=R$5)*(Plantillas!$D$2:$D$114=$A65)*(Plantillas!$G$2:$G$114*N(R$6)+Plantillas!$H$2:$H$114))) -> 0 | S65: =SUM(E65:R65) -> 0 | T65: =IF(INDEX(Partidas!$F$2:$F$99,MATCH(A65,Partidas!$A$2:$A$99,0))="","",INDEX(Partidas!$F$2:$F$99,MATCH(A65,Partidas!$A$2:$A$99,0))) -> 320 | U65: =IF(T65="",0,S65*T65) -> 0
A66: FON | C66: Fontanería y saneamiento | U66: =SUM(U67:U71) -> 2370
A67: FON-010 | B67: FON | C67: =INDEX(Partidas!$D$2:$D$99,MATCH(A67,Partidas!$A$2:$A$99,0)) -> Punto de agua fría y caliente | D67: =INDEX(Partidas!$C$2:$C$99,MATCH(A67,Partidas!$A$2:$A$99,0)) -> ud | E67: =IF(E$5="",0,SUMPRODUCT((Plantillas!$A$2:$A$114=E$5)*(Plantillas!$D$2:$D$114=$A67)*(Plantillas!$G$2:$G$114*N(E$6)+Plantillas!$H$2:$H$114))) -> 0 | F67: =IF(F$5="",0,SUMPRODUCT((Plantillas!$A$2:$A$114=F$5)*(Plantillas!$D$2:$D$114=$A67)*(Plantillas!$G$2:$G$114*N(F$6)+Plantillas!$H$2:$H$114))) -> 0 | G67: =IF(G$5="",0,SUMPRODUCT((Plantillas!$A$2:$A$114=G$5)*(Plantillas!$D$2:$D$114=$A67)*(Plantillas!$G$2:$G$114*N(G$6)+Plantillas!$H$2:$H$114))) -> 0 | H67: =IF(H$5="",0,SUMPRODUCT((Plantillas!$A$2:$A$114=H$5)*(Plantillas!$D$2:$D$114=$A67)*(Plantillas!$G$2:$G$114*N(H$6)+Plantillas!$H$2:$H$114))) -> 0 | I67: =IF(I$5="",0,SUMPRODUCT((Plantillas!$A$2:$A$114=I$5)*(Plantillas!$D$2:$D$114=$A67)*(Plantillas!$G$2:$G$114*N(I$6)+Plantillas!$H$2:$H$114))) -> 0 | J67: =IF(J$5="",0,SUMPRODUCT((Plantillas!$A$2:$A$114=J$5)*(Plantillas!$D$2:$D$114=$A67)*(Plantillas!$G$2:$G$114*N(J$6)+Plantillas!$H$2:$H$114))) -> 0 | K67: =IF(K$5="",0,SUMPRODUCT((Plantillas!$A$2:$A$114=K$5)*(Plantillas!$D$2:$D$114=$A67)*(Plantillas!$G$2:$G$114*N(K$6)+Plantillas!$H$2:$H$114))) -> 0 | L67: =IF(L$5="",0,SUMPRODUCT((Plantillas!$A$2:$A$114=L$5)*(Plantillas!$D$2:$D$114=$A67)*(Plantillas!$G$2:$G$114*N(L$6)+Plantillas!$H$2:$H$114))) -> 3 | ... R67: =IF(R$5="",0,SUMPRODUCT((Plantillas!$A$2:$A$114=R$5)*(Plantillas!$D$2:$D$114=$A67)*(Plantillas!$G$2:$G$114*N(R$6)+Plantillas!$H$2:$H$114))) -> 0 | S67: =SUM(E67:R67) -> 14 | T67: =IF(INDEX(Partidas!$F$2:$F$99,MATCH(A67,Partidas!$A$2:$A$99,0))="","",INDEX(Partidas!$F$2:$F$99,MATCH(A67,Partidas!$A$2:$A$99,0))) -> 120 | U67: =IF(T67="",0,S67*T67) -> 1680
A68: FON-020 | B68: FON | C68: =INDEX(Partidas!$D$2:$D$99,MATCH(A68,Partidas!$A$2:$A$99,0)) -> Punto de desagüe | D68: =INDEX(Partidas!$C$2:$C$99,MATCH(A68,Partidas!$A$2:$A$99,0)) -> ud | E68: =IF(E$5="",0,SUMPRODUCT((Plantillas!$A$2:$A$114=E$5)*(Plantillas!$D$2:$D$114=$A68)*(Plantillas!$G$2:$G$114*N(E$6)+Plantillas!$H$2:$H$114))) -> 0 | F68: =IF(F$5="",0,SUMPRODUCT((Plantillas!$A$2:$A$114=F$5)*(Plantillas!$D$2:$D$114=$A68)*(Plantillas!$G$2:$G$114*N(F$6)+Plantillas!$H$2:$H$114))) -> 0 | G68: =IF(G$5="",0,SUMPRODUCT((Plantillas!$A$2:$A$114=G$5)*(Plantillas!$D$2:$D$114=$A68)*(Plantillas!$G$2:$G$114*N(G$6)+Plantillas!$H$2:$H$114))) -> 0 | H68: =IF(H$5="",0,SUMPRODUCT((Plantillas!$A$2:$A$114=H$5)*(Plantillas!$D$2:$D$114=$A68)*(Plantillas!$G$2:$G$114*N(H$6)+Plantillas!$H$2:$H$114))) -> 0 | I68: =IF(I$5="",0,SUMPRODUCT((Plantillas!$A$2:$A$114=I$5)*(Plantillas!$D$2:$D$114=$A68)*(Plantillas!$G$2:$G$114*N(I$6)+Plantillas!$H$2:$H$114))) -> 0 | J68: =IF(J$5="",0,SUMPRODUCT((Plantillas!$A$2:$A$114=J$5)*(Plantillas!$D$2:$D$114=$A68)*(Plantillas!$G$2:$G$114*N(J$6)+Plantillas!$H$2:$H$114))) -> 0 | K68: =IF(K$5="",0,SUMPRODUCT((Plantillas!$A$2:$A$114=K$5)*(Plantillas!$D$2:$D$114=$A68)*(Plantillas!$G$2:$G$114*N(K$6)+Plantillas!$H$2:$H$114))) -> 0 | L68: =IF(L$5="",0,SUMPRODUCT((Plantillas!$A$2:$A$114=L$5)*(Plantillas!$D$2:$D$114=$A68)*(Plantillas!$G$2:$G$114*N(L$6)+Plantillas!$H$2:$H$114))) -> 2 | ... R68: =IF(R$5="",0,SUMPRODUCT((Plantillas!$A$2:$A$114=R$5)*(Plantillas!$D$2:$D$114=$A68)*(Plantillas!$G$2:$G$114*N(R$6)+Plantillas!$H$2:$H$114))) -> 0 | S68: =SUM(E68:R68) -> 9 | T68: =IF(INDEX(Partidas!$F$2:$F$99,MATCH(A68,Partidas!$A$2:$A$99,0))="","",INDEX(Partidas!$F$2:$F$99,MATCH(A68,Partidas!$A$2:$A$99,0))) -> 60 | U68: =IF(T68="",0,S68*T68) -> 540
A69: FON-030 | B69: FON | C69: =INDEX(Partidas!$D$2:$D$99,MATCH(A69,Partidas!$A$2:$A$99,0)) -> Bote sifónico | D69: =INDEX(Partidas!$C$2:$C$99,MATCH(A69,Partidas!$A$2:$A$99,0)) -> ud | E69: =IF(E$5="",0,SUMPRODUCT((Plantillas!$A$2:$A$114=E$5)*(Plantillas!$D$2:$D$114=$A69)*(Plantillas!$G$2:$G$114*N(E$6)+Plantillas!$H$2:$H$114))) -> 0 | F69: =IF(F$5="",0,SUMPRODUCT((Plantillas!$A$2:$A$114=F$5)*(Plantillas!$D$2:$D$114=$A69)*(Plantillas!$G$2:$G$114*N(F$6)+Plantillas!$H$2:$H$114))) -> 0 | G69: =IF(G$5="",0,SUMPRODUCT((Plantillas!$A$2:$A$114=G$5)*(Plantillas!$D$2:$D$114=$A69)*(Plantillas!$G$2:$G$114*N(G$6)+Plantillas!$H$2:$H$114))) -> 0 | H69: =IF(H$5="",0,SUMPRODUCT((Plantillas!$A$2:$A$114=H$5)*(Plantillas!$D$2:$D$114=$A69)*(Plantillas!$G$2:$G$114*N(H$6)+Plantillas!$H$2:$H$114))) -> 0 | I69: =IF(I$5="",0,SUMPRODUCT((Plantillas!$A$2:$A$114=I$5)*(Plantillas!$D$2:$D$114=$A69)*(Plantillas!$G$2:$G$114*N(I$6)+Plantillas!$H$2:$H$114))) -> 0 | J69: =IF(J$5="",0,SUMPRODUCT((Plantillas!$A$2:$A$114=J$5)*(Plantillas!$D$2:$D$114=$A69)*(Plantillas!$G$2:$G$114*N(J$6)+Plantillas!$H$2:$H$114))) -> 0 | K69: =IF(K$5="",0,SUMPRODUCT((Plantillas!$A$2:$A$114=K$5)*(Plantillas!$D$2:$D$114=$A69)*(Plantillas!$G$2:$G$114*N(K$6)+Plantillas!$H$2:$H$114))) -> 0 | L69: =IF(L$5="",0,SUMPRODUCT((Plantillas!$A$2:$A$114=L$5)*(Plantillas!$D$2:$D$114=$A69)*(Plantillas!$G$2:$G$114*N(L$6)+Plantillas!$H$2:$H$114))) -> 0 | ... R69: =IF(R$5="",0,SUMPRODUCT((Plantillas!$A$2:$A$114=R$5)*(Plantillas!$D$2:$D$114=$A69)*(Plantillas!$G$2:$G$114*N(R$6)+Plantillas!$H$2:$H$114))) -> 0 | S69: =SUM(E69:R69) -> 2 | T69: =IF(INDEX(Partidas!$F$2:$F$99,MATCH(A69,Partidas!$A$2:$A$99,0))="","",INDEX(Partidas!$F$2:$F$99,MATCH(A69,Partidas!$A$2:$A$99,0))) -> 75 | U69: =IF(T69="",0,S69*T69) -> 150
A70: FON-040 | B70: FON | C70: =INDEX(Partidas!$D$2:$D$99,MATCH(A70,Partidas!$A$2:$A$99,0)) -> Llave de corte por estancia húmeda | D70: =INDEX(Partidas!$C$2:$C$99,MATCH(A70,Partidas!$A$2:$A$99,0)) -> ud | E70: =IF(E$5="",0,SUMPRODUCT((Plantillas!$A$2:$A$114=E$5)*(Plantillas!$D$2:$D$114=$A70)*(Plantillas!$G$2:$G$114*N(E$6)+Plantillas!$H$2:$H$114))) -> 0 | F70: =IF(F$5="",0,SUMPRODUCT((Plantillas!$A$2:$A$114=F$5)*(Plantillas!$D$2:$D$114=$A70)*(Plantillas!$G$2:$G$114*N(F$6)+Plantillas!$H$2:$H$114))) -> 0 | G70: =IF(G$5="",0,SUMPRODUCT((Plantillas!$A$2:$A$114=G$5)*(Plantillas!$D$2:$D$114=$A70)*(Plantillas!$G$2:$G$114*N(G$6)+Plantillas!$H$2:$H$114))) -> 0 | H70: =IF(H$5="",0,SUMPRODUCT((Plantillas!$A$2:$A$114=H$5)*(Plantillas!$D$2:$D$114=$A70)*(Plantillas!$G$2:$G$114*N(H$6)+Plantillas!$H$2:$H$114))) -> 0 | I70: =IF(I$5="",0,SUMPRODUCT((Plantillas!$A$2:$A$114=I$5)*(Plantillas!$D$2:$D$114=$A70)*(Plantillas!$G$2:$G$114*N(I$6)+Plantillas!$H$2:$H$114))) -> 0 | J70: =IF(J$5="",0,SUMPRODUCT((Plantillas!$A$2:$A$114=J$5)*(Plantillas!$D$2:$D$114=$A70)*(Plantillas!$G$2:$G$114*N(J$6)+Plantillas!$H$2:$H$114))) -> 0 | K70: =IF(K$5="",0,SUMPRODUCT((Plantillas!$A$2:$A$114=K$5)*(Plantillas!$D$2:$D$114=$A70)*(Plantillas!$G$2:$G$114*N(K$6)+Plantillas!$H$2:$H$114))) -> 0 | L70: =IF(L$5="",0,SUMPRODUCT((Plantillas!$A$2:$A$114=L$5)*(Plantillas!$D$2:$D$114=$A70)*(Plantillas!$G$2:$G$114*N(L$6)+Plantillas!$H$2:$H$114))) -> 1 | ... R70: =IF(R$5="",0,SUMPRODUCT((Plantillas!$A$2:$A$114=R$5)*(Plantillas!$D$2:$D$114=$A70)*(Plantillas!$G$2:$G$114*N(R$6)+Plantillas!$H$2:$H$114))) -> 0 | S70: =SUM(E70:R70) -> 3 | T70: =IF(INDEX(Partidas!$F$2:$F$99,MATCH(A70,Partidas!$A$2:$A$99,0))="","",INDEX(Partidas!$F$2:$F$99,MATCH(A70,Partidas!$A$2:$A$99,0))) | U70: =IF(T70="",0,S70*T70) -> 0
A71: FON-050 | B71: FON | C71: =INDEX(Partidas!$D$2:$D$99,MATCH(A71,Partidas!$A$2:$A$99,0)) -> Pruebas de presión y estanqueidad | D71: =INDEX(Partidas!$C$2:$C$99,MATCH(A71,Partidas!$A$2:$A$99,0)) -> pa | E71: =IF(E$5="",0,SUMPRODUCT((Plantillas!$A$2:$A$114=E$5)*(Plantillas!$D$2:$D$114=$A71)*(Plantillas!$G$2:$G$114*N(E$6)+Plantillas!$H$2:$H$114))) -> 0 | F71: =IF(F$5="",0,SUMPRODUCT((Plantillas!$A$2:$A$114=F$5)*(Plantillas!$D$2:$D$114=$A71)*(Plantillas!$G$2:$G$114*N(F$6)+Plantillas!$H$2:$H$114))) -> 0 | G71: =IF(G$5="",0,SUMPRODUCT((Plantillas!$A$2:$A$114=G$5)*(Plantillas!$D$2:$D$114=$A71)*(Plantillas!$G$2:$G$114*N(G$6)+Plantillas!$H$2:$H$114))) -> 0 | H71: =IF(H$5="",0,SUMPRODUCT((Plantillas!$A$2:$A$114=H$5)*(Plantillas!$D$2:$D$114=$A71)*(Plantillas!$G$2:$G$114*N(H$6)+Plantillas!$H$2:$H$114))) -> 0 | I71: =IF(I$5="",0,SUMPRODUCT((Plantillas!$A$2:$A$114=I$5)*(Plantillas!$D$2:$D$114=$A71)*(Plantillas!$G$2:$G$114*N(I$6)+Plantillas!$H$2:$H$114))) -> 0 | J71: =IF(J$5="",0,SUMPRODUCT((Plantillas!$A$2:$A$114=J$5)*(Plantillas!$D$2:$D$114=$A71)*(Plantillas!$G$2:$G$114*N(J$6)+Plantillas!$H$2:$H$114))) -> 0 | K71: =IF(K$5="",0,SUMPRODUCT((Plantillas!$A$2:$A$114=K$5)*(Plantillas!$D$2:$D$114=$A71)*(Plantillas!$G$2:$G$114*N(K$6)+Plantillas!$H$2:$H$114))) -> 0 | L71: =IF(L$5="",0,SUMPRODUCT((Plantillas!$A$2:$A$114=L$5)*(Plantillas!$D$2:$D$114=$A71)*(Plantillas!$G$2:$G$114*N(L$6)+Plantillas!$H$2:$H$114))) -> 0 | ... R71: =IF(R$5="",0,SUMPRODUCT((Plantillas!$A$2:$A$114=R$5)*(Plantillas!$D$2:$D$114=$A71)*(Plantillas!$G$2:$G$114*N(R$6)+Plantillas!$H$2:$H$114))) -> 0 | S71: =SUM(E71:R71) -> 0 | T71: =IF(INDEX(Partidas!$F$2:$F$99,MATCH(A71,Partidas!$A$2:$A$99,0))="","",INDEX(Partidas!$F$2:$F$99,MATCH(A71,Partidas!$A$2:$A$99,0))) | U71: =IF(T71="",0,S71*T71) -> 0
A72: SAN | C72: Sanitarios, grifería y equipamiento de baño | U72: =SUM(U73:U84) -> 6292
A73: SAN-010 | B73: SAN | C73: =INDEX(Partidas!$D$2:$D$99,MATCH(A73,Partidas!$A$2:$A$99,0)) -> Plato de ducha | D73: =INDEX(Partidas!$C$2:$C$99,MATCH(A73,Partidas!$A$2:$A$99,0)) -> ud | E73: =IF(E$5="",0,SUMPRODUCT((Plantillas!$A$2:$A$114=E$5)*(Plantillas!$D$2:$D$114=$A73)*(Plantillas!$G$2:$G$114*N(E$6)+Plantillas!$H$2:$H$114))) -> 0 | F73: =IF(F$5="",0,SUMPRODUCT((Plantillas!$A$2:$A$114=F$5)*(Plantillas!$D$2:$D$114=$A73)*(Plantillas!$G$2:$G$114*N(F$6)+Plantillas!$H$2:$H$114))) -> 0 | G73: =IF(G$5="",0,SUMPRODUCT((Plantillas!$A$2:$A$114=G$5)*(Plantillas!$D$2:$D$114=$A73)*(Plantillas!$G$2:$G$114*N(G$6)+Plantillas!$H$2:$H$114))) -> 0 | H73: =IF(H$5="",0,SUMPRODUCT((Plantillas!$A$2:$A$114=H$5)*(Plantillas!$D$2:$D$114=$A73)*(Plantillas!$G$2:$G$114*N(H$6)+Plantillas!$H$2:$H$114))) -> 0 | I73: =IF(I$5="",0,SUMPRODUCT((Plantillas!$A$2:$A$114=I$5)*(Plantillas!$D$2:$D$114=$A73)*(Plantillas!$G$2:$G$114*N(I$6)+Plantillas!$H$2:$H$114))) -> 0 | J73: =IF(J$5="",0,SUMPRODUCT((Plantillas!$A$2:$A$114=J$5)*(Plantillas!$D$2:$D$114=$A73)*(Plantillas!$G$2:$G$114*N(J$6)+Plantillas!$H$2:$H$114))) -> 0 | K73: =IF(K$5="",0,SUMPRODUCT((Plantillas!$A$2:$A$114=K$5)*(Plantillas!$D$2:$D$114=$A73)*(Plantillas!$G$2:$G$114*N(K$6)+Plantillas!$H$2:$H$114))) -> 0 | L73: =IF(L$5="",0,SUMPRODUCT((Plantillas!$A$2:$A$114=L$5)*(Plantillas!$D$2:$D$114=$A73)*(Plantillas!$G$2:$G$114*N(L$6)+Plantillas!$H$2:$H$114))) -> 0 | ... R73: =IF(R$5="",0,SUMPRODUCT((Plantillas!$A$2:$A$114=R$5)*(Plantillas!$D$2:$D$114=$A73)*(Plantillas!$G$2:$G$114*N(R$6)+Plantillas!$H$2:$H$114))) -> 0 | S73: =SUM(E73:R73) -> 2 | T73: =IF(INDEX(Partidas!$F$2:$F$99,MATCH(A73,Partidas!$A$2:$A$99,0))="","",INDEX(Partidas!$F$2:$F$99,MATCH(A73,Partidas!$A$2:$A$99,0))) -> 640 | U73: =IF(T73="",0,S73*T73) -> 1280
A74: SAN-020 | B74: SAN | C74: =INDEX(Partidas!$D$2:$D$99,MATCH(A74,Partidas!$A$2:$A$99,0)) -> Bañera | D74: =INDEX(Partidas!$C$2:$C$99,MATCH(A74,Partidas!$A$2:$A$99,0)) -> ud | E74: =IF(E$5="",0,SUMPRODUCT((Plantillas!$A$2:$A$114=E$5)*(Plantillas!$D$2:$D$114=$A74)*(Plantillas!$G$2:$G$114*N(E$6)+Plantillas!$H$2:$H$114))) -> 0 | F74: =IF(F$5="",0,SUMPRODUCT((Plantillas!$A$2:$A$114=F$5)*(Plantillas!$D$2:$D$114=$A74)*(Plantillas!$G$2:$G$114*N(F$6)+Plantillas!$H$2:$H$114))) -> 0 | G74: =IF(G$5="",0,SUMPRODUCT((Plantillas!$A$2:$A$114=G$5)*(Plantillas!$D$2:$D$114=$A74)*(Plantillas!$G$2:$G$114*N(G$6)+Plantillas!$H$2:$H$114))) -> 0 | H74: =IF(H$5="",0,SUMPRODUCT((Plantillas!$A$2:$A$114=H$5)*(Plantillas!$D$2:$D$114=$A74)*(Plantillas!$G$2:$G$114*N(H$6)+Plantillas!$H$2:$H$114))) -> 0 | I74: =IF(I$5="",0,SUMPRODUCT((Plantillas!$A$2:$A$114=I$5)*(Plantillas!$D$2:$D$114=$A74)*(Plantillas!$G$2:$G$114*N(I$6)+Plantillas!$H$2:$H$114))) -> 0 | J74: =IF(J$5="",0,SUMPRODUCT((Plantillas!$A$2:$A$114=J$5)*(Plantillas!$D$2:$D$114=$A74)*(Plantillas!$G$2:$G$114*N(J$6)+Plantillas!$H$2:$H$114))) -> 0 | K74: =IF(K$5="",0,SUMPRODUCT((Plantillas!$A$2:$A$114=K$5)*(Plantillas!$D$2:$D$114=$A74)*(Plantillas!$G$2:$G$114*N(K$6)+Plantillas!$H$2:$H$114))) -> 0 | L74: =IF(L$5="",0,SUMPRODUCT((Plantillas!$A$2:$A$114=L$5)*(Plantillas!$D$2:$D$114=$A74)*(Plantillas!$G$2:$G$114*N(L$6)+Plantillas!$H$2:$H$114))) -> 0 | ... R74: =IF(R$5="",0,SUMPRODUCT((Plantillas!$A$2:$A$114=R$5)*(Plantillas!$D$2:$D$114=$A74)*(Plantillas!$G$2:$G$114*N(R$6)+Plantillas!$H$2:$H$114))) -> 0 | S74: =SUM(E74:R74) -> 0 | T74: =IF(INDEX(Partidas!$F$2:$F$99,MATCH(A74,Partidas!$A$2:$A$99,0))="","",INDEX(Partidas!$F$2:$F$99,MATCH(A74,Partidas!$A$2:$A$99,0))) -> 850 | U74: =IF(T74="",0,S74*T74) -> 0
A75: SAN-030 | B75: SAN | C75: =INDEX(Partidas!$D$2:$D$99,MATCH(A75,Partidas!$A$2:$A$99,0)) -> Inodoro suspendido con bastidor | D75: =INDEX(Partidas!$C$2:$C$99,MATCH(A75,Partidas!$A$2:$A$99,0)) -> ud | E75: =IF(E$5="",0,SUMPRODUCT((Plantillas!$A$2:$A$114=E$5)*(Plantillas!$D$2:$D$114=$A75)*(Plantillas!$G$2:$G$114*N(E$6)+Plantillas!$H$2:$H$114))) -> 0 | F75: =IF(F$5="",0,SUMPRODUCT((Plantillas!$A$2:$A$114=F$5)*(Plantillas!$D$2:$D$114=$A75)*(Plantillas!$G$2:$G$114*N(F$6)+Plantillas!$H$2:$H$114))) -> 0 | G75: =IF(G$5="",0,SUMPRODUCT((Plantillas!$A$2:$A$114=G$5)*(Plantillas!$D$2:$D$114=$A75)*(Plantillas!$G$2:$G$114*N(G$6)+Plantillas!$H$2:$H$114))) -> 0 | H75: =IF(H$5="",0,SUMPRODUCT((Plantillas!$A$2:$A$114=H$5)*(Plantillas!$D$2:$D$114=$A75)*(Plantillas!$G$2:$G$114*N(H$6)+Plantillas!$H$2:$H$114))) -> 0 | I75: =IF(I$5="",0,SUMPRODUCT((Plantillas!$A$2:$A$114=I$5)*(Plantillas!$D$2:$D$114=$A75)*(Plantillas!$G$2:$G$114*N(I$6)+Plantillas!$H$2:$H$114))) -> 0 | J75: =IF(J$5="",0,SUMPRODUCT((Plantillas!$A$2:$A$114=J$5)*(Plantillas!$D$2:$D$114=$A75)*(Plantillas!$G$2:$G$114*N(J$6)+Plantillas!$H$2:$H$114))) -> 0 | K75: =IF(K$5="",0,SUMPRODUCT((Plantillas!$A$2:$A$114=K$5)*(Plantillas!$D$2:$D$114=$A75)*(Plantillas!$G$2:$G$114*N(K$6)+Plantillas!$H$2:$H$114))) -> 0 | L75: =IF(L$5="",0,SUMPRODUCT((Plantillas!$A$2:$A$114=L$5)*(Plantillas!$D$2:$D$114=$A75)*(Plantillas!$G$2:$G$114*N(L$6)+Plantillas!$H$2:$H$114))) -> 0 | ... R75: =IF(R$5="",0,SUMPRODUCT((Plantillas!$A$2:$A$114=R$5)*(Plantillas!$D$2:$D$114=$A75)*(Plantillas!$G$2:$G$114*N(R$6)+Plantillas!$H$2:$H$114))) -> 0 | S75: =SUM(E75:R75) -> 2 | T75: =IF(INDEX(Partidas!$F$2:$F$99,MATCH(A75,Partidas!$A$2:$A$99,0))="","",INDEX(Partidas!$F$2:$F$99,MATCH(A75,Partidas!$A$2:$A$99,0))) -> 850 | U75: =IF(T75="",0,S75*T75) -> 1700
A76: SAN-040 | B76: SAN | C76: =INDEX(Partidas!$D$2:$D$99,MATCH(A76,Partidas!$A$2:$A$99,0)) -> Mueble de baño con lavabo | D76: =INDEX(Partidas!$C$2:$C$99,MATCH(A76,Partidas!$A$2:$A$99,0)) -> ud | E76: =IF(E$5="",0,SUMPRODUCT((Plantillas!$A$2:$A$114=E$5)*(Plantillas!$D$2:$D$114=$A76)*(Plantillas!$G$2:$G$114*N(E$6)+Plantillas!$H$2:$H$114))) -> 0 | F76: =IF(F$5="",0,SUMPRODUCT((Plantillas!$A$2:$A$114=F$5)*(Plantillas!$D$2:$D$114=$A76)*(Plantillas!$G$2:$G$114*N(F$6)+Plantillas!$H$2:$H$114))) -> 0 | G76: =IF(G$5="",0,SUMPRODUCT((Plantillas!$A$2:$A$114=G$5)*(Plantillas!$D$2:$D$114=$A76)*(Plantillas!$G$2:$G$114*N(G$6)+Plantillas!$H$2:$H$114))) -> 0 | H76: =IF(H$5="",0,SUMPRODUCT((Plantillas!$A$2:$A$114=H$5)*(Plantillas!$D$2:$D$114=$A76)*(Plantillas!$G$2:$G$114*N(H$6)+Plantillas!$H$2:$H$114))) -> 0 | I76: =IF(I$5="",0,SUMPRODUCT((Plantillas!$A$2:$A$114=I$5)*(Plantillas!$D$2:$D$114=$A76)*(Plantillas!$G$2:$G$114*N(I$6)+Plantillas!$H$2:$H$114))) -> 0 | J76: =IF(J$5="",0,SUMPRODUCT((Plantillas!$A$2:$A$114=J$5)*(Plantillas!$D$2:$D$114=$A76)*(Plantillas!$G$2:$G$114*N(J$6)+Plantillas!$H$2:$H$114))) -> 0 | K76: =IF(K$5="",0,SUMPRODUCT((Plantillas!$A$2:$A$114=K$5)*(Plantillas!$D$2:$D$114=$A76)*(Plantillas!$G$2:$G$114*N(K$6)+Plantillas!$H$2:$H$114))) -> 0 | L76: =IF(L$5="",0,SUMPRODUCT((Plantillas!$A$2:$A$114=L$5)*(Plantillas!$D$2:$D$114=$A76)*(Plantillas!$G$2:$G$114*N(L$6)+Plantillas!$H$2:$H$114))) -> 0 | ... R76: =IF(R$5="",0,SUMPRODUCT((Plantillas!$A$2:$A$114=R$5)*(Plantillas!$D$2:$D$114=$A76)*(Plantillas!$G$2:$G$114*N(R$6)+Plantillas!$H$2:$H$114))) -> 0 | S76: =SUM(E76:R76) -> 2 | T76: =IF(INDEX(Partidas!$F$2:$F$99,MATCH(A76,Partidas!$A$2:$A$99,0))="","",INDEX(Partidas!$F$2:$F$99,MATCH(A76,Partidas!$A$2:$A$99,0))) -> 420 | U76: =IF(T76="",0,S76*T76) -> 840
A77: SAN-050 | B77: SAN | C77: =INDEX(Partidas!$D$2:$D$99,MATCH(A77,Partidas!$A$2:$A$99,0)) -> Grifería de lavabo | D77: =INDEX(Partidas!$C$2:$C$99,MATCH(A77,Partidas!$A$2:$A$99,0)) -> ud | E77: =IF(E$5="",0,SUMPRODUCT((Plantillas!$A$2:$A$114=E$5)*(Plantillas!$D$2:$D$114=$A77)*(Plantillas!$G$2:$G$114*N(E$6)+Plantillas!$H$2:$H$114))) -> 0 | F77: =IF(F$5="",0,SUMPRODUCT((Plantillas!$A$2:$A$114=F$5)*(Plantillas!$D$2:$D$114=$A77)*(Plantillas!$G$2:$G$114*N(F$6)+Plantillas!$H$2:$H$114))) -> 0 | G77: =IF(G$5="",0,SUMPRODUCT((Plantillas!$A$2:$A$114=G$5)*(Plantillas!$D$2:$D$114=$A77)*(Plantillas!$G$2:$G$114*N(G$6)+Plantillas!$H$2:$H$114))) -> 0 | H77: =IF(H$5="",0,SUMPRODUCT((Plantillas!$A$2:$A$114=H$5)*(Plantillas!$D$2:$D$114=$A77)*(Plantillas!$G$2:$G$114*N(H$6)+Plantillas!$H$2:$H$114))) -> 0 | I77: =IF(I$5="",0,SUMPRODUCT((Plantillas!$A$2:$A$114=I$5)*(Plantillas!$D$2:$D$114=$A77)*(Plantillas!$G$2:$G$114*N(I$6)+Plantillas!$H$2:$H$114))) -> 0 | J77: =IF(J$5="",0,SUMPRODUCT((Plantillas!$A$2:$A$114=J$5)*(Plantillas!$D$2:$D$114=$A77)*(Plantillas!$G$2:$G$114*N(J$6)+Plantillas!$H$2:$H$114))) -> 0 | K77: =IF(K$5="",0,SUMPRODUCT((Plantillas!$A$2:$A$114=K$5)*(Plantillas!$D$2:$D$114=$A77)*(Plantillas!$G$2:$G$114*N(K$6)+Plantillas!$H$2:$H$114))) -> 0 | L77: =IF(L$5="",0,SUMPRODUCT((Plantillas!$A$2:$A$114=L$5)*(Plantillas!$D$2:$D$114=$A77)*(Plantillas!$G$2:$G$114*N(L$6)+Plantillas!$H$2:$H$114))) -> 0 | ... R77: =IF(R$5="",0,SUMPRODUCT((Plantillas!$A$2:$A$114=R$5)*(Plantillas!$D$2:$D$114=$A77)*(Plantillas!$G$2:$G$114*N(R$6)+Plantillas!$H$2:$H$114))) -> 0 | S77: =SUM(E77:R77) -> 2 | T77: =IF(INDEX(Partidas!$F$2:$F$99,MATCH(A77,Partidas!$A$2:$A$99,0))="","",INDEX(Partidas!$F$2:$F$99,MATCH(A77,Partidas!$A$2:$A$99,0))) -> 255 | U77: =IF(T77="",0,S77*T77) -> 510
A78: SAN-060 | B78: SAN | C78: =INDEX(Partidas!$D$2:$D$99,MATCH(A78,Partidas!$A$2:$A$99,0)) -> Grifería termostática de ducha o bañera | D78: =INDEX(Partidas!$C$2:$C$99,MATCH(A78,Partidas!$A$2:$A$99,0)) -> ud | E78: =IF(E$5="",0,SUMPRODUCT((Plantillas!$A$2:$A$114=E$5)*(Plantillas!$D$2:$D$114=$A78)*(Plantillas!$G$2:$G$114*N(E$6)+Plantillas!$H$2:$H$114))) -> 0 | F78: =IF(F$5="",0,SUMPRODUCT((Plantillas!$A$2:$A$114=F$5)*(Plantillas!$D$2:$D$114=$A78)*(Plantillas!$G$2:$G$114*N(F$6)+Plantillas!$H$2:$H$114))) -> 0 | G78: =IF(G$5="",0,SUMPRODUCT((Plantillas!$A$2:$A$114=G$5)*(Plantillas!$D$2:$D$114=$A78)*(Plantillas!$G$2:$G$114*N(G$6)+Plantillas!$H$2:$H$114))) -> 0 | H78: =IF(H$5="",0,SUMPRODUCT((Plantillas!$A$2:$A$114=H$5)*(Plantillas!$D$2:$D$114=$A78)*(Plantillas!$G$2:$G$114*N(H$6)+Plantillas!$H$2:$H$114))) -> 0 | I78: =IF(I$5="",0,SUMPRODUCT((Plantillas!$A$2:$A$114=I$5)*(Plantillas!$D$2:$D$114=$A78)*(Plantillas!$G$2:$G$114*N(I$6)+Plantillas!$H$2:$H$114))) -> 0 | J78: =IF(J$5="",0,SUMPRODUCT((Plantillas!$A$2:$A$114=J$5)*(Plantillas!$D$2:$D$114=$A78)*(Plantillas!$G$2:$G$114*N(J$6)+Plantillas!$H$2:$H$114))) -> 0 | K78: =IF(K$5="",0,SUMPRODUCT((Plantillas!$A$2:$A$114=K$5)*(Plantillas!$D$2:$D$114=$A78)*(Plantillas!$G$2:$G$114*N(K$6)+Plantillas!$H$2:$H$114))) -> 0 | L78: =IF(L$5="",0,SUMPRODUCT((Plantillas!$A$2:$A$114=L$5)*(Plantillas!$D$2:$D$114=$A78)*(Plantillas!$G$2:$G$114*N(L$6)+Plantillas!$H$2:$H$114))) -> 0 | ... R78: =IF(R$5="",0,SUMPRODUCT((Plantillas!$A$2:$A$114=R$5)*(Plantillas!$D$2:$D$114=$A78)*(Plantillas!$G$2:$G$114*N(R$6)+Plantillas!$H$2:$H$114))) -> 0 | S78: =SUM(E78:R78) -> 2 | T78: =IF(INDEX(Partidas!$F$2:$F$99,MATCH(A78,Partidas!$A$2:$A$99,0))="","",INDEX(Partidas!$F$2:$F$99,MATCH(A78,Partidas!$A$2:$A$99,0))) -> 255 | U78: =IF(T78="",0,S78*T78) -> 510
A79: SAN-070 | B79: SAN | C79: =INDEX(Partidas!$D$2:$D$99,MATCH(A79,Partidas!$A$2:$A$99,0)) -> Mampara fija de ducha | D79: =INDEX(Partidas!$C$2:$C$99,MATCH(A79,Partidas!$A$2:$A$99,0)) -> ud | E79: =IF(E$5="",0,SUMPRODUCT((Plantillas!$A$2:$A$114=E$5)*(Plantillas!$D$2:$D$114=$A79)*(Plantillas!$G$2:$G$114*N(E$6)+Plantillas!$H$2:$H$114))) -> 0 | F79: =IF(F$5="",0,SUMPRODUCT((Plantillas!$A$2:$A$114=F$5)*(Plantillas!$D$2:$D$114=$A79)*(Plantillas!$G$2:$G$114*N(F$6)+Plantillas!$H$2:$H$114))) -> 0 | G79: =IF(G$5="",0,SUMPRODUCT((Plantillas!$A$2:$A$114=G$5)*(Plantillas!$D$2:$D$114=$A79)*(Plantillas!$G$2:$G$114*N(G$6)+Plantillas!$H$2:$H$114))) -> 0 | H79: =IF(H$5="",0,SUMPRODUCT((Plantillas!$A$2:$A$114=H$5)*(Plantillas!$D$2:$D$114=$A79)*(Plantillas!$G$2:$G$114*N(H$6)+Plantillas!$H$2:$H$114))) -> 0 | I79: =IF(I$5="",0,SUMPRODUCT((Plantillas!$A$2:$A$114=I$5)*(Plantillas!$D$2:$D$114=$A79)*(Plantillas!$G$2:$G$114*N(I$6)+Plantillas!$H$2:$H$114))) -> 0 | J79: =IF(J$5="",0,SUMPRODUCT((Plantillas!$A$2:$A$114=J$5)*(Plantillas!$D$2:$D$114=$A79)*(Plantillas!$G$2:$G$114*N(J$6)+Plantillas!$H$2:$H$114))) -> 0 | K79: =IF(K$5="",0,SUMPRODUCT((Plantillas!$A$2:$A$114=K$5)*(Plantillas!$D$2:$D$114=$A79)*(Plantillas!$G$2:$G$114*N(K$6)+Plantillas!$H$2:$H$114))) -> 0 | L79: =IF(L$5="",0,SUMPRODUCT((Plantillas!$A$2:$A$114=L$5)*(Plantillas!$D$2:$D$114=$A79)*(Plantillas!$G$2:$G$114*N(L$6)+Plantillas!$H$2:$H$114))) -> 0 | ... R79: =IF(R$5="",0,SUMPRODUCT((Plantillas!$A$2:$A$114=R$5)*(Plantillas!$D$2:$D$114=$A79)*(Plantillas!$G$2:$G$114*N(R$6)+Plantillas!$H$2:$H$114))) -> 0 | S79: =SUM(E79:R79) -> 2 | T79: =IF(INDEX(Partidas!$F$2:$F$99,MATCH(A79,Partidas!$A$2:$A$99,0))="","",INDEX(Partidas!$F$2:$F$99,MATCH(A79,Partidas!$A$2:$A$99,0))) -> 420 | U79: =IF(T79="",0,S79*T79) -> 840
A80: SAN-080 | B80: SAN | C80: =INDEX(Partidas!$D$2:$D$99,MATCH(A80,Partidas!$A$2:$A$99,0)) -> Mampara de bañera | D80: =INDEX(Partidas!$C$2:$C$99,MATCH(A80,Partidas!$A$2:$A$99,0)) -> ud | E80: =IF(E$5="",0,SUMPRODUCT((Plantillas!$A$2:$A$114=E$5)*(Plantillas!$D$2:$D$114=$A80)*(Plantillas!$G$2:$G$114*N(E$6)+Plantillas!$H$2:$H$114))) -> 0 | F80: =IF(F$5="",0,SUMPRODUCT((Plantillas!$A$2:$A$114=F$5)*(Plantillas!$D$2:$D$114=$A80)*(Plantillas!$G$2:$G$114*N(F$6)+Plantillas!$H$2:$H$114))) -> 0 | G80: =IF(G$5="",0,SUMPRODUCT((Plantillas!$A$2:$A$114=G$5)*(Plantillas!$D$2:$D$114=$A80)*(Plantillas!$G$2:$G$114*N(G$6)+Plantillas!$H$2:$H$114))) -> 0 | H80: =IF(H$5="",0,SUMPRODUCT((Plantillas!$A$2:$A$114=H$5)*(Plantillas!$D$2:$D$114=$A80)*(Plantillas!$G$2:$G$114*N(H$6)+Plantillas!$H$2:$H$114))) -> 0 | I80: =IF(I$5="",0,SUMPRODUCT((Plantillas!$A$2:$A$114=I$5)*(Plantillas!$D$2:$D$114=$A80)*(Plantillas!$G$2:$G$114*N(I$6)+Plantillas!$H$2:$H$114))) -> 0 | J80: =IF(J$5="",0,SUMPRODUCT((Plantillas!$A$2:$A$114=J$5)*(Plantillas!$D$2:$D$114=$A80)*(Plantillas!$G$2:$G$114*N(J$6)+Plantillas!$H$2:$H$114))) -> 0 | K80: =IF(K$5="",0,SUMPRODUCT((Plantillas!$A$2:$A$114=K$5)*(Plantillas!$D$2:$D$114=$A80)*(Plantillas!$G$2:$G$114*N(K$6)+Plantillas!$H$2:$H$114))) -> 0 | L80: =IF(L$5="",0,SUMPRODUCT((Plantillas!$A$2:$A$114=L$5)*(Plantillas!$D$2:$D$114=$A80)*(Plantillas!$G$2:$G$114*N(L$6)+Plantillas!$H$2:$H$114))) -> 0 | ... R80: =IF(R$5="",0,SUMPRODUCT((Plantillas!$A$2:$A$114=R$5)*(Plantillas!$D$2:$D$114=$A80)*(Plantillas!$G$2:$G$114*N(R$6)+Plantillas!$H$2:$H$114))) -> 0 | S80: =SUM(E80:R80) -> 0 | T80: =IF(INDEX(Partidas!$F$2:$F$99,MATCH(A80,Partidas!$A$2:$A$99,0))="","",INDEX(Partidas!$F$2:$F$99,MATCH(A80,Partidas!$A$2:$A$99,0))) -> 320 | U80: =IF(T80="",0,S80*T80) -> 0
A81: SAN-090 | B81: SAN | C81: =INDEX(Partidas!$D$2:$D$99,MATCH(A81,Partidas!$A$2:$A$99,0)) -> Espejo de baño a medida | D81: =INDEX(Partidas!$C$2:$C$99,MATCH(A81,Partidas!$A$2:$A$99,0)) -> m2 | E81: =IF(E$5="",0,SUMPRODUCT((Plantillas!$A$2:$A$114=E$5)*(Plantillas!$D$2:$D$114=$A81)*(Plantillas!$G$2:$G$114*N(E$6)+Plantillas!$H$2:$H$114))) -> 0 | F81: =IF(F$5="",0,SUMPRODUCT((Plantillas!$A$2:$A$114=F$5)*(Plantillas!$D$2:$D$114=$A81)*(Plantillas!$G$2:$G$114*N(F$6)+Plantillas!$H$2:$H$114))) -> 0 | G81: =IF(G$5="",0,SUMPRODUCT((Plantillas!$A$2:$A$114=G$5)*(Plantillas!$D$2:$D$114=$A81)*(Plantillas!$G$2:$G$114*N(G$6)+Plantillas!$H$2:$H$114))) -> 0 | H81: =IF(H$5="",0,SUMPRODUCT((Plantillas!$A$2:$A$114=H$5)*(Plantillas!$D$2:$D$114=$A81)*(Plantillas!$G$2:$G$114*N(H$6)+Plantillas!$H$2:$H$114))) -> 0 | I81: =IF(I$5="",0,SUMPRODUCT((Plantillas!$A$2:$A$114=I$5)*(Plantillas!$D$2:$D$114=$A81)*(Plantillas!$G$2:$G$114*N(I$6)+Plantillas!$H$2:$H$114))) -> 0 | J81: =IF(J$5="",0,SUMPRODUCT((Plantillas!$A$2:$A$114=J$5)*(Plantillas!$D$2:$D$114=$A81)*(Plantillas!$G$2:$G$114*N(J$6)+Plantillas!$H$2:$H$114))) -> 0 | K81: =IF(K$5="",0,SUMPRODUCT((Plantillas!$A$2:$A$114=K$5)*(Plantillas!$D$2:$D$114=$A81)*(Plantillas!$G$2:$G$114*N(K$6)+Plantillas!$H$2:$H$114))) -> 0 | L81: =IF(L$5="",0,SUMPRODUCT((Plantillas!$A$2:$A$114=L$5)*(Plantillas!$D$2:$D$114=$A81)*(Plantillas!$G$2:$G$114*N(L$6)+Plantillas!$H$2:$H$114))) -> 0 | ... R81: =IF(R$5="",0,SUMPRODUCT((Plantillas!$A$2:$A$114=R$5)*(Plantillas!$D$2:$D$114=$A81)*(Plantillas!$G$2:$G$114*N(R$6)+Plantillas!$H$2:$H$114))) -> 0 | S81: =SUM(E81:R81) -> 1.6 | T81: =IF(INDEX(Partidas!$F$2:$F$99,MATCH(A81,Partidas!$A$2:$A$99,0))="","",INDEX(Partidas!$F$2:$F$99,MATCH(A81,Partidas!$A$2:$A$99,0))) -> 70 | U81: =IF(T81="",0,S81*T81) -> 112
A82: SAN-100 | B82: SAN | C82: =INDEX(Partidas!$D$2:$D$99,MATCH(A82,Partidas!$A$2:$A$99,0)) -> Toallero eléctrico | D82: =INDEX(Partidas!$C$2:$C$99,MATCH(A82,Partidas!$A$2:$A$99,0)) -> ud | E82: =IF(E$5="",0,SUMPRODUCT((Plantillas!$A$2:$A$114=E$5)*(Plantillas!$D$2:$D$114=$A82)*(Plantillas!$G$2:$G$114*N(E$6)+Plantillas!$H$2:$H$114))) -> 0 | F82: =IF(F$5="",0,SUMPRODUCT((Plantillas!$A$2:$A$114=F$5)*(Plantillas!$D$2:$D$114=$A82)*(Plantillas!$G$2:$G$114*N(F$6)+Plantillas!$H$2:$H$114))) -> 0 | G82: =IF(G$5="",0,SUMPRODUCT((Plantillas!$A$2:$A$114=G$5)*(Plantillas!$D$2:$D$114=$A82)*(Plantillas!$G$2:$G$114*N(G$6)+Plantillas!$H$2:$H$114))) -> 0 | H82: =IF(H$5="",0,SUMPRODUCT((Plantillas!$A$2:$A$114=H$5)*(Plantillas!$D$2:$D$114=$A82)*(Plantillas!$G$2:$G$114*N(H$6)+Plantillas!$H$2:$H$114))) -> 0 | I82: =IF(I$5="",0,SUMPRODUCT((Plantillas!$A$2:$A$114=I$5)*(Plantillas!$D$2:$D$114=$A82)*(Plantillas!$G$2:$G$114*N(I$6)+Plantillas!$H$2:$H$114))) -> 0 | J82: =IF(J$5="",0,SUMPRODUCT((Plantillas!$A$2:$A$114=J$5)*(Plantillas!$D$2:$D$114=$A82)*(Plantillas!$G$2:$G$114*N(J$6)+Plantillas!$H$2:$H$114))) -> 0 | K82: =IF(K$5="",0,SUMPRODUCT((Plantillas!$A$2:$A$114=K$5)*(Plantillas!$D$2:$D$114=$A82)*(Plantillas!$G$2:$G$114*N(K$6)+Plantillas!$H$2:$H$114))) -> 0 | L82: =IF(L$5="",0,SUMPRODUCT((Plantillas!$A$2:$A$114=L$5)*(Plantillas!$D$2:$D$114=$A82)*(Plantillas!$G$2:$G$114*N(L$6)+Plantillas!$H$2:$H$114))) -> 0 | ... R82: =IF(R$5="",0,SUMPRODUCT((Plantillas!$A$2:$A$114=R$5)*(Plantillas!$D$2:$D$114=$A82)*(Plantillas!$G$2:$G$114*N(R$6)+Plantillas!$H$2:$H$114))) -> 0 | S82: =SUM(E82:R82) -> 2 | T82: =IF(INDEX(Partidas!$F$2:$F$99,MATCH(A82,Partidas!$A$2:$A$99,0))="","",INDEX(Partidas!$F$2:$F$99,MATCH(A82,Partidas!$A$2:$A$99,0))) -> 250 | U82: =IF(T82="",0,S82*T82) -> 500
A83: SAN-110 | B83: SAN | C83: =INDEX(Partidas!$D$2:$D$99,MATCH(A83,Partidas!$A$2:$A$99,0)) -> Toallero-radiador de agua | D83: =INDEX(Partidas!$C$2:$C$99,MATCH(A83,Partidas!$A$2:$A$99,0)) -> ud | E83: =IF(E$5="",0,SUMPRODUCT((Plantillas!$A$2:$A$114=E$5)*(Plantillas!$D$2:$D$114=$A83)*(Plantillas!$G$2:$G$114*N(E$6)+Plantillas!$H$2:$H$114))) -> 0 | F83: =IF(F$5="",0,SUMPRODUCT((Plantillas!$A$2:$A$114=F$5)*(Plantillas!$D$2:$D$114=$A83)*(Plantillas!$G$2:$G$114*N(F$6)+Plantillas!$H$2:$H$114))) -> 0 | G83: =IF(G$5="",0,SUMPRODUCT((Plantillas!$A$2:$A$114=G$5)*(Plantillas!$D$2:$D$114=$A83)*(Plantillas!$G$2:$G$114*N(G$6)+Plantillas!$H$2:$H$114))) -> 0 | H83: =IF(H$5="",0,SUMPRODUCT((Plantillas!$A$2:$A$114=H$5)*(Plantillas!$D$2:$D$114=$A83)*(Plantillas!$G$2:$G$114*N(H$6)+Plantillas!$H$2:$H$114))) -> 0 | I83: =IF(I$5="",0,SUMPRODUCT((Plantillas!$A$2:$A$114=I$5)*(Plantillas!$D$2:$D$114=$A83)*(Plantillas!$G$2:$G$114*N(I$6)+Plantillas!$H$2:$H$114))) -> 0 | J83: =IF(J$5="",0,SUMPRODUCT((Plantillas!$A$2:$A$114=J$5)*(Plantillas!$D$2:$D$114=$A83)*(Plantillas!$G$2:$G$114*N(J$6)+Plantillas!$H$2:$H$114))) -> 0 | K83: =IF(K$5="",0,SUMPRODUCT((Plantillas!$A$2:$A$114=K$5)*(Plantillas!$D$2:$D$114=$A83)*(Plantillas!$G$2:$G$114*N(K$6)+Plantillas!$H$2:$H$114))) -> 0 | L83: =IF(L$5="",0,SUMPRODUCT((Plantillas!$A$2:$A$114=L$5)*(Plantillas!$D$2:$D$114=$A83)*(Plantillas!$G$2:$G$114*N(L$6)+Plantillas!$H$2:$H$114))) -> 0 | ... R83: =IF(R$5="",0,SUMPRODUCT((Plantillas!$A$2:$A$114=R$5)*(Plantillas!$D$2:$D$114=$A83)*(Plantillas!$G$2:$G$114*N(R$6)+Plantillas!$H$2:$H$114))) -> 0 | S83: =SUM(E83:R83) -> 0 | T83: =IF(INDEX(Partidas!$F$2:$F$99,MATCH(A83,Partidas!$A$2:$A$99,0))="","",INDEX(Partidas!$F$2:$F$99,MATCH(A83,Partidas!$A$2:$A$99,0))) | U83: =IF(T83="",0,S83*T83) -> 0
A84: SAN-120 | B84: SAN | C84: =INDEX(Partidas!$D$2:$D$99,MATCH(A84,Partidas!$A$2:$A$99,0)) -> Juego de accesorios de baño | D84: =INDEX(Partidas!$C$2:$C$99,MATCH(A84,Partidas!$A$2:$A$99,0)) -> ud | E84: =IF(E$5="",0,SUMPRODUCT((Plantillas!$A$2:$A$114=E$5)*(Plantillas!$D$2:$D$114=$A84)*(Plantillas!$G$2:$G$114*N(E$6)+Plantillas!$H$2:$H$114))) -> 0 | F84: =IF(F$5="",0,SUMPRODUCT((Plantillas!$A$2:$A$114=F$5)*(Plantillas!$D$2:$D$114=$A84)*(Plantillas!$G$2:$G$114*N(F$6)+Plantillas!$H$2:$H$114))) -> 0 | G84: =IF(G$5="",0,SUMPRODUCT((Plantillas!$A$2:$A$114=G$5)*(Plantillas!$D$2:$D$114=$A84)*(Plantillas!$G$2:$G$114*N(G$6)+Plantillas!$H$2:$H$114))) -> 0 | H84: =IF(H$5="",0,SUMPRODUCT((Plantillas!$A$2:$A$114=H$5)*(Plantillas!$D$2:$D$114=$A84)*(Plantillas!$G$2:$G$114*N(H$6)+Plantillas!$H$2:$H$114))) -> 0 | I84: =IF(I$5="",0,SUMPRODUCT((Plantillas!$A$2:$A$114=I$5)*(Plantillas!$D$2:$D$114=$A84)*(Plantillas!$G$2:$G$114*N(I$6)+Plantillas!$H$2:$H$114))) -> 0 | J84: =IF(J$5="",0,SUMPRODUCT((Plantillas!$A$2:$A$114=J$5)*(Plantillas!$D$2:$D$114=$A84)*(Plantillas!$G$2:$G$114*N(J$6)+Plantillas!$H$2:$H$114))) -> 0 | K84: =IF(K$5="",0,SUMPRODUCT((Plantillas!$A$2:$A$114=K$5)*(Plantillas!$D$2:$D$114=$A84)*(Plantillas!$G$2:$G$114*N(K$6)+Plantillas!$H$2:$H$114))) -> 0 | L84: =IF(L$5="",0,SUMPRODUCT((Plantillas!$A$2:$A$114=L$5)*(Plantillas!$D$2:$D$114=$A84)*(Plantillas!$G$2:$G$114*N(L$6)+Plantillas!$H$2:$H$114))) -> 0 | ... R84: =IF(R$5="",0,SUMPRODUCT((Plantillas!$A$2:$A$114=R$5)*(Plantillas!$D$2:$D$114=$A84)*(Plantillas!$G$2:$G$114*N(R$6)+Plantillas!$H$2:$H$114))) -> 0 | S84: =SUM(E84:R84) -> 2 | T84: =IF(INDEX(Partidas!$F$2:$F$99,MATCH(A84,Partidas!$A$2:$A$99,0))="","",INDEX(Partidas!$F$2:$F$99,MATCH(A84,Partidas!$A$2:$A$99,0))) | U84: =IF(T84="",0,S84*T84) -> 0
A85: COC | C85: Cocina | U85: =SUM(U86:U88) -> 0
A86: COC-010 | B86: COC | C86: =INDEX(Partidas!$D$2:$D$99,MATCH(A86,Partidas!$A$2:$A$99,0)) -> Mobiliario de cocina con encimera | D86: =INDEX(Partidas!$C$2:$C$99,MATCH(A86,Partidas!$A$2:$A$99,0)) -> m | E86: =IF(E$5="",0,SUMPRODUCT((Plantillas!$A$2:$A$114=E$5)*(Plantillas!$D$2:$D$114=$A86)*(Plantillas!$G$2:$G$114*N(E$6)+Plantillas!$H$2:$H$114))) -> 0 | F86: =IF(F$5="",0,SUMPRODUCT((Plantillas!$A$2:$A$114=F$5)*(Plantillas!$D$2:$D$114=$A86)*(Plantillas!$G$2:$G$114*N(F$6)+Plantillas!$H$2:$H$114))) -> 0 | G86: =IF(G$5="",0,SUMPRODUCT((Plantillas!$A$2:$A$114=G$5)*(Plantillas!$D$2:$D$114=$A86)*(Plantillas!$G$2:$G$114*N(G$6)+Plantillas!$H$2:$H$114))) -> 0 | H86: =IF(H$5="",0,SUMPRODUCT((Plantillas!$A$2:$A$114=H$5)*(Plantillas!$D$2:$D$114=$A86)*(Plantillas!$G$2:$G$114*N(H$6)+Plantillas!$H$2:$H$114))) -> 0 | I86: =IF(I$5="",0,SUMPRODUCT((Plantillas!$A$2:$A$114=I$5)*(Plantillas!$D$2:$D$114=$A86)*(Plantillas!$G$2:$G$114*N(I$6)+Plantillas!$H$2:$H$114))) -> 0 | J86: =IF(J$5="",0,SUMPRODUCT((Plantillas!$A$2:$A$114=J$5)*(Plantillas!$D$2:$D$114=$A86)*(Plantillas!$G$2:$G$114*N(J$6)+Plantillas!$H$2:$H$114))) -> 0 | K86: =IF(K$5="",0,SUMPRODUCT((Plantillas!$A$2:$A$114=K$5)*(Plantillas!$D$2:$D$114=$A86)*(Plantillas!$G$2:$G$114*N(K$6)+Plantillas!$H$2:$H$114))) -> 0 | L86: =IF(L$5="",0,SUMPRODUCT((Plantillas!$A$2:$A$114=L$5)*(Plantillas!$D$2:$D$114=$A86)*(Plantillas!$G$2:$G$114*N(L$6)+Plantillas!$H$2:$H$114))) -> 0 | ... R86: =IF(R$5="",0,SUMPRODUCT((Plantillas!$A$2:$A$114=R$5)*(Plantillas!$D$2:$D$114=$A86)*(Plantillas!$G$2:$G$114*N(R$6)+Plantillas!$H$2:$H$114))) -> 0 | S86: =SUM(E86:R86) -> 0 | T86: =IF(INDEX(Partidas!$F$2:$F$99,MATCH(A86,Partidas!$A$2:$A$99,0))="","",INDEX(Partidas!$F$2:$F$99,MATCH(A86,Partidas!$A$2:$A$99,0))) | U86: =IF(T86="",0,S86*T86) -> 0
A87: COC-020 | B87: COC | C87: =INDEX(Partidas!$D$2:$D$99,MATCH(A87,Partidas!$A$2:$A$99,0)) -> Montaje de cocina suministrada por la propiedad | D87: =INDEX(Partidas!$C$2:$C$99,MATCH(A87,Partidas!$A$2:$A$99,0)) -> pa | E87: =IF(E$5="",0,SUMPRODUCT((Plantillas!$A$2:$A$114=E$5)*(Plantillas!$D$2:$D$114=$A87)*(Plantillas!$G$2:$G$114*N(E$6)+Plantillas!$H$2:$H$114))) -> 0 | F87: =IF(F$5="",0,SUMPRODUCT((Plantillas!$A$2:$A$114=F$5)*(Plantillas!$D$2:$D$114=$A87)*(Plantillas!$G$2:$G$114*N(F$6)+Plantillas!$H$2:$H$114))) -> 0 | G87: =IF(G$5="",0,SUMPRODUCT((Plantillas!$A$2:$A$114=G$5)*(Plantillas!$D$2:$D$114=$A87)*(Plantillas!$G$2:$G$114*N(G$6)+Plantillas!$H$2:$H$114))) -> 0 | H87: =IF(H$5="",0,SUMPRODUCT((Plantillas!$A$2:$A$114=H$5)*(Plantillas!$D$2:$D$114=$A87)*(Plantillas!$G$2:$G$114*N(H$6)+Plantillas!$H$2:$H$114))) -> 0 | I87: =IF(I$5="",0,SUMPRODUCT((Plantillas!$A$2:$A$114=I$5)*(Plantillas!$D$2:$D$114=$A87)*(Plantillas!$G$2:$G$114*N(I$6)+Plantillas!$H$2:$H$114))) -> 0 | J87: =IF(J$5="",0,SUMPRODUCT((Plantillas!$A$2:$A$114=J$5)*(Plantillas!$D$2:$D$114=$A87)*(Plantillas!$G$2:$G$114*N(J$6)+Plantillas!$H$2:$H$114))) -> 0 | K87: =IF(K$5="",0,SUMPRODUCT((Plantillas!$A$2:$A$114=K$5)*(Plantillas!$D$2:$D$114=$A87)*(Plantillas!$G$2:$G$114*N(K$6)+Plantillas!$H$2:$H$114))) -> 0 | L87: =IF(L$5="",0,SUMPRODUCT((Plantillas!$A$2:$A$114=L$5)*(Plantillas!$D$2:$D$114=$A87)*(Plantillas!$G$2:$G$114*N(L$6)+Plantillas!$H$2:$H$114))) -> 0 | ... R87: =IF(R$5="",0,SUMPRODUCT((Plantillas!$A$2:$A$114=R$5)*(Plantillas!$D$2:$D$114=$A87)*(Plantillas!$G$2:$G$114*N(R$6)+Plantillas!$H$2:$H$114))) -> 0 | S87: =SUM(E87:R87) -> 0 | T87: =IF(INDEX(Partidas!$F$2:$F$99,MATCH(A87,Partidas!$A$2:$A$99,0))="","",INDEX(Partidas!$F$2:$F$99,MATCH(A87,Partidas!$A$2:$A$99,0))) | U87: =IF(T87="",0,S87*T87) -> 0
A88: COC-030 | B88: COC | C88: =INDEX(Partidas!$D$2:$D$99,MATCH(A88,Partidas!$A$2:$A$99,0)) -> Conexión de electrodomésticos y fregadero | D88: =INDEX(Partidas!$C$2:$C$99,MATCH(A88,Partidas!$A$2:$A$99,0)) -> pa | E88: =IF(E$5="",0,SUMPRODUCT((Plantillas!$A$2:$A$114=E$5)*(Plantillas!$D$2:$D$114=$A88)*(Plantillas!$G$2:$G$114*N(E$6)+Plantillas!$H$2:$H$114))) -> 0 | F88: =IF(F$5="",0,SUMPRODUCT((Plantillas!$A$2:$A$114=F$5)*(Plantillas!$D$2:$D$114=$A88)*(Plantillas!$G$2:$G$114*N(F$6)+Plantillas!$H$2:$H$114))) -> 0 | G88: =IF(G$5="",0,SUMPRODUCT((Plantillas!$A$2:$A$114=G$5)*(Plantillas!$D$2:$D$114=$A88)*(Plantillas!$G$2:$G$114*N(G$6)+Plantillas!$H$2:$H$114))) -> 0 | H88: =IF(H$5="",0,SUMPRODUCT((Plantillas!$A$2:$A$114=H$5)*(Plantillas!$D$2:$D$114=$A88)*(Plantillas!$G$2:$G$114*N(H$6)+Plantillas!$H$2:$H$114))) -> 0 | I88: =IF(I$5="",0,SUMPRODUCT((Plantillas!$A$2:$A$114=I$5)*(Plantillas!$D$2:$D$114=$A88)*(Plantillas!$G$2:$G$114*N(I$6)+Plantillas!$H$2:$H$114))) -> 0 | J88: =IF(J$5="",0,SUMPRODUCT((Plantillas!$A$2:$A$114=J$5)*(Plantillas!$D$2:$D$114=$A88)*(Plantillas!$G$2:$G$114*N(J$6)+Plantillas!$H$2:$H$114))) -> 0 | K88: =IF(K$5="",0,SUMPRODUCT((Plantillas!$A$2:$A$114=K$5)*(Plantillas!$D$2:$D$114=$A88)*(Plantillas!$G$2:$G$114*N(K$6)+Plantillas!$H$2:$H$114))) -> 0 | L88: =IF(L$5="",0,SUMPRODUCT((Plantillas!$A$2:$A$114=L$5)*(Plantillas!$D$2:$D$114=$A88)*(Plantillas!$G$2:$G$114*N(L$6)+Plantillas!$H$2:$H$114))) -> 1 | ... R88: =IF(R$5="",0,SUMPRODUCT((Plantillas!$A$2:$A$114=R$5)*(Plantillas!$D$2:$D$114=$A88)*(Plantillas!$G$2:$G$114*N(R$6)+Plantillas!$H$2:$H$114))) -> 0 | S88: =SUM(E88:R88) -> 1 | T88: =IF(INDEX(Partidas!$F$2:$F$99,MATCH(A88,Partidas!$A$2:$A$99,0))="","",INDEX(Partidas!$F$2:$F$99,MATCH(A88,Partidas!$A$2:$A$99,0))) | U88: =IF(T88="",0,S88*T88) -> 0
A89: ELE | C89: Electricidad y telecomunicaciones | U89: =SUM(U90:U102) -> 6035
A90: ELE-010 | B90: ELE | C90: =INDEX(Partidas!$D$2:$D$99,MATCH(A90,Partidas!$A$2:$A$99,0)) -> Instalación eléctrica: cuadro, circuitos y boletín | D90: =INDEX(Partidas!$C$2:$C$99,MATCH(A90,Partidas!$A$2:$A$99,0)) -> pa | E90: =IF(E$5="",0,SUMPRODUCT((Plantillas!$A$2:$A$114=E$5)*(Plantillas!$D$2:$D$114=$A90)*(Plantillas!$G$2:$G$114*N(E$6)+Plantillas!$H$2:$H$114))) -> 1 | F90: =IF(F$5="",0,SUMPRODUCT((Plantillas!$A$2:$A$114=F$5)*(Plantillas!$D$2:$D$114=$A90)*(Plantillas!$G$2:$G$114*N(F$6)+Plantillas!$H$2:$H$114))) -> 0 | G90: =IF(G$5="",0,SUMPRODUCT((Plantillas!$A$2:$A$114=G$5)*(Plantillas!$D$2:$D$114=$A90)*(Plantillas!$G$2:$G$114*N(G$6)+Plantillas!$H$2:$H$114))) -> 0 | H90: =IF(H$5="",0,SUMPRODUCT((Plantillas!$A$2:$A$114=H$5)*(Plantillas!$D$2:$D$114=$A90)*(Plantillas!$G$2:$G$114*N(H$6)+Plantillas!$H$2:$H$114))) -> 0 | I90: =IF(I$5="",0,SUMPRODUCT((Plantillas!$A$2:$A$114=I$5)*(Plantillas!$D$2:$D$114=$A90)*(Plantillas!$G$2:$G$114*N(I$6)+Plantillas!$H$2:$H$114))) -> 0 | J90: =IF(J$5="",0,SUMPRODUCT((Plantillas!$A$2:$A$114=J$5)*(Plantillas!$D$2:$D$114=$A90)*(Plantillas!$G$2:$G$114*N(J$6)+Plantillas!$H$2:$H$114))) -> 0 | K90: =IF(K$5="",0,SUMPRODUCT((Plantillas!$A$2:$A$114=K$5)*(Plantillas!$D$2:$D$114=$A90)*(Plantillas!$G$2:$G$114*N(K$6)+Plantillas!$H$2:$H$114))) -> 0 | L90: =IF(L$5="",0,SUMPRODUCT((Plantillas!$A$2:$A$114=L$5)*(Plantillas!$D$2:$D$114=$A90)*(Plantillas!$G$2:$G$114*N(L$6)+Plantillas!$H$2:$H$114))) -> 0 | ... R90: =IF(R$5="",0,SUMPRODUCT((Plantillas!$A$2:$A$114=R$5)*(Plantillas!$D$2:$D$114=$A90)*(Plantillas!$G$2:$G$114*N(R$6)+Plantillas!$H$2:$H$114))) -> 0 | S90: =SUM(E90:R90) -> 1 | T90: =IF(INDEX(Partidas!$F$2:$F$99,MATCH(A90,Partidas!$A$2:$A$99,0))="","",INDEX(Partidas!$F$2:$F$99,MATCH(A90,Partidas!$A$2:$A$99,0))) -> 2850 | U90: =IF(T90="",0,S90*T90) -> 2850
A91: ELE-020 | B91: ELE | C91: =INDEX(Partidas!$D$2:$D$99,MATCH(A91,Partidas!$A$2:$A$99,0)) -> Punto de luz sencillo | D91: =INDEX(Partidas!$C$2:$C$99,MATCH(A91,Partidas!$A$2:$A$99,0)) -> ud | E91: =IF(E$5="",0,SUMPRODUCT((Plantillas!$A$2:$A$114=E$5)*(Plantillas!$D$2:$D$114=$A91)*(Plantillas!$G$2:$G$114*N(E$6)+Plantillas!$H$2:$H$114))) -> 0 | F91: =IF(F$5="",0,SUMPRODUCT((Plantillas!$A$2:$A$114=F$5)*(Plantillas!$D$2:$D$114=$A91)*(Plantillas!$G$2:$G$114*N(F$6)+Plantillas!$H$2:$H$114))) -> 0 | G91: =IF(G$5="",0,SUMPRODUCT((Plantillas!$A$2:$A$114=G$5)*(Plantillas!$D$2:$D$114=$A91)*(Plantillas!$G$2:$G$114*N(G$6)+Plantillas!$H$2:$H$114))) -> 1 | H91: =IF(H$5="",0,SUMPRODUCT((Plantillas!$A$2:$A$114=H$5)*(Plantillas!$D$2:$D$114=$A91)*(Plantillas!$G$2:$G$114*N(H$6)+Plantillas!$H$2:$H$114))) -> 1 | I91: =IF(I$5="",0,SUMPRODUCT((Plantillas!$A$2:$A$114=I$5)*(Plantillas!$D$2:$D$114=$A91)*(Plantillas!$G$2:$G$114*N(I$6)+Plantillas!$H$2:$H$114))) -> 1 | J91: =IF(J$5="",0,SUMPRODUCT((Plantillas!$A$2:$A$114=J$5)*(Plantillas!$D$2:$D$114=$A91)*(Plantillas!$G$2:$G$114*N(J$6)+Plantillas!$H$2:$H$114))) -> 0 | K91: =IF(K$5="",0,SUMPRODUCT((Plantillas!$A$2:$A$114=K$5)*(Plantillas!$D$2:$D$114=$A91)*(Plantillas!$G$2:$G$114*N(K$6)+Plantillas!$H$2:$H$114))) -> 0 | L91: =IF(L$5="",0,SUMPRODUCT((Plantillas!$A$2:$A$114=L$5)*(Plantillas!$D$2:$D$114=$A91)*(Plantillas!$G$2:$G$114*N(L$6)+Plantillas!$H$2:$H$114))) -> 0 | ... R91: =IF(R$5="",0,SUMPRODUCT((Plantillas!$A$2:$A$114=R$5)*(Plantillas!$D$2:$D$114=$A91)*(Plantillas!$G$2:$G$114*N(R$6)+Plantillas!$H$2:$H$114))) -> 0 | S91: =SUM(E91:R91) -> 6 | T91: =IF(INDEX(Partidas!$F$2:$F$99,MATCH(A91,Partidas!$A$2:$A$99,0))="","",INDEX(Partidas!$F$2:$F$99,MATCH(A91,Partidas!$A$2:$A$99,0))) -> 50 | U91: =IF(T91="",0,S91*T91) -> 300
A92: ELE-030 | B92: ELE | C92: =INDEX(Partidas!$D$2:$D$99,MATCH(A92,Partidas!$A$2:$A$99,0)) -> Punto de luz adicional en el mismo circuito | D92: =INDEX(Partidas!$C$2:$C$99,MATCH(A92,Partidas!$A$2:$A$99,0)) -> ud | E92: =IF(E$5="",0,SUMPRODUCT((Plantillas!$A$2:$A$114=E$5)*(Plantillas!$D$2:$D$114=$A92)*(Plantillas!$G$2:$G$114*N(E$6)+Plantillas!$H$2:$H$114))) -> 0 | F92: =IF(F$5="",0,SUMPRODUCT((Plantillas!$A$2:$A$114=F$5)*(Plantillas!$D$2:$D$114=$A92)*(Plantillas!$G$2:$G$114*N(F$6)+Plantillas!$H$2:$H$114))) -> 4 | G92: =IF(G$5="",0,SUMPRODUCT((Plantillas!$A$2:$A$114=G$5)*(Plantillas!$D$2:$D$114=$A92)*(Plantillas!$G$2:$G$114*N(G$6)+Plantillas!$H$2:$H$114))) -> 1 | H92: =IF(H$5="",0,SUMPRODUCT((Plantillas!$A$2:$A$114=H$5)*(Plantillas!$D$2:$D$114=$A92)*(Plantillas!$G$2:$G$114*N(H$6)+Plantillas!$H$2:$H$114))) -> 1 | I92: =IF(I$5="",0,SUMPRODUCT((Plantillas!$A$2:$A$114=I$5)*(Plantillas!$D$2:$D$114=$A92)*(Plantillas!$G$2:$G$114*N(I$6)+Plantillas!$H$2:$H$114))) -> 1 | J92: =IF(J$5="",0,SUMPRODUCT((Plantillas!$A$2:$A$114=J$5)*(Plantillas!$D$2:$D$114=$A92)*(Plantillas!$G$2:$G$114*N(J$6)+Plantillas!$H$2:$H$114))) -> 1 | K92: =IF(K$5="",0,SUMPRODUCT((Plantillas!$A$2:$A$114=K$5)*(Plantillas!$D$2:$D$114=$A92)*(Plantillas!$G$2:$G$114*N(K$6)+Plantillas!$H$2:$H$114))) -> 1 | L92: =IF(L$5="",0,SUMPRODUCT((Plantillas!$A$2:$A$114=L$5)*(Plantillas!$D$2:$D$114=$A92)*(Plantillas!$G$2:$G$114*N(L$6)+Plantillas!$H$2:$H$114))) -> 2 | ... R92: =IF(R$5="",0,SUMPRODUCT((Plantillas!$A$2:$A$114=R$5)*(Plantillas!$D$2:$D$114=$A92)*(Plantillas!$G$2:$G$114*N(R$6)+Plantillas!$H$2:$H$114))) -> 0 | S92: =SUM(E92:R92) -> 13 | T92: =IF(INDEX(Partidas!$F$2:$F$99,MATCH(A92,Partidas!$A$2:$A$99,0))="","",INDEX(Partidas!$F$2:$F$99,MATCH(A92,Partidas!$A$2:$A$99,0))) -> 10 | U92: =IF(T92="",0,S92*T92) -> 130
A93: ELE-040 | B93: ELE | C93: =INDEX(Partidas!$D$2:$D$99,MATCH(A93,Partidas!$A$2:$A$99,0)) -> Punto de luz conmutado | D93: =INDEX(Partidas!$C$2:$C$99,MATCH(A93,Partidas!$A$2:$A$99,0)) -> ud | E93: =IF(E$5="",0,SUMPRODUCT((Plantillas!$A$2:$A$114=E$5)*(Plantillas!$D$2:$D$114=$A93)*(Plantillas!$G$2:$G$114*N(E$6)+Plantillas!$H$2:$H$114))) -> 0 | F93: =IF(F$5="",0,SUMPRODUCT((Plantillas!$A$2:$A$114=F$5)*(Plantillas!$D$2:$D$114=$A93)*(Plantillas!$G$2:$G$114*N(F$6)+Plantillas!$H$2:$H$114))) -> 2 | G93: =IF(G$5="",0,SUMPRODUCT((Plantillas!$A$2:$A$114=G$5)*(Plantillas!$D$2:$D$114=$A93)*(Plantillas!$G$2:$G$114*N(G$6)+Plantillas!$H$2:$H$114))) -> 1 | H93: =IF(H$5="",0,SUMPRODUCT((Plantillas!$A$2:$A$114=H$5)*(Plantillas!$D$2:$D$114=$A93)*(Plantillas!$G$2:$G$114*N(H$6)+Plantillas!$H$2:$H$114))) -> 1 | I93: =IF(I$5="",0,SUMPRODUCT((Plantillas!$A$2:$A$114=I$5)*(Plantillas!$D$2:$D$114=$A93)*(Plantillas!$G$2:$G$114*N(I$6)+Plantillas!$H$2:$H$114))) -> 1 | J93: =IF(J$5="",0,SUMPRODUCT((Plantillas!$A$2:$A$114=J$5)*(Plantillas!$D$2:$D$114=$A93)*(Plantillas!$G$2:$G$114*N(J$6)+Plantillas!$H$2:$H$114))) -> 1 | K93: =IF(K$5="",0,SUMPRODUCT((Plantillas!$A$2:$A$114=K$5)*(Plantillas!$D$2:$D$114=$A93)*(Plantillas!$G$2:$G$114*N(K$6)+Plantillas!$H$2:$H$114))) -> 1 | L93: =IF(L$5="",0,SUMPRODUCT((Plantillas!$A$2:$A$114=L$5)*(Plantillas!$D$2:$D$114=$A93)*(Plantillas!$G$2:$G$114*N(L$6)+Plantillas!$H$2:$H$114))) -> 1 | ... R93: =IF(R$5="",0,SUMPRODUCT((Plantillas!$A$2:$A$114=R$5)*(Plantillas!$D$2:$D$114=$A93)*(Plantillas!$G$2:$G$114*N(R$6)+Plantillas!$H$2:$H$114))) -> 0 | S93: =SUM(E93:R93) -> 8 | T93: =IF(INDEX(Partidas!$F$2:$F$99,MATCH(A93,Partidas!$A$2:$A$99,0))="","",INDEX(Partidas!$F$2:$F$99,MATCH(A93,Partidas!$A$2:$A$99,0))) -> 85 | U93: =IF(T93="",0,S93*T93) -> 680
A94: ELE-050 | B94: ELE | C94: =INDEX(Partidas!$D$2:$D$99,MATCH(A94,Partidas!$A$2:$A$99,0)) -> Punto de luz de cruce | D94: =INDEX(Partidas!$C$2:$C$99,MATCH(A94,Partidas!$A$2:$A$99,0)) -> ud | E94: =IF(E$5="",0,SUMPRODUCT((Plantillas!$A$2:$A$114=E$5)*(Plantillas!$D$2:$D$114=$A94)*(Plantillas!$G$2:$G$114*N(E$6)+Plantillas!$H$2:$H$114))) -> 0 | F94: =IF(F$5="",0,SUMPRODUCT((Plantillas!$A$2:$A$114=F$5)*(Plantillas!$D$2:$D$114=$A94)*(Plantillas!$G$2:$G$114*N(F$6)+Plantillas!$H$2:$H$114))) -> 1 | G94: =IF(G$5="",0,SUMPRODUCT((Plantillas!$A$2:$A$114=G$5)*(Plantillas!$D$2:$D$114=$A94)*(Plantillas!$G$2:$G$114*N(G$6)+Plantillas!$H$2:$H$114))) -> 0 | H94: =IF(H$5="",0,SUMPRODUCT((Plantillas!$A$2:$A$114=H$5)*(Plantillas!$D$2:$D$114=$A94)*(Plantillas!$G$2:$G$114*N(H$6)+Plantillas!$H$2:$H$114))) -> 0 | I94: =IF(I$5="",0,SUMPRODUCT((Plantillas!$A$2:$A$114=I$5)*(Plantillas!$D$2:$D$114=$A94)*(Plantillas!$G$2:$G$114*N(I$6)+Plantillas!$H$2:$H$114))) -> 0 | J94: =IF(J$5="",0,SUMPRODUCT((Plantillas!$A$2:$A$114=J$5)*(Plantillas!$D$2:$D$114=$A94)*(Plantillas!$G$2:$G$114*N(J$6)+Plantillas!$H$2:$H$114))) -> 0 | K94: =IF(K$5="",0,SUMPRODUCT((Plantillas!$A$2:$A$114=K$5)*(Plantillas!$D$2:$D$114=$A94)*(Plantillas!$G$2:$G$114*N(K$6)+Plantillas!$H$2:$H$114))) -> 0 | L94: =IF(L$5="",0,SUMPRODUCT((Plantillas!$A$2:$A$114=L$5)*(Plantillas!$D$2:$D$114=$A94)*(Plantillas!$G$2:$G$114*N(L$6)+Plantillas!$H$2:$H$114))) -> 0 | ... R94: =IF(R$5="",0,SUMPRODUCT((Plantillas!$A$2:$A$114=R$5)*(Plantillas!$D$2:$D$114=$A94)*(Plantillas!$G$2:$G$114*N(R$6)+Plantillas!$H$2:$H$114))) -> 0 | S94: =SUM(E94:R94) -> 1 | T94: =IF(INDEX(Partidas!$F$2:$F$99,MATCH(A94,Partidas!$A$2:$A$99,0))="","",INDEX(Partidas!$F$2:$F$99,MATCH(A94,Partidas!$A$2:$A$99,0))) -> 120 | U94: =IF(T94="",0,S94*T94) -> 120
A95: ELE-060 | B95: ELE | C95: =INDEX(Partidas!$D$2:$D$99,MATCH(A95,Partidas!$A$2:$A$99,0)) -> Toma de corriente | D95: =INDEX(Partidas!$C$2:$C$99,MATCH(A95,Partidas!$A$2:$A$99,0)) -> ud | E95: =IF(E$5="",0,SUMPRODUCT((Plantillas!$A$2:$A$114=E$5)*(Plantillas!$D$2:$D$114=$A95)*(Plantillas!$G$2:$G$114*N(E$6)+Plantillas!$H$2:$H$114))) -> 0 | F95: =IF(F$5="",0,SUMPRODUCT((Plantillas!$A$2:$A$114=F$5)*(Plantillas!$D$2:$D$114=$A95)*(Plantillas!$G$2:$G$114*N(F$6)+Plantillas!$H$2:$H$114))) -> 8 | G95: =IF(G$5="",0,SUMPRODUCT((Plantillas!$A$2:$A$114=G$5)*(Plantillas!$D$2:$D$114=$A95)*(Plantillas!$G$2:$G$114*N(G$6)+Plantillas!$H$2:$H$114))) -> 4 | H95: =IF(H$5="",0,SUMPRODUCT((Plantillas!$A$2:$A$114=H$5)*(Plantillas!$D$2:$D$114=$A95)*(Plantillas!$G$2:$G$114*N(H$6)+Plantillas!$H$2:$H$114))) -> 4 | I95: =IF(I$5="",0,SUMPRODUCT((Plantillas!$A$2:$A$114=I$5)*(Plantillas!$D$2:$D$114=$A95)*(Plantillas!$G$2:$G$114*N(I$6)+Plantillas!$H$2:$H$114))) -> 4 | J95: =IF(J$5="",0,SUMPRODUCT((Plantillas!$A$2:$A$114=J$5)*(Plantillas!$D$2:$D$114=$A95)*(Plantillas!$G$2:$G$114*N(J$6)+Plantillas!$H$2:$H$114))) -> 2 | K95: =IF(K$5="",0,SUMPRODUCT((Plantillas!$A$2:$A$114=K$5)*(Plantillas!$D$2:$D$114=$A95)*(Plantillas!$G$2:$G$114*N(K$6)+Plantillas!$H$2:$H$114))) -> 2 | L95: =IF(L$5="",0,SUMPRODUCT((Plantillas!$A$2:$A$114=L$5)*(Plantillas!$D$2:$D$114=$A95)*(Plantillas!$G$2:$G$114*N(L$6)+Plantillas!$H$2:$H$114))) -> 4 | ... R95: =IF(R$5="",0,SUMPRODUCT((Plantillas!$A$2:$A$114=R$5)*(Plantillas!$D$2:$D$114=$A95)*(Plantillas!$G$2:$G$114*N(R$6)+Plantillas!$H$2:$H$114))) -> 0 | S95: =SUM(E95:R95) -> 33 | T95: =IF(INDEX(Partidas!$F$2:$F$99,MATCH(A95,Partidas!$A$2:$A$99,0))="","",INDEX(Partidas!$F$2:$F$99,MATCH(A95,Partidas!$A$2:$A$99,0))) -> 45 | U95: =IF(T95="",0,S95*T95) -> 1485
A96: ELE-070 | B96: ELE | C96: =INDEX(Partidas!$D$2:$D$99,MATCH(A96,Partidas!$A$2:$A$99,0)) -> Toma de corriente con cargador USB-C | D96: =INDEX(Partidas!$C$2:$C$99,MATCH(A96,Partidas!$A$2:$A$99,0)) -> ud | E96: =IF(E$5="",0,SUMPRODUCT((Plantillas!$A$2:$A$114=E$5)*(Plantillas!$D$2:$D$114=$A96)*(Plantillas!$G$2:$G$114*N(E$6)+Plantillas!$H$2:$H$114))) -> 0 | F96: =IF(F$5="",0,SUMPRODUCT((Plantillas!$A$2:$A$114=F$5)*(Plantillas!$D$2:$D$114=$A96)*(Plantillas!$G$2:$G$114*N(F$6)+Plantillas!$H$2:$H$114))) -> 0 | G96: =IF(G$5="",0,SUMPRODUCT((Plantillas!$A$2:$A$114=G$5)*(Plantillas!$D$2:$D$114=$A96)*(Plantillas!$G$2:$G$114*N(G$6)+Plantillas!$H$2:$H$114))) -> 0 | H96: =IF(H$5="",0,SUMPRODUCT((Plantillas!$A$2:$A$114=H$5)*(Plantillas!$D$2:$D$114=$A96)*(Plantillas!$G$2:$G$114*N(H$6)+Plantillas!$H$2:$H$114))) -> 0 | I96: =IF(I$5="",0,SUMPRODUCT((Plantillas!$A$2:$A$114=I$5)*(Plantillas!$D$2:$D$114=$A96)*(Plantillas!$G$2:$G$114*N(I$6)+Plantillas!$H$2:$H$114))) -> 0 | J96: =IF(J$5="",0,SUMPRODUCT((Plantillas!$A$2:$A$114=J$5)*(Plantillas!$D$2:$D$114=$A96)*(Plantillas!$G$2:$G$114*N(J$6)+Plantillas!$H$2:$H$114))) -> 0 | K96: =IF(K$5="",0,SUMPRODUCT((Plantillas!$A$2:$A$114=K$5)*(Plantillas!$D$2:$D$114=$A96)*(Plantillas!$G$2:$G$114*N(K$6)+Plantillas!$H$2:$H$114))) -> 0 | L96: =IF(L$5="",0,SUMPRODUCT((Plantillas!$A$2:$A$114=L$5)*(Plantillas!$D$2:$D$114=$A96)*(Plantillas!$G$2:$G$114*N(L$6)+Plantillas!$H$2:$H$114))) -> 0 | ... R96: =IF(R$5="",0,SUMPRODUCT((Plantillas!$A$2:$A$114=R$5)*(Plantillas!$D$2:$D$114=$A96)*(Plantillas!$G$2:$G$114*N(R$6)+Plantillas!$H$2:$H$114))) -> 0 | S96: =SUM(E96:R96) -> 0 | T96: =IF(INDEX(Partidas!$F$2:$F$99,MATCH(A96,Partidas!$A$2:$A$99,0))="","",INDEX(Partidas!$F$2:$F$99,MATCH(A96,Partidas!$A$2:$A$99,0))) -> 90 | U96: =IF(T96="",0,S96*T96) -> 0
A97: ELE-080 | B97: ELE | C97: =INDEX(Partidas!$D$2:$D$99,MATCH(A97,Partidas!$A$2:$A$99,0)) -> Toma de TV o datos | D97: =INDEX(Partidas!$C$2:$C$99,MATCH(A97,Partidas!$A$2:$A$99,0)) -> ud | E97: =IF(E$5="",0,SUMPRODUCT((Plantillas!$A$2:$A$114=E$5)*(Plantillas!$D$2:$D$114=$A97)*(Plantillas!$G$2:$G$114*N(E$6)+Plantillas!$H$2:$H$114))) -> 0 | F97: =IF(F$5="",0,SUMPRODUCT((Plantillas!$A$2:$A$114=F$5)*(Plantillas!$D$2:$D$114=$A97)*(Plantillas!$G$2:$G$114*N(F$6)+Plantillas!$H$2:$H$114))) -> 2 | G97: =IF(G$5="",0,SUMPRODUCT((Plantillas!$A$2:$A$114=G$5)*(Plantillas!$D$2:$D$114=$A97)*(Plantillas!$G$2:$G$114*N(G$6)+Plantillas!$H$2:$H$114))) -> 0 | H97: =IF(H$5="",0,SUMPRODUCT((Plantillas!$A$2:$A$114=H$5)*(Plantillas!$D$2:$D$114=$A97)*(Plantillas!$G$2:$G$114*N(H$6)+Plantillas!$H$2:$H$114))) -> 0 | I97: =IF(I$5="",0,SUMPRODUCT((Plantillas!$A$2:$A$114=I$5)*(Plantillas!$D$2:$D$114=$A97)*(Plantillas!$G$2:$G$114*N(I$6)+Plantillas!$H$2:$H$114))) -> 0 | J97: =IF(J$5="",0,SUMPRODUCT((Plantillas!$A$2:$A$114=J$5)*(Plantillas!$D$2:$D$114=$A97)*(Plantillas!$G$2:$G$114*N(J$6)+Plantillas!$H$2:$H$114))) -> 0 | K97: =IF(K$5="",0,SUMPRODUCT((Plantillas!$A$2:$A$114=K$5)*(Plantillas!$D$2:$D$114=$A97)*(Plantillas!$G$2:$G$114*N(K$6)+Plantillas!$H$2:$H$114))) -> 0 | L97: =IF(L$5="",0,SUMPRODUCT((Plantillas!$A$2:$A$114=L$5)*(Plantillas!$D$2:$D$114=$A97)*(Plantillas!$G$2:$G$114*N(L$6)+Plantillas!$H$2:$H$114))) -> 0 | ... R97: =IF(R$5="",0,SUMPRODUCT((Plantillas!$A$2:$A$114=R$5)*(Plantillas!$D$2:$D$114=$A97)*(Plantillas!$G$2:$G$114*N(R$6)+Plantillas!$H$2:$H$114))) -> 0 | S97: =SUM(E97:R97) -> 2 | T97: =IF(INDEX(Partidas!$F$2:$F$99,MATCH(A97,Partidas!$A$2:$A$99,0))="","",INDEX(Partidas!$F$2:$F$99,MATCH(A97,Partidas!$A$2:$A$99,0))) -> 45 | U97: =IF(T97="",0,S97*T97) -> 90
A98: ELE-090 | B98: ELE | C98: =INDEX(Partidas!$D$2:$D$99,MATCH(A98,Partidas!$A$2:$A$99,0)) -> Toma para electrodoméstico | D98: =INDEX(Partidas!$C$2:$C$99,MATCH(A98,Partidas!$A$2:$A$99,0)) -> ud | E98: =IF(E$5="",0,SUMPRODUCT((Plantillas!$A$2:$A$114=E$5)*(Plantillas!$D$2:$D$114=$A98)*(Plantillas!$G$2:$G$114*N(E$6)+Plantillas!$H$2:$H$114))) -> 0 | F98: =IF(F$5="",0,SUMPRODUCT((Plantillas!$A$2:$A$114=F$5)*(Plantillas!$D$2:$D$114=$A98)*(Plantillas!$G$2:$G$114*N(F$6)+Plantillas!$H$2:$H$114))) -> 0 | G98: =IF(G$5="",0,SUMPRODUCT((Plantillas!$A$2:$A$114=G$5)*(Plantillas!$D$2:$D$114=$A98)*(Plantillas!$G$2:$G$114*N(G$6)+Plantillas!$H$2:$H$114))) -> 0 | H98: =IF(H$5="",0,SUMPRODUCT((Plantillas!$A$2:$A$114=H$5)*(Plantillas!$D$2:$D$114=$A98)*(Plantillas!$G$2:$G$114*N(H$6)+Plantillas!$H$2:$H$114))) -> 0 | I98: =IF(I$5="",0,SUMPRODUCT((Plantillas!$A$2:$A$114=I$5)*(Plantillas!$D$2:$D$114=$A98)*(Plantillas!$G$2:$G$114*N(I$6)+Plantillas!$H$2:$H$114))) -> 0 | J98: =IF(J$5="",0,SUMPRODUCT((Plantillas!$A$2:$A$114=J$5)*(Plantillas!$D$2:$D$114=$A98)*(Plantillas!$G$2:$G$114*N(J$6)+Plantillas!$H$2:$H$114))) -> 0 | K98: =IF(K$5="",0,SUMPRODUCT((Plantillas!$A$2:$A$114=K$5)*(Plantillas!$D$2:$D$114=$A98)*(Plantillas!$G$2:$G$114*N(K$6)+Plantillas!$H$2:$H$114))) -> 0 | L98: =IF(L$5="",0,SUMPRODUCT((Plantillas!$A$2:$A$114=L$5)*(Plantillas!$D$2:$D$114=$A98)*(Plantillas!$G$2:$G$114*N(L$6)+Plantillas!$H$2:$H$114))) -> 5 | ... R98: =IF(R$5="",0,SUMPRODUCT((Plantillas!$A$2:$A$114=R$5)*(Plantillas!$D$2:$D$114=$A98)*(Plantillas!$G$2:$G$114*N(R$6)+Plantillas!$H$2:$H$114))) -> 0 | S98: =SUM(E98:R98) -> 7 | T98: =IF(INDEX(Partidas!$F$2:$F$99,MATCH(A98,Partidas!$A$2:$A$99,0))="","",INDEX(Partidas!$F$2:$F$99,MATCH(A98,Partidas!$A$2:$A$99,0))) -> 45 | U98: =IF(T98="",0,S98*T98) -> 315
A99: ELE-100 | B99: ELE | C99: =INDEX(Partidas!$D$2:$D$99,MATCH(A99,Partidas!$A$2:$A$99,0)) -> Mecanismo de persiana motorizada | D99: =INDEX(Partidas!$C$2:$C$99,MATCH(A99,Partidas!$A$2:$A$99,0)) -> ud | E99: =IF(E$5="",0,SUMPRODUCT((Plantillas!$A$2:$A$114=E$5)*(Plantillas!$D$2:$D$114=$A99)*(Plantillas!$G$2:$G$114*N(E$6)+Plantillas!$H$2:$H$114))) -> 0 | F99: =IF(F$5="",0,SUMPRODUCT((Plantillas!$A$2:$A$114=F$5)*(Plantillas!$D$2:$D$114=$A99)*(Plantillas!$G$2:$G$114*N(F$6)+Plantillas!$H$2:$H$114))) -> 0 | G99: =IF(G$5="",0,SUMPRODUCT((Plantillas!$A$2:$A$114=G$5)*(Plantillas!$D$2:$D$114=$A99)*(Plantillas!$G$2:$G$114*N(G$6)+Plantillas!$H$2:$H$114))) -> 0 | H99: =IF(H$5="",0,SUMPRODUCT((Plantillas!$A$2:$A$114=H$5)*(Plantillas!$D$2:$D$114=$A99)*(Plantillas!$G$2:$G$114*N(H$6)+Plantillas!$H$2:$H$114))) -> 0 | I99: =IF(I$5="",0,SUMPRODUCT((Plantillas!$A$2:$A$114=I$5)*(Plantillas!$D$2:$D$114=$A99)*(Plantillas!$G$2:$G$114*N(I$6)+Plantillas!$H$2:$H$114))) -> 0 | J99: =IF(J$5="",0,SUMPRODUCT((Plantillas!$A$2:$A$114=J$5)*(Plantillas!$D$2:$D$114=$A99)*(Plantillas!$G$2:$G$114*N(J$6)+Plantillas!$H$2:$H$114))) -> 0 | K99: =IF(K$5="",0,SUMPRODUCT((Plantillas!$A$2:$A$114=K$5)*(Plantillas!$D$2:$D$114=$A99)*(Plantillas!$G$2:$G$114*N(K$6)+Plantillas!$H$2:$H$114))) -> 0 | L99: =IF(L$5="",0,SUMPRODUCT((Plantillas!$A$2:$A$114=L$5)*(Plantillas!$D$2:$D$114=$A99)*(Plantillas!$G$2:$G$114*N(L$6)+Plantillas!$H$2:$H$114))) -> 0 | ... R99: =IF(R$5="",0,SUMPRODUCT((Plantillas!$A$2:$A$114=R$5)*(Plantillas!$D$2:$D$114=$A99)*(Plantillas!$G$2:$G$114*N(R$6)+Plantillas!$H$2:$H$114))) -> 0 | S99: =SUM(E99:R99) -> 0 | T99: =IF(INDEX(Partidas!$F$2:$F$99,MATCH(A99,Partidas!$A$2:$A$99,0))="","",INDEX(Partidas!$F$2:$F$99,MATCH(A99,Partidas!$A$2:$A$99,0))) -> 45 | U99: =IF(T99="",0,S99*T99) -> 0
A100: ELE-110 | B100: ELE | C100: =INDEX(Partidas!$D$2:$D$99,MATCH(A100,Partidas!$A$2:$A$99,0)) -> Timbre | D100: =INDEX(Partidas!$C$2:$C$99,MATCH(A100,Partidas!$A$2:$A$99,0)) -> ud | E100: =IF(E$5="",0,SUMPRODUCT((Plantillas!$A$2:$A$114=E$5)*(Plantillas!$D$2:$D$114=$A100)*(Plantillas!$G$2:$G$114*N(E$6)+Plantillas!$H$2:$H$114))) -> 1 | F100: =IF(F$5="",0,SUMPRODUCT((Plantillas!$A$2:$A$114=F$5)*(Plantillas!$D$2:$D$114=$A100)*(Plantillas!$G$2:$G$114*N(F$6)+Plantillas!$H$2:$H$114))) -> 0 | G100: =IF(G$5="",0,SUMPRODUCT((Plantillas!$A$2:$A$114=G$5)*(Plantillas!$D$2:$D$114=$A100)*(Plantillas!$G$2:$G$114*N(G$6)+Plantillas!$H$2:$H$114))) -> 0 | H100: =IF(H$5="",0,SUMPRODUCT((Plantillas!$A$2:$A$114=H$5)*(Plantillas!$D$2:$D$114=$A100)*(Plantillas!$G$2:$G$114*N(H$6)+Plantillas!$H$2:$H$114))) -> 0 | I100: =IF(I$5="",0,SUMPRODUCT((Plantillas!$A$2:$A$114=I$5)*(Plantillas!$D$2:$D$114=$A100)*(Plantillas!$G$2:$G$114*N(I$6)+Plantillas!$H$2:$H$114))) -> 0 | J100: =IF(J$5="",0,SUMPRODUCT((Plantillas!$A$2:$A$114=J$5)*(Plantillas!$D$2:$D$114=$A100)*(Plantillas!$G$2:$G$114*N(J$6)+Plantillas!$H$2:$H$114))) -> 0 | K100: =IF(K$5="",0,SUMPRODUCT((Plantillas!$A$2:$A$114=K$5)*(Plantillas!$D$2:$D$114=$A100)*(Plantillas!$G$2:$G$114*N(K$6)+Plantillas!$H$2:$H$114))) -> 0 | L100: =IF(L$5="",0,SUMPRODUCT((Plantillas!$A$2:$A$114=L$5)*(Plantillas!$D$2:$D$114=$A100)*(Plantillas!$G$2:$G$114*N(L$6)+Plantillas!$H$2:$H$114))) -> 0 | ... R100: =IF(R$5="",0,SUMPRODUCT((Plantillas!$A$2:$A$114=R$5)*(Plantillas!$D$2:$D$114=$A100)*(Plantillas!$G$2:$G$114*N(R$6)+Plantillas!$H$2:$H$114))) -> 0 | S100: =SUM(E100:R100) -> 1 | T100: =IF(INDEX(Partidas!$F$2:$F$99,MATCH(A100,Partidas!$A$2:$A$99,0))="","",INDEX(Partidas!$F$2:$F$99,MATCH(A100,Partidas!$A$2:$A$99,0))) -> 65 | U100: =IF(T100="",0,S100*T100) -> 65
A101: ELE-120 | B101: ELE | C101: =INDEX(Partidas!$D$2:$D$99,MATCH(A101,Partidas!$A$2:$A$99,0)) -> Videoportero, terminal interior | D101: =INDEX(Partidas!$C$2:$C$99,MATCH(A101,Partidas!$A$2:$A$99,0)) -> ud | E101: =IF(E$5="",0,SUMPRODUCT((Plantillas!$A$2:$A$114=E$5)*(Plantillas!$D$2:$D$114=$A101)*(Plantillas!$G$2:$G$114*N(E$6)+Plantillas!$H$2:$H$114))) -> 0 | F101: =IF(F$5="",0,SUMPRODUCT((Plantillas!$A$2:$A$114=F$5)*(Plantillas!$D$2:$D$114=$A101)*(Plantillas!$G$2:$G$114*N(F$6)+Plantillas!$H$2:$H$114))) -> 0 | G101: =IF(G$5="",0,SUMPRODUCT((Plantillas!$A$2:$A$114=G$5)*(Plantillas!$D$2:$D$114=$A101)*(Plantillas!$G$2:$G$114*N(G$6)+Plantillas!$H$2:$H$114))) -> 0 | H101: =IF(H$5="",0,SUMPRODUCT((Plantillas!$A$2:$A$114=H$5)*(Plantillas!$D$2:$D$114=$A101)*(Plantillas!$G$2:$G$114*N(H$6)+Plantillas!$H$2:$H$114))) -> 0 | I101: =IF(I$5="",0,SUMPRODUCT((Plantillas!$A$2:$A$114=I$5)*(Plantillas!$D$2:$D$114=$A101)*(Plantillas!$G$2:$G$114*N(I$6)+Plantillas!$H$2:$H$114))) -> 0 | J101: =IF(J$5="",0,SUMPRODUCT((Plantillas!$A$2:$A$114=J$5)*(Plantillas!$D$2:$D$114=$A101)*(Plantillas!$G$2:$G$114*N(J$6)+Plantillas!$H$2:$H$114))) -> 0 | K101: =IF(K$5="",0,SUMPRODUCT((Plantillas!$A$2:$A$114=K$5)*(Plantillas!$D$2:$D$114=$A101)*(Plantillas!$G$2:$G$114*N(K$6)+Plantillas!$H$2:$H$114))) -> 0 | L101: =IF(L$5="",0,SUMPRODUCT((Plantillas!$A$2:$A$114=L$5)*(Plantillas!$D$2:$D$114=$A101)*(Plantillas!$G$2:$G$114*N(L$6)+Plantillas!$H$2:$H$114))) -> 0 | ... R101: =IF(R$5="",0,SUMPRODUCT((Plantillas!$A$2:$A$114=R$5)*(Plantillas!$D$2:$D$114=$A101)*(Plantillas!$G$2:$G$114*N(R$6)+Plantillas!$H$2:$H$114))) -> 0 | S101: =SUM(E101:R101) -> 0 | T101: =IF(INDEX(Partidas!$F$2:$F$99,MATCH(A101,Partidas!$A$2:$A$99,0))="","",INDEX(Partidas!$F$2:$F$99,MATCH(A101,Partidas!$A$2:$A$99,0))) | U101: =IF(T101="",0,S101*T101) -> 0
A102: ELE-130 | B102: ELE | C102: =INDEX(Partidas!$D$2:$D$99,MATCH(A102,Partidas!$A$2:$A$99,0)) -> Detector de humo autónomo | D102: =INDEX(Partidas!$C$2:$C$99,MATCH(A102,Partidas!$A$2:$A$99,0)) -> ud | E102: =IF(E$5="",0,SUMPRODUCT((Plantillas!$A$2:$A$114=E$5)*(Plantillas!$D$2:$D$114=$A102)*(Plantillas!$G$2:$G$114*N(E$6)+Plantillas!$H$2:$H$114))) -> 2 | F102: =IF(F$5="",0,SUMPRODUCT((Plantillas!$A$2:$A$114=F$5)*(Plantillas!$D$2:$D$114=$A102)*(Plantillas!$G$2:$G$114*N(F$6)+Plantillas!$H$2:$H$114))) -> 0 | G102: =IF(G$5="",0,SUMPRODUCT((Plantillas!$A$2:$A$114=G$5)*(Plantillas!$D$2:$D$114=$A102)*(Plantillas!$G$2:$G$114*N(G$6)+Plantillas!$H$2:$H$114))) -> 0 | H102: =IF(H$5="",0,SUMPRODUCT((Plantillas!$A$2:$A$114=H$5)*(Plantillas!$D$2:$D$114=$A102)*(Plantillas!$G$2:$G$114*N(H$6)+Plantillas!$H$2:$H$114))) -> 0 | I102: =IF(I$5="",0,SUMPRODUCT((Plantillas!$A$2:$A$114=I$5)*(Plantillas!$D$2:$D$114=$A102)*(Plantillas!$G$2:$G$114*N(I$6)+Plantillas!$H$2:$H$114))) -> 0 | J102: =IF(J$5="",0,SUMPRODUCT((Plantillas!$A$2:$A$114=J$5)*(Plantillas!$D$2:$D$114=$A102)*(Plantillas!$G$2:$G$114*N(J$6)+Plantillas!$H$2:$H$114))) -> 0 | K102: =IF(K$5="",0,SUMPRODUCT((Plantillas!$A$2:$A$114=K$5)*(Plantillas!$D$2:$D$114=$A102)*(Plantillas!$G$2:$G$114*N(K$6)+Plantillas!$H$2:$H$114))) -> 0 | L102: =IF(L$5="",0,SUMPRODUCT((Plantillas!$A$2:$A$114=L$5)*(Plantillas!$D$2:$D$114=$A102)*(Plantillas!$G$2:$G$114*N(L$6)+Plantillas!$H$2:$H$114))) -> 0 | ... R102: =IF(R$5="",0,SUMPRODUCT((Plantillas!$A$2:$A$114=R$5)*(Plantillas!$D$2:$D$114=$A102)*(Plantillas!$G$2:$G$114*N(R$6)+Plantillas!$H$2:$H$114))) -> 0 | S102: =SUM(E102:R102) -> 2 | T102: =IF(INDEX(Partidas!$F$2:$F$99,MATCH(A102,Partidas!$A$2:$A$99,0))="","",INDEX(Partidas!$F$2:$F$99,MATCH(A102,Partidas!$A$2:$A$99,0))) | U102: =IF(T102="",0,S102*T102) -> 0
...
